Workbook
Name Slicer_Country: #N/A
Name Slicer_Income_Level: #N/A
Name Slicer_Income_Level1: #N/A
Name Slicer_Income_Level2: #N/A
Name Slicer_Income_Level3: #N/A
Name Slicer_Income_Level4: #N/A
Name Slicer_Region: #N/A
Name Slicer_Region1: #N/A
Name Slicer_Region2: #N/A
Name Slicer_Region3: #N/A
Name Slicer_Region4: #N/A
Name Slicer_Year: #N/A
Name Slicer_Year1: #N/A
Name Slicer_Year2: #N/A
Name Slicer_Year3: #N/A

Sheet IncomeLevel_Cleaned
A1: Country Name | B1: Country Code | C1: 1960 | D1: 1961 | E1: 1962 | F1: 1963 | G1: 1964 | H1: 1965 | I1: 1966 | J1: 1967 | K1: 1968 | L1: 1969 | M1: 1970 | N1: 1971 | O1: 1972 | P1: 1973 | Q1: 1974 | R1: 1975 | S1: 1976 | T1: 1977 | U1: 1978 | V1: 1979 | W1: 1980 | X1: 1981 | Y1: 1982 | Z1: 1983 | AA1: 1984 | AB1: 1985 | AC1: 1986 | AD1: 1987 | AE1: 1988 | AF1: 1989 | AG1: 1990 | AH1: 1991 | AI1: 1992 | AJ1: 1993 | AK1: 1994 | AL1: 1995 | AM1: 1996 | AN1: 1997 | AO1: 1998 | AP1: 1999 | AQ1: 2000 | AR1: 2001 | AS1: 2002 | AT1: 2003 | AU1: 2004 | AV1: 2005 | AW1: 2006 | AX1: 2007 | AY1: 2008 | AZ1: 2009 | BA1: 2010 | BB1: 2011 | BC1: 2012 | BD1: 2013 | BE1: 2014 | BF1: 2015 | BG1: 2016 | BH1: 2017 | BI1: 2018 | BJ1: 2019 | BK1: 2020 | BL1: 2021 | BM1: 2022 | BN1: 2023 | BO1: 2024 | BP1: ABW | BQ1: Region | BR1: Income | BS1: Country
A2: Aruba | B2: ABW | C2: 64.049 | D2: 64.215 | E2: 64.602 | F2: 64.944 | G2: 65.303 | H2: 65.615 | I2: 66.126 | J2: 66.385 | K2: 66.744 | L2: 67.098 | M2: 67.44 | N2: 67.783 | O2: 68.335 | P2: 68.862 | Q2: 69.278 | R2: 69.564 | S2: 69.808 | T2: 70.054 | U2: 70.271 | V2: 70.507 | W2: 70.771 | X2: 71.344 | Y2: 71.485 | Z2: 71.606 | AA2: 71.711 | AB2: 71.792 | AC2: 71.831 | AD2: 72.448 | AE2: 72.519 | AF2: 72.531 | AG2: 72.546 | AH2: 72.592 | AI2: 72.717 | AJ2: 72.777 | AK2: 72.796 | AL2: 72.832 | AM2: 72.856 | AN2: 72.904 | AO2: 72.94 | AP2: 72.857 | AQ2: 72.939 | AR2: 73.044 | AS2: 73.135 | AT2: 73.236 | AU2: 73.223 | AV2: 73.415 | AW2: 73.498 | AX2: 73.642 | AY2: 73.783 | AZ2: 73.974 | BA2: 74.297 | BB2: 74.578 | BC2: 74.841 | BD2: 75.072 | BE2: 75.261 | BF2: 75.405 | BG2: 75.54 | BH2: 75.62 | BI2: 75.88 | BJ2: 76.019 | BK2: 75.406 | BL2: 73.655 | BM2: 76.226 | BN2: 76.353 | BO2: 76.5
A3: Africa Eastern and Southern | B3: AFE | C3: 44.169658 | D3: 44.468838 | E3: 44.87789 | F3: 45.160583 | G3: 45.535695 | H3: 45.770723 | I3: 45.765725 | J3: 46.440745 | K3: 46.738632 | L3: 46.977476 | M3: 47.248006 | N3: 47.464016 | O3: 47.166792 | P3: 47.746608 | Q3: 47.744328 | R3: 47.968548 | S3: 48.568138 | T3: 48.860725 | U3: 48.983917 | V3: 49.416988 | W3: 49.816713 | X3: 50.020493 | Y3: 50.290829 | Z3: 48.904096 | AA3: 48.997959 | AB3: 49.392902 | AC3: 50.009761 | AD3: 51.068943 | AE3: 50.876607 | AF3: 51.265874 | AG3: 51.096326 | AH3: 50.873244 | AI3: 50.715946 | AJ3: 51.073762 | AK3: 50.966589 | AL3: 51.482057 | AM3: 51.35319 | AN3: 51.570887 | AO3: 51.317955 | AP3: 51.807077 | AQ3: 52.557342 | AR3: 52.875536 | AS3: 53.206744 | AT3: 53.678305 | AU3: 54.192928 | AV3: 54.807681 | AW3: 55.693515 | AX3: 56.484353 | AY3: 57.240106 | AZ3: 58.095527 | BA3: 58.827279 | BB3: 59.200004 | BC3: 60.249512 | BD3: 60.89574 | BE3: 61.251436 | BF3: 61.713031 | BG3: 62.167981 | BH3: 62.591275 | BI3: 63.330691 | BJ3: 63.857261 | BK3: 63.766484 | BL3: 62.979999 | BM3: 64.487152 | BN3: 65.146228 | BO3: 65.34993 | BP3: AFE | BS3: Africa Eastern and Southern
A4: Afghanistan | B4: AFG | C4: 32.799 | D4: 33.291 | E4: 33.757 | F4: 34.201 | G4: 34.673 | H4: 35.124 | I4: 35.583 | J4: 36.042 | K4: 36.51 | L4: 36.979 | M4: 37.46 | N4: 37.932 | O4: 38.423 | P4: 38.951 | Q4: 39.469 | R4: 39.994 | S4: 40.518 | T4: 41.082 | U4: 40.086 | V4: 38.844 | W4: 39.258 | X4: 39.406 | Y4: 36.058 | Z4: 36.517 | AA4: 31.473 | AB4: 32.132 | AC4: 38.4 | AD4: 38.831 | AE4: 43.238 | AF4: 44.496 | AG4: 45.118 | AH4: 45.521 | AI4: 46.569 | AJ4: 51.021 | AK4: 50.969 | AL4: 52.103 | AM4: 52.83 | AN4: 53.212 | AO4: 52.487 | AP4: 54.532 | AQ4: 55.005 | AR4: 55.511 | AS4: 56.225 | AT4: 57.171 | AU4: 57.81 | AV4: 58.247 | AW4: 58.553 | AX4: 58.956 | AY4: 59.708 | AZ4: 60.248 | BA4: 60.702 | BB4: 61.25 | BC4: 61.735 | BD4: 62.188 | BE4: 62.26 | BF4: 62.27 | BG4: 62.646 | BH4: 62.406 | BI4: 62.443 | BJ4: 62.941 | BK4: 61.454 | BL4: 60.417 | BM4: 65.617 | BN4: 66.035 | BO4: 66.289 | BP4: AFG | BQ4: Middle East & North Africa | BR4: Low income | BS4: Afghanistan
A5: Africa Western and Central | B5: AFW | C5: 37.779636 | D5: 38.058973 | E5: 38.681792 | F5: 38.936918 | G5: 39.19458 | H5: 39.479784 | I5: 39.719265 | J5: 39.529359 | K5: 40.25889 | L5: 40.567814 | M5: 41.277939 | N5: 41.730102 | O5: 42.356132 | P5: 42.868104 | Q5: 43.437155 | R5: 43.967079 | S5: 44.75257 | T5: 45.362264 | U5: 45.876278 | V5: 46.328507 | W5: 46.696229 | X5: 47.075219 | Y5: 47.373942 | Z5: 47.619559 | AA5: 47.797646 | AB5: 47.944482 | AC5: 48.038163 | AD5: 48.139567 | AE5: 48.371525 | AF5: 48.496155 | AG5: 48.459467 | AH5: 48.531229 | AI5: 48.688726 | AJ5: 48.855051 | AK5: 48.859717 | AL5: 49.027301 | AM5: 49.11178 | AN5: 49.21897 | AO5: 49.45259 | AP5: 49.823913 | AQ5: 50.29817 | AR5: 50.677996 | AS5: 51.108247 | AT5: 51.578364 | AU5: 52.106342 | AV5: 52.55603 | AW5: 52.978931 | AX5: 53.482672 | AY5: 53.916483 | AZ5: 53.852486 | BA5: 54.603593 | BB5: 54.964195 | BC5: 55.292945 | BD5: 55.55511 | BE5: 55.69563 | BF5: 56.038519 | BG5: 56.392598 | BH5: 56.626622 | BI5: 57.037104 | BJ5: 57.149956 | BK5: 57.364736 | BL5: 57.362736 | BM5: 57.98785 | BN5: 58.85574 | BO5: 59.049811 | BP5: AFW | BS5: Africa Western and Central
A6: Angola | B6: AGO | C6: 37.933 | D6: 36.902 | E6: 37.168 | F6: 37.419 | G6: 37.704 | H6: 37.968 | I6: 38.258 | J6: 38.616 | K6: 38.968 | L6: 39.329 | M6: 39.688 | N6: 40.076 | O6: 40.469 | P6: 40.871 | Q6: 41.26 | R6: 40.817 | S6: 40.812 | T6: 41.215 | U6: 41.573 | V6: 41.913 | W6: 42.242 | X6: 42.556 | Y6: 42.857 | Z6: 41.972 | AA6: 42.245 | AB6: 42.495 | AC6: 42.739 | AD6: 40.786 | AE6: 41.471 | AF6: 41.698 | AG6: 41.854 | AH6: 43.812 | AI6: 42.267 | AJ6: 42.19 | AK6: 43.567 | AL6: 46.139 | AM6: 46.418 | AN6: 46.688 | AO6: 45.452 | AP6: 45.808 | AQ6: 46.501 | AR6: 47.032 | AS6: 47.874 | AT6: 50.218 | AU6: 51.123 | AV6: 52.13 | AW6: 52.965 | AX6: 54.2 | AY6: 55.281 | AZ6: 56.225 | BA6: 57.242 | BB6: 58.093 | BC6: 58.916 | BD6: 59.705 | BE6: 60.396 | BF6: 61.042 | BG6: 61.619 | BH6: 62.122 | BI6: 62.622 | BJ6: 63.051 | BK6: 63.116 | BL6: 62.958 | BM6: 64.246 | BN6: 64.617 | BO6: 64.805 | BP6: AGO | BQ6: Sub-Saharan Africa | BR6: Lower middle income | BS6: Angola
A7: Albania | B7: ALB | C7: 56.413 | D7: 57.488 | E7: 58.494 | F7: 59.479 | G7: 60.404 | H7: 61.273 | I7: 62.149 | J7: 62.976 | K7: 63.788 | L7: 64.538 | M7: 65.234 | N7: 65.896 | O7: 66.526 | P7: 67.107 | Q7: 67.633 | R7: 68.12 | S7: 68.57 | T7: 68.992 | U7: 69.367 | V7: 69.617 | W7: 69.903 | X7: 70.145 | Y7: 70.425 | Z7: 70.705 | AA7: 70.984 | AB7: 71.282 | AC7: 71.665 | AD7: 71.981 | AE7: 72.217 | AF7: 72.457 | AG7: 72.71 | AH7: 73.001 | AI7: 73.303 | AJ7: 73.638 | AK7: 73.837 | AL7: 74.022 | AM7: 74.113 | AN7: 73.383 | AO7: 74.357 | AP7: 74.568 | AQ7: 74.826 | AR7: 75.083 | AS7: 75.299 | AT7: 75.557 | AU7: 75.951 | AV7: 76.427 | AW7: 76.994 | AX7: 77.691 | AY7: 78.248 | AZ7: 78.509 | BA7: 78.414 | BB7: 78.303 | BC7: 78.084 | BD7: 77.995 | BE7: 78.029 | BF7: 78.358 | BG7: 78.643 | BH7: 78.9 | BI7: 79.238 | BJ7: 79.467 | BK7: 77.824 | BL7: 76.844 | BM7: 78.769 | BN7: 79.602 | BO7: 79.776 | BP7: ALB | BQ7: Europe & Central Asia | BR7: Upper middle income | BS7: Albania
A8: Andorra | B8: AND | C8: 72.094 | D8: 72.573 | E8: 72.993 | F8: 73.298 | G8: 73.624 | H8: 73.856 | I8: 74.02 | J8: 74.119 | K8: 74.22 | L8: 74.296 | M8: 74.452 | N8: 74.615 | O8: 74.864 | P8: 75.096 | Q8: 75.34 | R8: 75.567 | S8: 75.869 | T8: 76.154 | U8: 76.488 | V8: 76.819 | W8: 77.137 | X8: 77.391 | Y8: 77.617 | Z8: 77.787 | AA8: 77.916 | AB8: 78.006 | AC8: 78.107 | AD8: 78.189 | AE8: 78.364 | AF8: 78.557 | AG8: 78.961 | AH8: 79.346 | AI8: 79.794 | AJ8: 80.186 | AK8: 80.587 | AL8: 80.804 | AM8: 81.009 | AN8: 81.145 | AO8: 81.28 | AP8: 81.55 | AQ8: 81.863 | AR8: 82.162 | AS8: 82.448 | AT8: 82.718 | AU8: 82.815 | AV8: 83.086 | AW8: 83.374 | AX8: 83.632 | AY8: 83.855 | AZ8: 84.1 | BA8: 84.197 | BB8: 84.296 | BC8: 84.334 | BD8: 84.406 | BE8: 84.485 | BF8: 84.532 | BG8: 84.489 | BH8: 84.359 | BI8: 84.242 | BJ8: 84.098 | BK8: 79.418 | BL8: 82.331 | BM8: 84.016 | BN8: 84.041 | BO8: 84.188 | BP8: AND | BQ8: Europe & Central Asia | BR8: High income | BS8: Andorra
A9: Arab World | B9: ARB | C9: 44.794056 | D9: 45.545371 | E9: 45.993769 | F9: 46.979338 | G9: 47.570034 | H9: 48.117159 | I9: 48.625424 | J9: 49.092434 | K9: 49.657787 | L9: 50.148857 | M9: 50.692871 | N9: 51.318319 | O9: 51.89371 | P9: 52.30196 | Q9: 52.92555 | R9: 53.420351 | S9: 53.850649 | T9: 55.081922 | U9: 55.757128 | V9: 56.479748 | W9: 57.006353 | X9: 57.569166 | Y9: 57.870235 | Z9: 58.637607 | AA9: 59.329582 | AB9: 59.989461 | AC9: 60.918684 | AD9: 61.620809 | AE9: 61.671533 | AF9: 62.298247 | AG9: 62.755973 | AH9: 62.827507 | AI9: 63.575576 | AJ9: 64.60128 | AK9: 64.850083 | AL9: 65.202506 | AM9: 65.526889 | AN9: 65.852992 | AO9: 66.193579 | AP9: 66.549934 | AQ9: 66.8907 | AR9: 67.240617 | AS9: 67.58063 | AT9: 67.650335 | AU9: 67.733103 | AV9: 68.040502 | AW9: 68.491265 | AX9: 68.879226 | AY9: 69.258133 | AZ9: 69.706904 | BA9: 69.807322 | BB9: 69.363338 | BC9: 69.842317 | BD9: 70.192106 | BE9: 70.535067 | BF9: 70.658012 | BG9: 70.896488 | BH9: 71.112856 | BI9: 71.4313 | BJ9: 71.839893 | BK9: 70.726559 | BL9: 70.404114 | BM9: 71.876096 | BN9: 72.444678 | BO9: 72.721805 | BP9: ARB | BS9: Arab World
A10: United Arab Emirates | B10: ARE | C10: 50.651 | D10: 51.596 | E10: 52.546 | F10: 53.509 | G10: 54.495 | H10: 55.512 | I10: 56.572 | J10: 57.648 | K10: 58.727 | L10: 59.764 | M10: 60.78 | N10: 61.753 | O10: 62.675 | P10: 63.542 | Q10: 64.351 | R10: 65.105 | S10: 65.806 | T10: 66.471 | U10: 67.083 | V10: 67.645 | W10: 68.157 | X10: 68.622 | Y10: 69.056 | Z10: 69.448 | AA10: 69.802 | AB10: 70.123 | AC10: 70.41 | AD10: 70.623 | AE10: 70.808 | AF10: 70.96 | AG10: 71.074 | AH10: 71.144 | AI10: 71.166 | AJ10: 71.159 | AK10: 71.204 | AL10: 71.392 | AM10: 71.82 | AN10: 72.559 | AO10: 73.66 | AP10: 74.982 | AQ10: 76.347 | AR10: 77.621 | AS10: 78.721 | AT10: 79.6 | AU10: 80.272 | AV10: 80.779 | AW10: 81.155 | AX10: 81.438 | AY10: 81.591 | AZ10: 81.679 | BA10: 81.886 | BB10: 81.898 | BC10: 81.913 | BD10: 81.95 | BE10: 81.99 | BF10: 82.076 | BG10: 82.195 | BH10: 82.388 | BI10: 82.449 | BJ10: 82.596 | BK10: 81.936 | BL10: 79.083 | BM10: 80.487 | BN10: 82.909 | BO10: 83.069 | BP10: ARE | BQ10: Middle East & North Africa | BR10: High income | BS10: United Arab Emirates
A11: Argentina | B11: ARG | C11: 64.242 | D11: 64.631 | E11: 64.618 | F11: 64.855 | G11: 64.816 | H11: 65.053 | I11: 65.398 | J11: 65.467 | K11: 65.234 | L11: 65.085 | M11: 65.647 | N11: 65.619 | O11: 65.953 | P11: 66.186 | Q11: 66.405 | R11: 66.965 | S11: 67.03 | T11: 67.595 | U11: 67.999 | V11: 68.434 | W11: 68.576 | X11: 68.858 | Y11: 68.973 | Z11: 69.29 | AA11: 69.353 | AB11: 69.879 | AC11: 70.281 | AD11: 70.699 | AE11: 71.097 | AF11: 71.502 | AG11: 71.615 | AH11: 72.02 | AI11: 72.096 | AJ11: 72.303 | AK11: 72.732 | AL11: 72.864 | AM11: 73.056 | AN11: 73.407 | AO11: 73.412 | AP11: 73.683 | AQ11: 73.91 | AR11: 74.154 | AS11: 74.312 | AT11: 74.307 | AU11: 74.871 | AV11: 75.231 | AW11: 75.279 | AX11: 74.783 | AY11: 75.428 | AZ11: 75.577 | BA11: 75.68 | BB11: 76.1 | BC11: 75.802 | BD11: 75.829 | BE11: 76.268 | BF11: 76.6 | BG11: 76.105 | BH11: 76.543 | BI11: 76.77 | BJ11: 76.847 | BK11: 75.878 | BL11: 73.948 | BM11: 75.806 | BN11: 77.395 | BO11: 77.543 | BP11: ARG | BQ11: Latin America & Caribbean | BR11: Upper middle income | BS11: Argentina
A12: Armenia | B12: ARM | C12: 59.063 | D12: 59.494098 | E12: 59.916683 | F12: 60.328268 | G12: 60.723829 | H12: 61.099341 | I12: 61.453829 | J12: 61.784756 | K12: 62.093634 | L12: 62.379951 | M12: 62.644707 | N12: 62.888902 | O12: 63.114488 | P12: 63.330927 | Q12: 63.546756 | R12: 63.767878 | S12: 64.001488 | T12: 64.253951 | U12: 64.526195 | V12: 64.820829 | W12: 65.138561 | X12: 65.482488 | Y12: 65.850927 | Z12: 66.229244 | AA12: 66.591366 | AB12: 66.915268 | AC12: 67.178 | AD12: 67.359073 | AE12: 52.600122 | AF12: 67.518561 | AG12: 67.549366 | AH12: 67.627049 | AI12: 67.718537 | AJ12: 67.973195 | AK12: 68.271805 | AL12: 68.628488 | AM12: 69.006122 | AN12: 69.393829 | AO12: 69.799341 | AP12: 70.198951 | AQ12: 72.880488 | AR12: 72.97561 | AS12: 72.826829 | AT12: 72.826829 | AU12: 73.026829 | AV12: 73.07561 | AW12: 72.82439 | AX12: 72.873171 | AY12: 73.073171 | AZ12: 73.073171 | BA12: 73.173171 | BB12: 73.817073 | BC12: 74.119512 | BD12: 74.621951 | BE12: 74.873171 | BF12: 74.870732 | BG12: 74.868293 | BH12: 75.217073 | BI12: 75.619512 | BJ12: 76.221951 | BK12: 73.37561 | BL12: 72.278049 | BM12: 74.765854 | BN12: 77.465854 | BO12: 78.319512 | BP12: ARM | BQ12: Europe & Central Asia | BR12: Upper middle income | BS12: Armenia
A13: American Samoa | B13: ASM | C13: 65.053 | D13: 65.648 | E13: 66.008 | F13: 66.161 | G13: 66.135 | H13: 65.996 | I13: 58.284 | J13: 65.807 | K13: 65.847 | L13: 66.05 | M13: 66.364 | N13: 66.77 | O13: 67.186 | P13: 67.604 | Q13: 67.95 | R13: 68.256 | S13: 68.475 | T13: 68.701 | U13: 68.881 | V13: 69.114 | W13: 69.413 | X13: 69.731 | Y13: 69.975 | Z13: 70.163 | AA13: 70.326 | AB13: 70.532 | AC13: 70.704 | AD13: 70.828 | AE13: 70.883 | AF13: 70.929 | AG13: 71.107 | AH13: 71.312 | AI13: 71.511 | AJ13: 71.54 | AK13: 71.569 | AL13: 71.565 | AM13: 71.576 | AN13: 71.606 | AO13: 71.542 | AP13: 71.484 | AQ13: 71.443 | AR13: 71.573 | AS13: 71.755 | AT13: 71.698 | AU13: 72.277 | AV13: 72.382 | AW13: 72.397 | AX13: 72.365 | AY13: 72.43 | AZ13: 70.839 | BA13: 72.587 | BB13: 72.662 | BC13: 72.709 | BD13: 72.769 | BE13: 72.687 | BF13: 72.654 | BG13: 72.64 | BH13: 72.801 | BI13: 72.794 | BJ13: 72.751 | BK13: 72.672 | BL13: 72.708 | BM13: 72.752 | BN13: 72.852 | BO13: 72.992 | BP13: ASM | BQ13: East Asia & Pacific | BR13: High income | BS13: American Samoa
A14: Antigua and Barbuda | B14: ATG | C14: 62.635 | D14: 63.335 | E14: 63.995 | F14: 64.697 | G14: 65.428 | H14: 66.171 | I14: 66.902 | J14: 67.586 | K14: 68.23 | L14: 68.827 | M14: 69.371 | N14: 69.861 | O14: 70.304 | P14: 70.71 | Q14: 71.095 | R14: 71.447 | S14: 71.794 | T14: 72.149 | U14: 72.5 | V14: 72.823 | W14: 73.094 | X14: 73.32 | Y14: 73.525 | Z14: 73.684 | AA14: 73.808 | AB14: 73.873 | AC14: 73.893 | AD14: 73.873 | AE14: 73.811 | AF14: 73.628 | AG14: 73.602 | AH14: 73.472 | AI14: 73.386 | AJ14: 73.39 | AK14: 73.493 | AL14: 73.576 | AM14: 73.839 | AN14: 74.045 | AO14: 74.187 | AP14: 74.456 | AQ14: 74.819 | AR14: 75.108 | AS14: 75.237 | AT14: 75.313 | AU14: 75.329 | AV14: 75.364 | AW14: 75.506 | AX14: 75.72 | AY14: 76.075 | AZ14: 76.386 | BA14: 76.701 | BB14: 77.023 | BC14: 77.1 | BD14: 77.05 | BE14: 76.912 | BF14: 76.892 | BG14: 76.968 | BH14: 77.03 | BI14: 77.132 | BJ14: 77.168 | BK14: 77.161 | BL14: 77.197 | BM14: 77.483 | BN14: 77.598 | BO14: 77.766 | BP14: ATG | BQ14: Latin America & Caribbean | BR14: High income | BS14: Antigua and Barbuda
A15: Australia | B15: AUS | C15: 70.817073 | D15: 70.973171 | E15: 70.942439 | F15: 70.911707 | G15: 70.880976 | H15: 70.850244 | I15: 70.819512 | J15: 70.869268 | K15: 70.919024 | L15: 70.96878 | M15: 71.018537 | N15: 71.068293 | O15: 71.457561 | P15: 71.846829 | Q15: 72.236098 | R15: 72.625366 | S15: 73.014634 | T15: 73.34439 | U15: 73.674146 | V15: 74.003902 | W15: 74.333659 | X15: 74.663415 | Y15: 74.904878 | Z15: 75.146341 | AA15: 75.387805 | AB15: 75.629268 | AC15: 75.870732 | AD15: 76.151707 | AE15: 76.432683 | AF15: 76.713659 | AG15: 76.994634 | AH15: 77.27561 | AI15: 77.378049 | AJ15: 77.878049 | AK15: 77.878049 | AL15: 77.829268 | AM15: 78.078049 | AN15: 78.480488 | AO15: 78.631707 | AP15: 78.931707 | AQ15: 79.234146 | AR15: 79.634146 | AS15: 79.936585 | AT15: 80.239024 | AU15: 80.490244 | AV15: 80.841463 | AW15: 81.041463 | AX15: 81.292683 | AY15: 81.395122 | AZ15: 81.543902 | BA15: 81.695122 | BB15: 81.895122 | BC15: 82.046341 | BD15: 82.14878 | BE15: 82.3 | BF15: 82.4 | BG15: 82.44878 | BH15: 82.5 | BI15: 82.74878 | BJ15: 82.9 | BK15: 83.2 | BL15: 83.3 | BM15: 83.2 | BN15: 83.05122 | BO15: 83.05122 | BP15: AUS | BQ15: East Asia & Pacific | BR15: High income | BS15: Australia
A16: Austria | B16: AUT | C16: 68.58561 | D16: 69.577317 | E16: 69.309512 | F16: 69.443659 | G16: 69.921951 | H16: 69.722195 | I16: 70.045854 | J16: 69.917805 | K16: 70.057561 | L16: 69.833171 | M16: 69.914634 | N16: 70.114634 | O16: 70.463415 | P16: 71.014634 | Q16: 71.012195 | R16: 71.114634 | S16: 71.565854 | T16: 71.914634 | U16: 72.012195 | V16: 72.312195 | W16: 72.463415 | X16: 72.812195 | Y16: 72.960976 | Z16: 73.012195 | AA16: 73.612195 | AB16: 73.814634 | AC16: 74.317073 | AD16: 74.768293 | AE16: 75.217073 | AF16: 75.265854 | AG16: 75.568293 | AH16: 75.617073 | AI16: 75.817073 | AJ16: 76.068293 | AK16: 76.419512 | AL16: 76.668293 | AM16: 76.870732 | AN16: 77.319512 | AO16: 77.670732 | AP16: 77.87561 | AQ16: 78.126829 | AR16: 78.57561 | AS16: 78.678049 | AT16: 78.631707 | AU16: 79.180488 | AV16: 79.331707 | AW16: 79.880488 | AX16: 80.180488 | AY16: 80.431707 | AZ16: 80.331707 | BA16: 80.580488 | BB16: 80.982927 | BC16: 80.936585 | BD16: 81.136585 | BE16: 81.490244 | BF16: 81.190244 | BG16: 81.641463 | BH16: 81.643902 | BI16: 81.692683 | BJ16: 81.895122 | BK16: 81.192683 | BL16: 81.190244 | BM16: 81.295122 | BN16: 81.792683 | BO16: 81.995122 | BP16: AUT | BQ16: Europe & Central Asia | BR16: High income | BS16: Austria
A17: Azerbaijan | B17: AZE | C17: 50.862 | D17: 51.435 | E17: 52.053 | F17: 52.696 | G17: 53.292 | H17: 53.884 | I17: 54.485 | J17: 55.032 | K17: 55.563 | L17: 56.08 | M17: 56.586 | N17: 57.043 | O17: 57.503 | P17: 57.926 | Q17: 58.332 | R17: 58.687 | S17: 59.477 | T17: 59.972 | U17: 60.494 | V17: 60.931 | W17: 61.433 | X17: 61.908 | Y17: 62.23 | Z17: 62.479 | AA17: 62.084 | AB17: 62.674 | AC17: 62.603 | AD17: 62.824 | AE17: 62.672 | AF17: 62.945 | AG17: 62.75 | AH17: 62.544 | AI17: 60.773 | AJ17: 61.426 | AK17: 60.277 | AL17: 61.931 | AM17: 62.66 | AN17: 62.953 | AO17: 63.75 | AP17: 64.733 | AQ17: 65.377 | AR17: 66.043 | AS17: 66.769 | AT17: 67.036 | AU17: 67.488 | AV17: 67.71 | AW17: 68.489 | AX17: 68.659 | AY17: 69.355 | AZ17: 69.874 | BA17: 70.309 | BB17: 70.565 | BC17: 71.08 | BD17: 71.485 | BE17: 71.93 | BF17: 72.349 | BG17: 72.568 | BH17: 72.694 | BI17: 73.016 | BJ17: 73.29 | BK17: 70.312 | BL17: 70.999 | BM17: 74.125 | BN17: 74.429 | BO17: 74.576 | BP17: AZE | BQ17: Europe & Central Asia | BR17: Upper middle income | BS17: Azerbaijan
A18: Burundi | B18: BDI | C18: 43.262 | D18: 43.364 | E18: 43.492 | F18: 43.559 | G18: 43.601 | H18: 41.844 | I18: 43.529 | J18: 43.332 | K18: 43.405 | L18: 43 | M18: 43.225 | N18: 43.172 | O18: 25.777 | P18: 37.409 | Q18: 43.337 | R18: 43.445 | S18: 43.691 | T18: 43.97 | U18: 44.404 | V18: 45.038 | W18: 45.731 | X18: 46.412 | Y18: 47.012 | Z18: 47.433 | AA18: 47.687 | AB18: 47.662 | AC18: 47.402 | AD18: 47.066 | AE18: 42.889 | AF18: 45.745 | AG18: 45.184 | AH18: 44.66 | AI18: 44.469 | AJ18: 37.221 | AK18: 44.515 | AL18: 44.589 | AM18: 44.807 | AN18: 45.721 | AO18: 46.678 | AP18: 47.627 | AQ18: 47.617 | AR18: 48.509 | AS18: 49.924 | AT18: 50.997 | AU18: 52.217 | AV18: 53.053 | AW18: 53.962 | AX18: 54.832 | AY18: 55.581 | AZ18: 56.422 | BA18: 57.088 | BB18: 57.804 | BC18: 58.501 | BD18: 59.179 | BE18: 59.764 | BF18: 60.107 | BG18: 60.789 | BH18: 61.345 | BI18: 61.806 | BJ18: 62.18 | BK18: 62.569 | BL18: 62.101 | BM18: 62.882 | BN18: 63.651 | BO18: 63.818 | BP18: BDI | BQ18: Sub-Saharan Africa | BR18: Low income | BS18: Burundi
A19: Belgium | B19: BEL | C19: 69.701951 | D19: 70.520976 | E19: 70.219512 | F19: 70.051463 | G19: 70.755122 | H19: 70.625366 | I19: 70.706341 | J19: 71.012927 | K19: 70.693171 | L19: 70.764878 | M19: 70.971951 | N19: 71.060488 | O19: 71.405122 | P19: 71.635366 | Q19: 71.985854 | R19: 71.97122 | S19: 72.119756 | T19: 72.773902 | U19: 72.698049 | V19: 73.193659 | W19: 73.207073 | X19: 73.621707 | Y19: 73.888049 | Z19: 73.869024 | AA19: 74.404878 | AB19: 74.520244 | AC19: 74.731707 | AD19: 75.365854 | AE19: 75.565854 | AF19: 75.632683 | AG19: 76.051951 | AH19: 76.192195 | AI19: 76.35122 | AJ19: 76.345366 | AK19: 76.691707 | AL19: 76.840732 | AM19: 77.187317 | AN19: 77.370732 | AO19: 77.473171 | AP19: 77.619512 | AQ19: 77.721951 | AR19: 77.973171 | AS19: 78.07561 | AT19: 78.129268 | AU19: 78.878049 | AV19: 78.980488 | AW19: 79.380488 | AX19: 79.782927 | AY19: 79.680488 | AZ19: 80.034146 | BA19: 80.182927 | BB19: 80.585366 | BC19: 80.385366 | BD19: 80.587805 | BE19: 81.287805 | BF19: 80.992683 | BG19: 81.439024 | BH19: 81.492683 | BI19: 81.595122 | BJ19: 81.995122 | BK19: 80.695122 | BL19: 81.790244 | BM19: 81.74878 | BN19: 82.4 | BO19: 82.3 | BP19: BEL | BQ19: Europe & Central Asia | BR19: High income | BS19: Belgium
A20: Benin | B20: BEN | C20: 38.775 | D20: 39.233 | E20: 39.643 | F20: 40.081 | G20: 40.502 | H20: 40.971 | I20: 41.274 | J20: 41.759 | K20: 42.182 | L20: 42.591 | M20: 43.029 | N20: 43.391 | O20: 43.928 | P20: 44.435 | Q20: 44.876 | R20: 45.405 | S20: 45.952 | T20: 46.504 | U20: 46.941 | V20: 47.362 | W20: 47.747 | X20: 48.122 | Y20: 48.493 | Z20: 48.845 | AA20: 49.399 | AB20: 49.959 | AC20: 50.632 | AD20: 51.258 | AE20: 52.019 | AF20: 52.45 | AG20: 53.02 | AH20: 53.441 | AI20: 54.137 | AJ20: 54.612 | AK20: 54.988 | AL20: 55.366 | AM20: 55.648 | AN20: 55.986 | AO20: 56.154 | AP20: 56.336 | AQ20: 56.594 | AR20: 56.654 | AS20: 56.851 | AT20: 57.092 | AU20: 57.346 | AV20: 57.738 | AW20: 57.966 | AX20: 58.249 | AY20: 58.099 | AZ20: 58.258 | BA20: 58.387 | BB20: 58.462 | BC20: 58.559 | BD20: 58.863 | BE20: 59.008 | BF20: 59.123 | BG20: 59.283 | BH20: 59.528 | BI20: 59.71 | BJ20: 59.888 | BK20: 60.154 | BL20: 59.61 | BM20: 60.475 | BN20: 60.774 | BO20: 60.961 | BP20: BEN | BQ20: Sub-Saharan Africa | BR20: Lower middle income | BS20: Benin
A21: Burkina Faso | B21: BFA | C21: 36.074 | D21: 36.361 | E21: 36.753 | F21: 37.093 | G21: 37.399 | H21: 37.758 | I21: 38.091 | J21: 38.432 | K21: 38.76 | L21: 39.023 | M21: 39.54 | N21: 39.853 | O21: 40.399 | P21: 40.947 | Q21: 41.711 | R21: 42.486 | S21: 43.327 | T21: 44.167 | U21: 44.995 | V21: 45.702 | W21: 46.465 | X21: 46.866 | Y21: 47.633 | Z21: 48.061 | AA21: 48.464 | AB21: 48.748 | AC21: 48.987 | AD21: 49.097 | AE21: 49.215 | AF21: 49.27 | AG21: 49.315 | AH21: 49.33 | AI21: 49.378 | AJ21: 49.412 | AK21: 49.469 | AL21: 49.554 | AM21: 49.693 | AN21: 49.56 | AO21: 50.163 | AP21: 50.463 | AQ21: 50.808 | AR21: 51.188 | AS21: 51.447 | AT21: 51.959 | AU21: 52.6 | AV21: 53.271 | AW21: 53.784 | AX21: 54.377 | AY21: 55.199 | AZ21: 55.791 | BA21: 56.343 | BB21: 57.001 | BC21: 57.457 | BD21: 57.903 | BE21: 58.331 | BF21: 58.778 | BG21: 59.173 | BH21: 59.578 | BI21: 59.972 | BJ21: 60.184 | BK21: 60.454 | BL21: 60.046 | BM21: 60.7 | BN21: 61.092 | BO21: 61.292 | BP21: BFA | BQ21: Sub-Saharan Africa | BR21: Low income | BS21: Burkina Faso
... A37: Canada | B37: CAN | C37: 71.133171 | D37: 71.346098 | E37: 71.367073 | F37: 71.380732 | G37: 71.776341 | H37: 71.872195 | I37: 72.00439 | J37: 72.207805 | K37: 72.353415 | L37: 72.501463 | M37: 72.700488 | N37: 73.029268 | O37: 72.933902 | P37: 73.162683 | Q37: 73.237561 | R37: 73.521707 | S37: 73.856098 | T37: 74.21561 | U37: 74.529756 | V37: 74.866341 | W37: 75.102195 | X37: 75.497805 | Y37: 75.725122 | Z37: 76.060488 | AA37: 76.331951 | AB37: 76.327317 | AC37: 76.463902 | AD37: 76.77878 | AE37: 76.85878 | AF37: 77.124878 | AG37: 77.436585 | AH37: 77.593415 | AI37: 77.838049 | AJ37: 77.704878 | AK37: 77.871707 | AL37: 77.977317 | AM37: 78.220244 | AN37: 78.412439 | AO37: 78.623659 | AP37: 78.839024 | AQ37: 79.166829 | AR37: 79.398049 | AS37: 79.530732 | AT37: 79.715122 | AU37: 79.992195 | AV37: 80.112683 | AW37: 80.543659 | AX37: 80.543659 | AY37: 80.724634 | AZ37: 81.066098 | BA37: 81.322195 | BB37: 81.482683 | BC37: 81.663659 | BD37: 81.744878 | BE37: 81.78439 | BF37: 81.825854 | BG37: 81.94 | BH37: 81.807805 | BI37: 81.803659 | BJ37: 82.158537 | BK37: 81.53 | BL37: 81.451463 | BM37: 81.094878 | BN37: 81.626341 | BO37: 82.108049 | BP37: CAN | BQ37: North America | BR37: High income | BS37: Canada
A38: Central Europe and the Baltics | B38: CEB | C38: 67.943473 | D38: 68.244951 | E38: 67.723736 | F38: 68.701 | G38: 69.195417 | H38: 69.350174 | I38: 69.856985 | J38: 69.355379 | K38: 69.573536 | L38: 69.066603 | M38: 69.345324 | N38: 69.511244 | O38: 69.971171 | P38: 70.109598 | Q38: 70.36857 | R38: 70.180888 | S38: 70.326408 | T38: 70.247694 | U38: 70.149887 | V38: 70.251482 | W38: 69.89341 | X38: 70.37205 | Y38: 70.455473 | Z38: 70.389785 | AA38: 70.349115 | AB38: 70.312883 | AC38: 70.565136 | AD38: 70.611763 | AE38: 70.861708 | AF38: 70.731972 | AG38: 70.656331 | AH38: 70.575221 | AI38: 70.732837 | AJ38: 70.845987 | AK38: 70.869544 | AL38: 71.025421 | AM38: 71.336058 | AN38: 71.517258 | AO38: 71.898238 | AP38: 72.184561 | AQ38: 72.719725 | AR38: 73.096148 | AS38: 73.242415 | AT38: 73.382253 | AU38: 73.730435 | AV38: 73.844995 | AW38: 74.092603 | AX38: 74.250649 | AY38: 74.575953 | AZ38: 74.930364 | BA38: 75.293966 | BB38: 75.888475 | BC38: 76.003394 | BD38: 76.374735 | BE38: 76.68877 | BF38: 76.575512 | BG38: 76.970306 | BH38: 76.929789 | BI38: 76.976438 | BJ38: 77.265914 | BK38: 76.01627 | BL38: 74.723283 | BM38: 76.652299 | BN38: 77.758038 | BO38: 77.918095 | BP38: CEB | BS38: Central Europe and the Baltics
A39: Switzerland | B39: CHE | C39: 71.313415 | D39: 71.644878 | E39: 71.196098 | F39: 71.187561 | G39: 72.077805 | H39: 72.201707 | I39: 72.33561 | J39: 72.636585 | K39: 72.590244 | L39: 72.612683 | M39: 73.020244 | N39: 73.130732 | O39: 73.64439 | P39: 73.940976 | Q39: 74.287073 | R39: 74.66561 | S39: 74.785366 | T39: 75.238049 | U39: 75.187317 | V39: 75.466098 | W39: 75.459268 | X39: 75.693171 | Y39: 76.033902 | Z39: 76.03122 | AA39: 76.608537 | AB39: 76.733659 | AC39: 76.899024 | AD39: 77.197561 | AE39: 77.226585 | AF39: 77.42122 | AG39: 77.242439 | AH39: 77.514634 | AI39: 77.806098 | AJ39: 78.085366 | AK39: 78.35 | AL39: 78.417073 | AM39: 78.896098 | AN39: 79.079512 | AO39: 79.32439 | AP39: 79.580488 | AQ39: 79.680488 | AR39: 80.180488 | AS39: 80.385366 | AT39: 80.536585 | AU39: 81.087805 | AV39: 81.236585 | AW39: 81.490244 | AX39: 81.741463 | AY39: 81.992683 | AZ39: 82.043902 | BA39: 82.246341 | BB39: 82.695122 | BC39: 82.697561 | BD39: 82.797561 | BE39: 83.197561 | BF39: 82.897561 | BG39: 83.602439 | BH39: 83.55122 | BI39: 83.753659 | BJ39: 83.904878 | BK39: 83 | BL39: 83.75122 | BM39: 83.604878 | BN39: 84.156098 | BO39: 84.407317 | BP39: CHE | BQ39: Europe & Central Asia | BR39: High income | BS39: Switzerland
A40: Channel Islands | B40: CHI | C40: 72.5 | D40: 71.6 | E40: 72 | F40: 72.2 | G40: 72 | H40: 71.6 | I40: 72.3 | J40: 72.2 | K40: 71.7 | L40: 71.7 | M40: 71.8 | N40: 72 | O40: 72 | P40: 72.7 | Q40: 72.5 | R40: 72.6 | S40: 72.7 | T40: 72.9 | U40: 73.1 | V40: 73.2 | W40: 73.9 | X40: 73.8 | Y40: 73.1 | Z40: 74.9 | AA40: 75.2 | AB40: 75.3 | AC40: 75.4 | AD40: 75.7 | AE40: 76 | AF40: 76.5 | AG40: 76.3 | AH40: 76.5 | AI40: 77.1 | AJ40: 76.8 | AK40: 77 | AL40: 77.7 | AM40: 77.8 | AN40: 78.2 | AO40: 78.5 | AP40: 79.1 | AQ40: 78.8 | AR40: 79 | AS40: 79.1 | AT40: 79.4 | AU40: 79.8 | AV40: 80.1 | AW40: 80.4 | AX40: 80.6 | AY40: 80.8 | AZ40: 81 | BA40: 81.2 | BB40: 81.4 | BC40: 81.3 | BD40: 81.5 | BE40: 81.6 | BF40: 81.4 | BG40: 81.2 | BH40: 81 | BI40: 81.1 | BJ40: 81.2 | BK40: 80.9 | BL40: 80.3 | BM40: 81 | BN40: 81.1 | BO40: 81.2 | BP40: CHI | BQ40: Europe & Central Asia | BR40: High income | BS40: Channel Islands
A41: Chile | B41: CHL | C41: 57.216 | D41: 57.309 | E41: 57.811 | F41: 58.349 | G41: 58.812 | H41: 59.473 | I41: 60.373 | J41: 61.054 | K41: 61.68 | L41: 62.341 | M41: 62.634 | N41: 63.072 | O41: 63.717 | P41: 64.42 | Q41: 65.085 | R41: 66.037 | S41: 66.819 | T41: 67.529 | U41: 68.042 | V41: 68.858 | W41: 69.475 | X41: 69.822 | Y41: 70.291 | Z41: 70.83 | AA41: 71.215 | AB41: 71.615 | AC41: 72.061 | AD41: 72.466 | AE41: 72.788 | AF41: 73.188 | AG41: 73.675 | AH41: 74.082 | AI41: 74.367 | AJ41: 74.679 | AK41: 74.973 | AL41: 75.298 | AM41: 75.555 | AN41: 75.826 | AO41: 76.324 | AP41: 76.738 | AQ41: 77.128 | AR41: 77.58 | AS41: 77.84 | AT41: 77.884 | AU41: 78.276 | AV41: 78.459 | AW41: 78.533 | AX41: 78.652 | AY41: 78.752 | AZ41: 78.89 | BA41: 79.095 | BB41: 79.236 | BC41: 79.221 | BD41: 79.551 | BE41: 79.714 | BF41: 80.008 | BG41: 80.295 | BH41: 80.61 | BI41: 80.559 | BJ41: 80.324 | BK41: 79.349 | BL41: 78.876 | BM41: 79.176 | BN41: 81.167 | BO41: 81.359 | BP41: CHL | BQ41: Latin America & Caribbean | BR41: High income | BS41: Chile
A42: China | B42: CHN | C42: 33.419 | D42: 40.158 | E42: 50.959 | F42: 51.67 | G42: 52.343 | H42: 53.001 | I42: 53.662 | J42: 54.401 | K42: 55.191 | L42: 55.988 | M42: 56.824 | N42: 57.731 | O42: 58.579 | P42: 59.496 | Q42: 60.241 | R42: 60.952 | S42: 61.225 | T42: 62.458 | U42: 63.102 | V42: 63.704 | W42: 64.243 | X42: 64.778 | Y42: 65.249 | Z42: 65.728 | AA42: 66.148 | AB42: 66.532 | AC42: 66.887 | AD42: 67.263 | AE42: 67.607 | AF42: 67.93 | AG42: 68.155 | AH42: 68.61 | AI42: 69.059 | AJ42: 69.492 | AK42: 69.835 | AL42: 70.363 | AM42: 70.823 | AN42: 71.227 | AO42: 71.601 | AP42: 71.952 | AQ42: 72.288 | AR42: 72.675 | AS42: 73.034 | AT42: 73.385 | AU42: 73.727 | AV42: 74.085 | AW42: 74.404 | AX42: 74.789 | AY42: 74.833 | AZ42: 75.317 | BA42: 75.668 | BB42: 75.889 | BC42: 76.2 | BD42: 76.452 | BE42: 76.714 | BF42: 76.975 | BG42: 77.214 | BH42: 77.235 | BI42: 77.709 | BJ42: 77.94 | BK42: 78.019 | BL42: 78.117 | BM42: 78.202 | BN42: 77.953 | BO42: 78.017 | BP42: CHN | BQ42: East Asia & Pacific | BR42: Upper middle income | BS42: China
A43: Cote d'Ivoire | B43: CIV | C43: 37.244 | D43: 37.923 | E43: 38.62 | F43: 39.315 | G43: 39.966 | H43: 40.643 | I43: 41.297 | J43: 41.959 | K43: 42.648 | L43: 43.345 | M43: 44.045 | N43: 44.783 | O43: 45.575 | P43: 46.372 | Q43: 47.207 | R43: 48.03 | S43: 48.863 | T43: 49.624 | U43: 50.361 | V43: 50.983 | W43: 51.437 | X43: 51.791 | Y43: 52.09 | Z43: 52.352 | AA43: 52.648 | AB43: 52.861 | AC43: 53.009 | AD43: 53.118 | AE43: 53.062 | AF43: 52.955 | AG43: 52.796 | AH43: 52.621 | AI43: 52.429 | AJ43: 52.247 | AK43: 52.005 | AL43: 51.713 | AM43: 51.596 | AN43: 51.498 | AO43: 51.22 | AP43: 51.273 | AQ43: 51.393 | AR43: 51.428 | AS43: 51.544 | AT43: 51.443 | AU43: 51.939 | AV43: 52.432 | AW43: 52.885 | AX43: 53.452 | AY43: 54.179 | AZ43: 54.744 | BA43: 55.282 | BB43: 55.972 | BC43: 56.57 | BD43: 57.057 | BE43: 57.772 | BF43: 58.281 | BG43: 58.814 | BH43: 59.315 | BI43: 59.795 | BJ43: 60.274 | BK43: 60.14 | BL43: 60.29 | BM43: 61.562 | BN43: 61.944 | BO43: 62.11 | BP43: CIV | BQ43: Sub-Saharan Africa | BR43: Lower middle income | BS43: Côte d'Ivoire
A44: Cameroon | B44: CMR | C44: 34.667 | D44: 35.186 | E44: 42.599 | F44: 43.074 | G44: 43.596 | H44: 44.175 | I44: 44.839 | J44: 45.602 | K44: 46.389 | L44: 47.191 | M44: 47.954 | N44: 48.577 | O44: 49.12 | P44: 49.517 | Q44: 49.734 | R44: 49.891 | S44: 50.017 | T44: 50.13 | U44: 50.319 | V44: 50.535 | W44: 50.852 | X44: 51.227 | Y44: 51.801 | Z44: 52.447 | AA44: 52.886 | AB44: 53.465 | AC44: 53.572 | AD44: 54.188 | AE44: 54.359 | AF44: 54.389 | AG44: 54.348 | AH44: 54.168 | AI44: 54.053 | AJ44: 53.872 | AK44: 53.537 | AL44: 53.347 | AM44: 53.2 | AN44: 53.105 | AO44: 53.043 | AP44: 53.166 | AQ44: 53.338 | AR44: 53.598 | AS44: 53.922 | AT44: 54.253 | AU44: 54.578 | AV44: 54.904 | AW44: 55.301 | AX44: 55.71 | AY44: 56.116 | AZ44: 56.486 | BA44: 56.965 | BB44: 57.482 | BC44: 58.17 | BD44: 58.73 | BE44: 59.13 | BF44: 59.687 | BG44: 60.293 | BH44: 60.817 | BI44: 61.189 | BJ44: 61.695 | BK44: 61.674 | BL44: 61.146 | BM44: 62.443 | BN44: 63.7 | BO44: 63.968 | BP44: CMR | BQ44: Sub-Saharan Africa | BR44: Lower middle income | BS44: Cameroon
A45: Congo, Dem. Rep. | B45: COD | C45: 40.752 | D45: 40.161 | E45: 40.382 | F45: 40.604 | G45: 40.099 | H45: 40.767 | I45: 42.169 | J45: 42.339 | K45: 42.667 | L45: 42.959 | M45: 43.3 | N45: 43.578 | O45: 43.869 | P45: 44.09 | Q45: 44.311 | R45: 44.53 | S45: 44.695 | T45: 44.866 | U45: 44.628 | V45: 45.278 | W45: 45.543 | X45: 45.726 | Y45: 45.946 | Z45: 46.207 | AA45: 46.514 | AB45: 46.663 | AC45: 47.016 | AD45: 47.362 | AE45: 47.755 | AF45: 48.149 | AG45: 48.538 | AH45: 48.944 | AI45: 49.323 | AJ45: 49.621 | AK45: 49.88 | AL45: 50.381 | AM45: 49.376 | AN45: 50.461 | AO45: 49.664 | AP45: 50.089 | AQ45: 51.887 | AR45: 52.205 | AS45: 52.371 | AT45: 52.952 | AU45: 53.534 | AV45: 54.001 | AW45: 54.498 | AX45: 54.954 | AY45: 55.388 | AZ45: 55.798 | BA45: 56.411 | BB45: 56.911 | BC45: 57.35 | BD45: 57.795 | BE45: 58.236 | BF45: 58.658 | BG45: 59.081 | BH45: 59.495 | BI45: 59.926 | BJ45: 60.242 | BK45: 60.428 | BL45: 60.044 | BM45: 60.979 | BN45: 61.895 | BO45: 62.074 | BP45: COD | BQ45: Sub-Saharan Africa | BR45: Low income | BS45: Congo, Dem. Rep.
A46: Congo, Rep. | B46: COG | C46: 47.595 | D46: 48.351 | E46: 49.038 | F46: 49.729 | G46: 50.363 | H46: 50.996 | I46: 51.557 | J46: 51.91 | K46: 52.62 | L46: 53.114 | M46: 53.555 | N46: 53.983 | O46: 54.361 | P46: 54.744 | Q46: 55.053 | R46: 55.402 | S46: 55.699 | T46: 56.027 | U46: 56.248 | V46: 56.524 | W46: 56.803 | X46: 57.065 | Y46: 57.236 | Z46: 57.428 | AA46: 57.54 | AB46: 57.608 | AC46: 57.633 | AD46: 57.59 | AE46: 57.493 | AF46: 57.292 | AG46: 57.07 | AH46: 56.764 | AI46: 56.483 | AJ46: 56.041 | AK46: 55.641 | AL46: 55.474 | AM46: 55.24 | AN46: 48.575 | AO46: 52.551 | AP46: 54.427 | AQ46: 55.371 | AR46: 55.885 | AS46: 56.414 | AT46: 57.131 | AU46: 57.957 | AV46: 58.73 | AW46: 59.474 | AX46: 60.05 | AY46: 60.79 | AZ46: 61.215 | BA46: 61.731 | BB46: 62.286 | BC46: 62.662 | BD46: 62.969 | BE46: 63.349 | BF46: 63.662 | BG46: 63.911 | BH46: 64.203 | BI46: 64.472 | BJ46: 63.152 | BK46: 64.391 | BL46: 64.192 | BM46: 65 | BN46: 65.772 | BO46: 66.001 | BP46: COG | BQ46: Sub-Saharan Africa | BR46: Lower middle income | BS46: Congo, Rep.
A47: Colombia | B47: COL | C47: 56.609 | D47: 57.203 | E47: 57.737 | F47: 58.296 | G47: 58.77 | H47: 59.247 | I47: 59.713 | J47: 60.15 | K47: 60.572 | L47: 61.031 | M47: 61.465 | N47: 62.005 | O47: 62.53 | P47: 62.991 | Q47: 63.497 | R47: 64.012 | S47: 64.642 | T47: 65.237 | U47: 65.827 | V47: 66.162 | W47: 66.693 | X47: 67.189 | Y47: 67.861 | Z47: 68.121 | AA47: 68.308 | AB47: 65.359 | AC47: 68.303 | AD47: 68.166 | AE47: 68.301 | AF47: 68.616 | AG47: 68.701 | AH47: 68.772 | AI47: 68.764 | AJ47: 69.083 | AK47: 69.422 | AL47: 69.81 | AM47: 70.209 | AN47: 70.632 | AO47: 70.924 | AP47: 70.913 | AQ47: 70.905 | AR47: 71.185 | AS47: 71.537 | AT47: 72.309 | AU47: 72.76 | AV47: 73.156 | AW47: 73.497 | AX47: 73.751 | AY47: 74.206 | AZ47: 74.531 | BA47: 74.876 | BB47: 75.18 | BC47: 75.611 | BD47: 75.834 | BE47: 75.95 | BF47: 76.067 | BG47: 76.228 | BH47: 76.418 | BI47: 76.579 | BJ47: 76.793 | BK47: 74.757 | BL47: 72.698 | BM47: 76.508 | BN47: 77.725 | BO47: 77.913 | BP47: COL | BQ47: Latin America & Caribbean | BR47: Upper middle income | BS47: Colombia
A48: Comoros | B48: COM | C48: 40.777 | D48: 41.157 | E48: 41.534 | F48: 41.909 | G48: 42.328 | H48: 42.676 | I48: 43.153 | J48: 43.593 | K48: 44.101 | L48: 44.643 | M48: 45.226 | N48: 45.849 | O48: 46.463 | P48: 47.045 | Q48: 47.609 | R48: 46.866 | S48: 48.645 | T48: 49.17 | U48: 49.702 | V48: 50.126 | W48: 50.681 | X48: 51.211 | Y48: 51.75 | Z48: 52.121 | AA48: 52.784 | AB48: 53.263 | AC48: 53.756 | AD48: 54.134 | AE48: 54.678 | AF48: 54.983 | AG48: 55.62 | AH48: 56.104 | AI48: 56.576 | AJ48: 57.026 | AK48: 57.458 | AL48: 57.83 | AM48: 58.151 | AN48: 58.228 | AO48: 58.301 | AP48: 58.853 | AQ48: 58.941 | AR48: 59.587 | AS48: 59.723 | AT48: 60.24 | AU48: 60.557 | AV48: 60.883 | AW48: 61.229 | AX48: 61.475 | AY48: 61.955 | AZ48: 62.302 | BA48: 62.747 | BB48: 63.105 | BC48: 63.463 | BD48: 63.839 | BE48: 64.143 | BF48: 64.473 | BG48: 64.792 | BH48: 65.127 | BI48: 65.401 | BJ48: 65.662 | BK48: 65.756 | BL48: 65.201 | BM48: 66.481 | BN48: 66.777 | BO48: 67.023 | BP48: COM | BQ48: Sub-Saharan Africa | BR48: Lower middle income | BS48: Comoros
A49: Cabo Verde | B49: CPV | C49: 48.713 | D49: 49.419 | E49: 50.239 | F49: 51.145 | G49: 52.089 | H49: 53.04 | I49: 53.922 | J49: 54.716 | K49: 55.426 | L49: 56.038 | M49: 56.559 | N49: 57.027 | O49: 57.486 | P49: 57.979 | Q49: 58.432 | R49: 58.976 | S49: 59.396 | T49: 59.986 | U49: 60.381 | V49: 60.726 | W49: 61.031 | X49: 61.299 | Y49: 61.519 | Z49: 61.767 | AA49: 61.829 | AB49: 62.281 | AC49: 62.584 | AD49: 62.91 | AE49: 63.242 | AF49: 63.566 | AG49: 63.869 | AH49: 64.066 | AI49: 64.253 | AJ49: 64.458 | AK49: 64.648 | AL49: 63.691 | AM49: 65.521 | AN49: 66.082 | AO49: 66.714 | AP49: 67.409 | AQ49: 68.117 | AR49: 68.707 | AS49: 69.447 | AT49: 70.006 | AU49: 70.499 | AV49: 70.936 | AW49: 71.341 | AX49: 71.487 | AY49: 71.888 | AZ49: 72.142 | BA49: 72.507 | BB49: 72.913 | BC49: 73.315 | BD49: 73.481 | BE49: 73.788 | BF49: 74.096 | BG49: 74.35 | BH49: 74.71 | BI49: 74.84 | BJ49: 75.449 | BK49: 73.818 | BL49: 74.424 | BM49: 75.907 | BN49: 76.059 | BO49: 76.224 | BP49: CPV | BQ49: Sub-Saharan Africa | BR49: Upper middle income | BS49: Cabo Verde
A50: Costa Rica | B50: CRI | C50: 63.463 | D50: 63.86 | E50: 64.232 | F50: 64.326 | G50: 64.493 | H50: 64.76 | I50: 65.096 | J50: 65.552 | K50: 65.78 | L50: 66.363 | M50: 66.787 | N50: 67.413 | O50: 68.014 | P50: 68.731 | Q50: 69.446 | R50: 70.253 | S50: 70.946 | T50: 71.519 | U50: 72.029 | V50: 72.537 | W50: 73.034 | X50: 73.441 | Y50: 73.865 | Z50: 74.245 | AA50: 74.581 | AB50: 74.765 | AC50: 74.949 | AD50: 75.224 | AE50: 75.546 | AF50: 75.85 | AG50: 76.094 | AH50: 76.237 | AI50: 76.385 | AJ50: 76.315 | AK50: 76.329 | AL50: 76.44 | AM50: 76.428 | AN50: 76.603 | AO50: 76.869 | AP50: 77.058 | AQ50: 77.317 | AR50: 77.609 | AS50: 77.939 | AT50: 78.214 | AU50: 78.512 | AV50: 78.877 | AW50: 79.049 | AX50: 79.098 | AY50: 79.18 | AZ50: 79.372 | BA50: 79.354 | BB50: 79.624 | BC50: 79.925 | BD50: 80.189 | BE50: 80.231 | BF50: 80.407 | BG50: 79.988 | BH50: 79.994 | BI50: 80.09 | BJ50: 80.296 | BK50: 79.725 | BL50: 78.05 | BM50: 79.316 | BN50: 80.799 | BO50: 80.996 | BP50: CRI | BQ50: Latin America & Caribbean | BR50: High income | BS50: Costa Rica
A51: Caribbean small states | B51: CSS | C51: 60.296076 | D51: 60.671113 | E51: 61.366755 | F51: 61.717282 | G51: 62.116938 | H51: 62.427899 | I51: 62.688492 | J51: 62.919213 | K51: 63.147976 | L51: 63.33756 | M51: 63.491125 | N51: 63.642161 | O51: 63.85759 | P51: 64.052426 | Q51: 64.263256 | R51: 64.483005 | S51: 64.756251 | T51: 64.972608 | U51: 65.124541 | V51: 65.347242 | W51: 65.501582 | X51: 65.663476 | Y51: 65.778323 | Z51: 65.84727 | AA51: 66.13987 | AB51: 66.30206 | AC51: 66.411303 | AD51: 66.570945 | AE51: 66.74044 | AF51: 66.9248 | AG51: 67.045151 | AH51: 67.219377 | AI51: 67.353289 | AJ51: 67.475565 | AK51: 67.521661 | AL51: 67.555572 | AM51: 67.626402 | AN51: 67.736543 | AO51: 67.984923 | AP51: 68.209564 | AQ51: 68.397676 | AR51: 68.661972 | AS51: 68.899714 | AT51: 69.087649 | AU51: 69.36097 | AV51: 69.632051 | AW51: 69.934423 | AX51: 70.293733 | AY51: 70.549997 | AZ51: 70.797738 | BA51: 71.011437 | BB51: 71.266093 | BC51: 71.401914 | BD51: 71.569251 | BE51: 71.773941 | BF51: 71.864102 | BG51: 72.051636 | BH51: 72.173104 | BI51: 72.221085 | BJ51: 72.12926 | BK51: 71.939436 | BL51: 69.922811 | BM51: 72.832292 | BN51: 73.171645 | BO51: 73.312667 | BP51: CSS | BS51: Caribbean small states
A52: Cuba | B52: CUB | C52: 63.316 | D52: 63.743 | E52: 64.374 | F52: 64.347 | G52: 65.264 | H52: 65.636 | I52: 66.074 | J52: 66.514 | K52: 66.944 | L52: 67.358 | M52: 67.935 | N52: 68.432 | O52: 68.949 | P52: 69.347 | Q52: 69.867 | R52: 70.375 | S52: 70.878 | T52: 71.411 | U52: 71.89 | V52: 72.272 | W52: 72.603 | X52: 72.996 | Y52: 73.439 | Z52: 73.564 | AA52: 73.552 | AB52: 73.464 | AC52: 73.558 | AD52: 73.596 | AE52: 73.724 | AF52: 73.69 | AG52: 73.823 | AH52: 73.757 | AI52: 73.846 | AJ52: 73.874 | AK52: 74.092 | AL52: 74.346 | AM52: 74.69 | AN52: 75.064 | AO52: 75.412 | AP52: 75.719 | AQ52: 75.922 | AR52: 76.429 | AS52: 76.766 | AT52: 77.405 | AU52: 77.326 | AV52: 77.54 | AW52: 77.406 | AX52: 77.55 | AY52: 77.589 | AZ52: 77.584 | BA52: 77.876 | BB52: 78.051 | BC52: 78.162 | BD52: 78.028 | BE52: 77.825 | BF52: 77.745 | BG52: 77.571 | BH52: 77.3 | BI52: 77.426 | BJ52: 77.413 | BK52: 77.407 | BL52: 73.201 | BM52: 77.629 | BN52: 78.085 | BO52: 78.264 | BP52: CUB | BQ52: Latin America & Caribbean | BR52: Upper middle income | BS52: Cuba
A53: Curacao | B53: CUW | C53: 65.406 | D53: 65.745 | E53: 66.027 | F53: 66.312 | G53: 66.59 | H53: 66.862 | I53: 67.136 | J53: 67.405 | K53: 67.67 | L53: 67.929 | M53: 68.23 | N53: 68.505 | O53: 68.811 | P53: 69.092 | Q53: 69.394 | R53: 69.672 | S53: 69.951 | T53: 70.202 | U53: 70.445 | V53: 70.716 | W53: 70.951 | X53: 71.175 | Y53: 71.377 | Z53: 71.534 | AA53: 71.715 | AB53: 71.867 | AC53: 71.996 | AD53: 72.139 | AE53: 72.23 | AF53: 72.151 | AG53: 72.439 | AH53: 72.536 | AI53: 72.65 | AJ53: 72.703 | AK53: 72.791 | AL53: 72.831 | AM53: 72.945 | AN53: 73.035 | AO53: 73.084 | AP53: 73.174 | AQ53: 73.283 | AR53: 73.36 | AS53: 73.472 | AT53: 73.603 | AU53: 73.735 | AV53: 73.873 | AW53: 73.978 | AX53: 74.137 | AY53: 74.314 | AZ53: 74.485 | BA53: 75.117 | BB53: 75.576 | BC53: 75.96 | BD53: 76.239 | BE53: 76.384 | BF53: 76.482 | BG53: 76.322 | BH53: 76.423 | BI53: 76.493 | BJ53: 76.492 | BK53: 76.501 | BL53: 75.686 | BM53: 76.729 | BN53: 76.8 | BO53: 76.989 | BP53: CUW | BQ53: Latin America & Caribbean | BR53: High income | BS53: Curaçao
A54: Cayman Islands | B54: CYM | C54: 58.782 | D54: 59.426 | E54: 60.09 | F54: 60.78 | G54: 61.436 | H54: 62.186 | I54: 62.841 | J54: 63.205 | K54: 63.597 | L54: 63.965 | M54: 64.383 | N54: 64.827 | O54: 65.365 | P54: 65.889 | Q54: 66.489 | R54: 67.044 | S54: 67.549 | T54: 68.08 | U54: 68.533 | V54: 69.02 | W54: 69.487 | X54: 69.951 | Y54: 70.407 | Z54: 70.839 | AA54: 71.187 | AB54: 71.558 | AC54: 71.869 | AD54: 72.13 | AE54: 72.351 | AF54: 72.545 | AG54: 72.744 | AH54: 72.911 | AI54: 73.088 | AJ54: 73.25 | AK54: 73.42 | AL54: 73.597 | AM54: 73.74 | AN54: 73.904 | AO54: 74.08 | AP54: 74.232 | AQ54: 74.378 | AR54: 74.529 | AS54: 74.609 | AT54: 74.639 | AU54: 74.596 | AV54: 74.863 | AW54: 75 | AX54: 75.152 | AY54: 75.386 | AZ54: 75.671 | BA54: 76.069 | BB54: 76.562 | BC54: 77.121 | BD54: 77.652 | BE54: 77.865 | BF54: 78.119 | BG54: 78.367 | BH54: 78.615 | BI54: 78.835 | BJ54: 79.052 | BK54: 79.23 | BL54: 79.3 | BM54: 79.984 | BN54: 80.358 | BO54: 80.54 | BP54: CYM | BQ54: Latin America & Caribbean | BR54: High income | BS54: Cayman Islands
A55: Cyprus | B55: CYP | C55: 63.32 | D55: 64.076 | E55: 64.72 | F55: 61.779 | G55: 62.24 | H55: 66.124 | I55: 66.489 | J55: 66.906 | K55: 67.251 | L55: 67.599 | M55: 68.05 | N55: 68.351 | O55: 68.629 | P55: 69.005 | Q55: 54.551 | R55: 70.336 | S55: 70.805 | T55: 71.258 | U55: 71.741 | V55: 72.179 | W55: 72.844 | X55: 73.053 | Y55: 73.518 | Z55: 73.708 | AA55: 74 | AB55: 74.64 | AC55: 74.93 | AD55: 75.264 | AE55: 75.39 | AF55: 75.841 | AG55: 76.044 | AH55: 76.246 | AI55: 76.291 | AJ55: 76.294 | AK55: 76.383 | AL55: 76.583 | AM55: 76.88 | AN55: 77.119 | AO55: 77.164 | AP55: 77.572 | AQ55: 77.9 | AR55: 78.185 | AS55: 78.758 | AT55: 78.908 | AU55: 79.007 | AV55: 79.198 | AW55: 79.456 | AX55: 79.798 | AY55: 79.906 | AZ55: 80.375 | BA55: 80.632 | BB55: 80.855 | BC55: 81.128 | BD55: 81.317 | BE55: 81.337 | BF55: 81.464 | BG55: 81.534 | BH55: 81.543 | BI55: 81.556 | BJ55: 81.454 | BK55: 81.23 | BL55: 80.573 | BM55: 80.434 | BN55: 81.648 | BO55: 81.821 | BP55: CYP | BQ55: Europe & Central Asia | BR55: High income | BS55: Cyprus
A56: Czechia | B56: CZE | C56: 70.34878 | D56: 70.512683 | E56: 69.786829 | F56: 70.30439 | G56: 70.459512 | H56: 70.163171 | I56: 70.384878 | J56: 70.264146 | K56: 69.840732 | L56: 69.367073 | M56: 69.440244 | N56: 69.677073 | O56: 70.176585 | P56: 70.022683 | Q56: 70.086585 | R56: 70.414634 | S56: 70.532683 | T56: 70.573415 | U56: 70.643902 | V56: 70.749512 | W56: 70.278049 | X56: 70.722195 | Y56: 70.807805 | Z56: 70.591463 | AA56: 70.837561 | AB56: 71.046341 | AC56: 70.997317 | AD56: 71.44561 | AE56: 71.641463 | AF56: 71.67561 | AG56: 71.383902 | AH56: 71.898293 | AI56: 72.271707 | AJ56: 72.767805 | AK56: 72.972683 | AL56: 73.074878 | AM56: 73.714634 | AN56: 73.824878 | AO56: 74.514634 | AP56: 74.668293 | AQ56: 74.968293 | AR56: 75.173171 | AS56: 75.221951 | AT56: 75.170732 | AU56: 75.721951 | AV56: 75.92439 | AW56: 76.52439 | AX56: 76.72439 | AY56: 76.97561 | AZ56: 77.078049 | BA56: 77.42439 | BB56: 77.873171 | BC56: 78.07561 | BD56: 78.17561 | BE56: 78.82439 | BF56: 78.578049 | BG56: 79.026829 | BH56: 78.978049 | BI56: 79.029268 | BJ56: 79.229268 | BK56: 78.226829 | BL56: 77.221951 | BM56: 78.929268 | BN56: 79.826829 | BO56: 79.978049 | BP56: CZE | BQ56: Europe & Central Asia | BR56: High income | BS56: Czechia
A57: Germany | B57: DEU | C57: 69.064073 | D57: 69.644878 | E57: 69.79922 | F57: 69.914073 | G57: 70.435561 | H57: 70.410366 | I57: 70.521585 | J57: 70.731732 | K57: 70.378463 | L57: 70.228805 | M57: 70.447195 | N57: 70.676756 | O57: 70.906707 | P57: 71.112805 | Q57: 71.418927 | R57: 71.259244 | S57: 71.71222 | T57: 72.307317 | U57: 72.290415 | V57: 72.630171 | W57: 72.800317 | X57: 73.04022 | Y57: 73.333146 | Z57: 73.622146 | AA57: 74.072293 | AB57: 74.189098 | AC57: 74.396829 | AD57: 74.807024 | AE57: 74.998732 | AF57: 75.191537 | AG57: 75.085634 | AH57: 75.319512 | AI57: 75.819512 | AJ57: 75.870732 | AK57: 76.270732 | AL57: 76.421951 | AM57: 76.673171 | AN57: 77.073171 | AO57: 77.47561 | AP57: 77.726829 | AQ57: 77.926829 | AR57: 78.329268 | AS57: 78.229268 | AT57: 78.380488 | AU57: 78.680488 | AV57: 78.931707 | AW57: 79.131707 | AX57: 79.534146 | AY57: 79.736585 | AZ57: 79.836585 | BA57: 79.987805 | BB57: 80.436585 | BC57: 80.539024 | BD57: 80.490244 | BE57: 81.090244 | BF57: 80.641463 | BG57: 80.990244 | BH57: 80.992683 | BI57: 80.892683 | BJ57: 81.292683 | BK57: 81.041463 | BL57: 80.790244 | BM57: 80.608049 | BN57: 81.041463 | BO57: 80.792683 | BP57: DEU | BQ57: Europe & Central Asia | BR57: High income | BS57: Germany
A58: Djibouti | B58: DJI | C58: 43.421 | D58: 43.781 | E58: 44.092 | F58: 44.442 | G58: 44.812 | H58: 45.234 | I58: 45.62 | J58: 46.103 | K58: 46.552 | L58: 47.067 | M58: 47.536 | N58: 47.259 | O58: 48.532 | P58: 49.097 | Q58: 49.52 | R58: 49.923 | S58: 50.335 | T58: 50.755 | U58: 51.172 | V58: 51.597 | W58: 52.046 | X58: 52.355 | Y58: 52.893 | Z58: 53.334 | AA58: 53.745 | AB58: 54.075 | AC58: 54.494 | AD58: 54.832 | AE58: 55.133 | AF58: 55.369 | AG58: 55.469 | AH58: 55.194 | AI58: 54.375 | AJ58: 55.734 | AK58: 55.592 | AL58: 56.234 | AM58: 56.33 | AN58: 56.207 | AO58: 56.426 | AP58: 56.564 | AQ58: 56.734 | AR58: 57.506 | AS58: 57.824 | AT58: 58.041 | AU58: 58.103 | AV58: 58.548 | AW58: 58.962 | AX58: 59.362 | AY58: 59.815 | AZ58: 60.351 | BA58: 60.743 | BB58: 61.337 | BC58: 61.719 | BD58: 62.116 | BE58: 62.427 | BF58: 62.833 | BG58: 63.335 | BH58: 63.71 | BI58: 64.105 | BJ58: 64.381 | BK58: 64.2 | BL58: 63.83 | BM58: 65.54 | BN58: 65.987 | BO58: 66.202 | BP58: DJI | BQ58: Middle East & North Africa | BR58: Lower middle income | BS58: Djibouti
A59: Dominica | B59: DMA | C59: 60.076 | D59: 61.022 | E59: 61.894 | F59: 62.612 | G59: 63.278 | H59: 63.913 | I59: 64.457 | J59: 64.856 | K59: 65.277 | L59: 65.704 | M59: 66.208 | N59: 66.763 | O59: 67.468 | P59: 68.097 | Q59: 68.585 | R59: 69.059 | S59: 69.411 | T59: 69.715 | U59: 70.115 | V59: 69.195 | W59: 71.013 | X59: 71.46 | Y59: 71.749 | Z59: 72.005 | AA59: 71.913 | AB59: 71.918 | AC59: 71.671 | AD59: 71.368 | AE59: 70.974 | AF59: 70.663 | AG59: 70.471 | AH59: 70.398 | AI59: 70.473 | AJ59: 70.612 | AK59: 70.777 | AL59: 70.832 | AM59: 71.039 | AN59: 71.195 | AO59: 71.352 | AP59: 71.527 | AQ59: 71.715 | AR59: 71.862 | AS59: 71.927 | AT59: 71.942 | AU59: 71.987 | AV59: 72.016 | AW59: 72.007 | AX59: 71.901 | AY59: 71.945 | AZ59: 71.835 | BA59: 71.68 | BB59: 71.517 | BC59: 71.391 | BD59: 71.228 | BE59: 71.189 | BF59: 69.968 | BG59: 71.189 | BH59: 68.62 | BI59: 71.378 | BJ59: 71.305 | BK59: 71.269 | BL59: 69.832 | BM59: 71.081 | BN59: 71.132 | BO59: 71.294 | BP59: DMA | BQ59: Latin America & Caribbean | BR59: Upper middle income | BS59: Dominica
A60: Denmark | B60: DNK | C60: 72.176585 | D60: 72.438293 | E60: 72.319756 | F60: 72.400488 | G60: 72.485122 | H60: 72.370732 | I60: 72.444146 | J60: 72.922195 | K60: 73.121463 | L60: 73.220976 | M60: 73.343415 | N60: 73.414634 | O60: 73.439024 | P60: 73.682195 | Q60: 73.808293 | R60: 74.075122 | S60: 73.739756 | T60: 74.632439 | U60: 74.392927 | V60: 74.219268 | W60: 74.101707 | X60: 74.230488 | Y60: 74.55122 | Z60: 74.420488 | AA60: 74.562195 | AB60: 74.427561 | AC60: 74.579756 | AD60: 74.69122 | AE60: 74.771707 | AF60: 74.799756 | AG60: 74.805366 | AH60: 75.157805 | AI60: 75.194146 | AJ60: 75.116829 | AK60: 75.375122 | AL60: 75.212683 | AM60: 75.591463 | AN60: 75.945122 | AO60: 76.139024 | AP60: 76.341463 | AQ60: 76.592683 | AR60: 76.792683 | AS60: 76.895122 | AT60: 77.143902 | AU60: 77.492683 | AV60: 77.843902 | AW60: 78.095122 | AX60: 78.195122 | AY60: 78.446341 | AZ60: 78.597561 | BA60: 79.1 | BB60: 79.8 | BC60: 80.05122 | BD60: 80.3 | BE60: 80.7 | BF60: 80.702439 | BG60: 80.853659 | BH60: 81.102439 | BI60: 80.953659 | BJ60: 81.45122 | BK60: 81.602439 | BL60: 81.404878 | BM60: 81.304878 | BN60: 81.753659 | BO60: 82.253659 | BP60: DNK | BQ60: Europe & Central Asia | BR60: High income | BS60: Denmark
A61: Dominican Republic | B61: DOM | C61: 51.705 | D61: 52.447 | E61: 53.199 | F61: 53.754 | G61: 54.653 | H61: 52.842 | I61: 55.965 | J61: 56.646 | K61: 57.272 | L61: 57.886 | M61: 58.493 | N61: 59.09 | O61: 59.661 | P61: 60.228 | Q61: 60.757 | R61: 61.254 | S61: 61.739 | T61: 62.2 | U61: 62.624 | V61: 62.425 | W61: 63.391 | X61: 63.776 | Y61: 64.198 | Z61: 64.63 | AA61: 65.134 | AB61: 65.614 | AC61: 66.059 | AD61: 66.49 | AE61: 66.914 | AF61: 67.331 | AG61: 67.746 | AH61: 68.154 | AI61: 68.525 | AJ61: 68.86 | AK61: 69.16 | AL61: 69.394 | AM61: 69.595 | AN61: 69.809 | AO61: 69.875 | AP61: 70.178 | AQ61: 70.365 | AR61: 70.553 | AS61: 70.719 | AT61: 70.856 | AU61: 70.73 | AV61: 71.043 | AW61: 71.054 | AX61: 71.097 | AY61: 71.331 | AZ61: 71.587 | BA61: 72.039 | BB61: 72.496 | BC61: 72.817 | BD61: 73.038 | BE61: 73.145 | BF61: 72.982 | BG61: 72.889 | BH61: 73.37 | BI61: 73.555 | BJ61: 73.112 | BK61: 72.636 | BL61: 71.757 | BM61: 74.211 | BN61: 73.72 | BO61: 73.868 | BP61: DOM | BQ61: Latin America & Caribbean | BR61: Upper middle income | BS61: Dominican Republic
A62: Algeria | B62: DZA | C62: 40.839 | D62: 40.792 | E62: 39.527 | F62: 43.143 | G62: 42.987 | H62: 42.846 | I62: 42.745 | J62: 42.731 | K62: 42.806 | L62: 42.991 | M62: 43.328 | N62: 43.782 | O62: 44.384 | P62: 45.102 | Q62: 45.953 | R62: 46.921 | S62: 48.034 | T62: 49.249 | U62: 50.615 | V62: 52.409 | W62: 54.512 | X62: 57.422 | Y62: 59.594 | Z62: 61.251 | AA62: 62.722 | AB62: 64.155 | AC62: 65.273 | AD62: 66.13 | AE62: 66.91 | AF62: 67.461 | AG62: 67.658 | AH62: 67.692 | AI62: 67.725 | AJ62: 67.797 | AK62: 67.284 | AL62: 67.691 | AM62: 68.219 | AN62: 68.859 | AO62: 69.327 | AP62: 70.088 | AQ62: 70.576 | AR62: 71.025 | AS62: 71.644 | AT62: 71.906 | AU62: 72.536 | AV62: 72.836 | AW62: 73.116 | AX62: 73.346 | AY62: 73.618 | AZ62: 73.871 | BA62: 74.144 | BB62: 74.383 | BC62: 74.609 | BD62: 74.809 | BE62: 74.992 | BF62: 75.159 | BG62: 75.31 | BH62: 75.431 | BI62: 75.555 | BJ62: 75.682 | BK62: 73.257 | BL62: 75.208 | BM62: 76.129 | BN62: 76.261 | BO62: 76.475 | BP62: DZA | BQ62: Middle East & North Africa | BR62: Upper middle income | BS62: Algeria
A63: East Asia & Pacific (excluding high income) | B63: EAP | C63: 37.84668 | D63: 43.071859 | E63: 51.168112 | F63: 51.768145 | G63: 52.417159 | H63: 52.258198 | I63: 53.393359 | J63: 54.289215 | K63: 54.832459 | L63: 55.628545 | M63: 56.320393 | N63: 57.130371 | O63: 57.715651 | P63: 58.622846 | Q63: 59.239289 | R63: 59.986851 | S63: 60.357347 | T63: 61.415143 | U63: 62.007544 | V63: 62.685172 | W63: 63.211273 | X63: 63.699859 | Y63: 64.175366 | Z63: 64.655678 | AA63: 65.086305 | AB63: 65.485224 | AC63: 65.838034 | AD63: 66.218323 | AE63: 66.562681 | AF63: 66.903771 | AG63: 67.150584 | AH63: 67.566 | AI63: 68.000611 | AJ63: 68.423224 | AK63: 68.721178 | AL63: 69.030878 | AM63: 69.425739 | AN63: 69.794844 | AO63: 70.127762 | AP63: 70.422659 | AQ63: 70.735707 | AR63: 71.074092 | AS63: 71.39675 | AT63: 71.803996 | AU63: 71.858801 | AV63: 72.398327 | AW63: 72.65187 | AX63: 72.993754 | AY63: 72.924138 | AZ63: 73.467788 | BA63: 73.761639 | BB63: 73.985745 | BC63: 74.259787 | BD63: 74.485932 | BE63: 74.719453 | BF63: 74.951124 | BG63: 75.155912 | BH63: 75.239671 | BI63: 75.578286 | BJ63: 75.768969 | BK63: 75.697639 | BL63: 75.278142 | BM63: 75.932541 | BN63: 75.880683 | BO63: 75.959316 | BP63: EAP | BS63: East Asia & Pacific (excluding high income)
A64: Early-demographic dividend | B64: EAR | C64: 46.913414 | D64: 47.404937 | E64: 47.850475 | F64: 48.254031 | G64: 48.735986 | H64: 47.751614 | I64: 48.755611 | J64: 49.435347 | K64: 50.43708 | L64: 50.83672 | M64: 50.756227 | N64: 50.131965 | O64: 51.945658 | P64: 52.360569 | Q64: 52.806231 | R64: 53.223031 | S64: 53.743027 | T64: 54.313194 | U64: 54.825594 | V64: 55.521188 | W64: 56.068907 | X64: 56.524472 | Y64: 57.019749 | Z64: 57.451068 | AA64: 57.98943 | AB64: 58.476397 | AC64: 58.931153 | AD64: 59.526278 | AE64: 59.908348 | AF64: 60.347993 | AG64: 60.638326 | AH64: 60.9285 | AI64: 61.396685 | AJ64: 61.73757 | AK64: 61.977301 | AL64: 62.404529 | AM64: 62.742784 | AN64: 63.098742 | AO64: 63.436967 | AP64: 63.77938 | AQ64: 64.21961 | AR64: 64.556705 | AS64: 64.968075 | AT64: 65.279155 | AU64: 65.513239 | AV64: 65.979786 | AW64: 66.39193 | AX64: 66.760547 | AY64: 67.021819 | AZ64: 67.496408 | BA64: 67.824443 | BB64: 68.260038 | BC64: 68.609463 | BD64: 68.962838 | BE64: 69.324976 | BF64: 69.630548 | BG64: 69.948484 | BH64: 70.272995 | BI64: 70.548666 | BJ64: 70.842406 | BK64: 69.880131 | BL64: 68.179099 | BM64: 71.430455 | BN64: 71.796245 | BO64: 72.008031 | BP64: EAR | BS64: Early-demographic dividend
A65: East Asia & Pacific | B65: EAS | C65: 41.707757 | D65: 46.321922 | E65: 53.310067 | F65: 53.910616 | G65: 54.511616 | H65: 54.382812 | I65: 55.382885 | J65: 56.318455 | K65: 56.78074 | L65: 57.497752 | M65: 58.107419 | N65: 58.895135 | O65: 59.433912 | P65: 60.238248 | Q65: 60.814616 | R65: 61.524708 | S65: 61.888864 | T65: 62.863032 | U65: 63.416217 | V65: 64.055218 | W65: 64.519653 | X65: 64.99152 | Y65: 65.452367 | Z65: 65.882113 | AA65: 66.305254 | AB65: 66.687001 | AC65: 67.039383 | AD65: 67.411771 | AE65: 67.713452 | AF65: 68.049712 | AG65: 68.282549 | AH65: 68.675193 | AI65: 69.065106 | AJ65: 69.464568 | AK65: 69.760996 | AL65: 70.024398 | AM65: 70.433304 | AN65: 70.790129 | AO65: 71.099637 | AP65: 71.367553 | AQ65: 71.702832 | AR65: 72.041306 | AS65: 72.357106 | AT65: 72.734691 | AU65: 72.812661 | AV65: 73.298435 | AW65: 73.564044 | AX65: 73.894851 | AY65: 73.848163 | AZ65: 74.368347 | BA65: 74.629979 | BB65: 74.825283 | BC65: 75.105973 | BD65: 75.334773 | BE65: 75.564427 | BF65: 75.792601 | BG65: 75.987017 | BH65: 76.078992 | BI65: 76.391423 | BJ65: 76.586241 | BK65: 76.543395 | BL65: 76.152941 | BM65: 76.676717 | BN65: 76.657202 | BO65: 76.737895 | BP65: EAS | BS65: East Asia & Pacific
A66: Europe & Central Asia (excluding high income) | B66: ECA | C66: 60.894038 | D66: 61.428816 | E66: 61.773325 | F66: 62.165329 | G66: 62.537912 | H66: 62.823863 | I66: 63.064576 | J66: 63.302164 | K66: 63.424744 | L66: 63.573619 | M66: 63.751075 | N66: 63.969152 | O66: 64.248819 | P66: 64.448485 | Q66: 64.625976 | R66: 64.741856 | S66: 64.885995 | T66: 65.109954 | U66: 65.306668 | V66: 65.490551 | W66: 65.756334 | X66: 66.002425 | Y66: 66.301253 | Z66: 66.535624 | AA66: 66.762754 | AB66: 67.237909 | AC66: 67.660854 | AD66: 67.952052 | AE66: 67.851143 | AF66: 68.262835 | AG66: 68.207885 | AH66: 68.057856 | AI66: 67.251633 | AJ66: 67.059263 | AK66: 67.307492 | AL66: 67.444737 | AM66: 67.720885 | AN66: 68.043246 | AO66: 68.339075 | AP66: 68.20278 | AQ66: 68.857053 | AR66: 69.090278 | AS66: 69.318731 | AT66: 69.587902 | AU66: 69.791149 | AV66: 69.959515 | AW66: 70.217866 | AX66: 70.557979 | AY66: 70.974318 | AZ66: 71.442292 | BA66: 71.912591 | BB66: 72.15095 | BC66: 72.673598 | BD66: 73.125829 | BE66: 73.419516 | BF66: 73.755408 | BG66: 74.031377 | BH66: 74.403354 | BI66: 74.592799 | BJ66: 74.815834 | BK66: 73.553687 | BL66: 72.882376 | BM66: 74.573168 | BN66: 74.790189 | BO66: 75.142498 | BP66: ECA | BS66: Europe & Central Asia (excluding high income)
A67: Europe & Central Asia | B67: ECS | C67: 67.419602 | D67: 67.735031 | E67: 67.693324 | F67: 68.040633 | G67: 68.525532 | H67: 68.593802 | I67: 68.808013 | J67: 68.863904 | K67: 68.826157 | L67: 68.680544 | M67: 68.979213 | N67: 69.154155 | O67: 69.385225 | P67: 69.495152 | Q67: 69.709259 | R67: 69.647127 | S67: 69.771666 | T67: 69.993348 | U67: 70.070479 | V67: 70.205516 | W67: 70.281688 | X67: 70.56516 | Y67: 70.872259 | Z67: 70.922763 | AA67: 71.062996 | AB67: 71.302507 | AC67: 71.811678 | AD67: 72.026726 | AE67: 72.105706 | AF67: 72.224994 | AG67: 72.194388 | AH67: 72.15369 | AI67: 71.854327 | AJ67: 71.531617 | AK67: 71.687124 | AL67: 71.830264 | AM67: 72.249924 | AN67: 72.645301 | AO67: 72.914693 | AP67: 72.838967 | AQ67: 73.113712 | AR67: 73.355824 | AS67: 73.446412 | AT67: 73.562747 | AU67: 73.988037 | AV67: 74.153645 | AW67: 74.639772 | AX67: 75.008654 | AY67: 75.302314 | AZ67: 75.689199 | BA67: 75.995356 | BB67: 76.479369 | BC67: 76.680497 | BD67: 77.032439 | BE67: 77.353579 | BF67: 77.330938 | BG67: 77.681282 | BH67: 77.899015 | BI67: 78.031841 | BJ67: 78.303872 | BK67: 77.175491 | BL67: 76.728643 | BM67: 77.834452 | BN67: 78.391133 | BO67: 78.598685 | BP67: ECS | BS67: Europe & Central Asia
A68: Ecuador | B68: ECU | C68: 53.396 | D68: 54.052 | E68: 54.681 | F68: 55.322 | G68: 55.95 | H68: 56.524 | I68: 57.019 | J68: 57.482 | K68: 57.946 | L68: 58.267 | M68: 58.85 | N68: 59.343 | O68: 59.816 | P68: 60.306 | Q68: 60.7 | R68: 61.085 | S68: 61.425 | T68: 61.935 | U68: 62.397 | V68: 62.854 | W68: 63.326 | X68: 63.809 | Y68: 64.271 | Z68: 64.659 | AA68: 65.202 | AB68: 65.625 | AC68: 66.123 | AD68: 66.587 | AE68: 67.038 | AF68: 67.817 | AG68: 68.445 | AH68: 69.04 | AI68: 69.468 | AJ68: 70.07 | AK68: 70.876 | AL68: 71.349 | AM68: 71.82 | AN68: 72.007 | AO68: 71.949 | AP68: 71.92 | AQ68: 72.09 | AR68: 72.571 | AS68: 73.164 | AT68: 73.632 | AU68: 73.868 | AV68: 73.909 | AW68: 74.01 | AX68: 74.226 | AY68: 74.709 | AZ68: 74.901 | BA68: 75.188 | BB68: 75.179 | BC68: 75.486 | BD68: 75.832 | BE68: 76.141 | BF68: 76.222 | BG68: 76.094 | BH68: 76.22 | BI68: 77.248 | BJ68: 77.286 | BK68: 72.004 | BL68: 72.746 | BM68: 76.577 | BN68: 77.392 | BO68: 77.579 | BP68: ECU | BQ68: Latin America & Caribbean | BR68: Upper middle income | BS68: Ecuador
A69: Egypt, Arab Rep. | B69: EGY | C69: 44.436 | D69: 45.146 | E69: 45.844 | F69: 46.493 | G69: 47.075 | H69: 47.577 | I69: 47.988 | J69: 48.13 | K69: 48.602 | L69: 48.7 | M69: 49 | N69: 49.48 | O69: 49.908 | P69: 50.098 | Q69: 51.044 | R69: 51.734 | S69: 52.484 | T69: 53.272 | U69: 54.075 | V69: 54.876 | W69: 55.673 | X69: 56.454 | Y69: 57.219 | Z69: 57.967 | AA69: 58.697 | AB69: 59.405 | AC69: 60.085 | AD69: 60.736 | AE69: 61.358 | AF69: 61.949 | AG69: 62.513 | AH69: 63.059 | AI69: 63.585 | AJ69: 64.147 | AK69: 64.663 | AL69: 65.214 | AM69: 65.733 | AN69: 66.207 | AO69: 66.635 | AP69: 67.01 | AQ69: 67.332 | AR69: 67.612 | AS69: 67.846 | AT69: 68.045 | AU69: 68.211 | AV69: 68.355 | AW69: 68.493 | AX69: 68.627 | AY69: 68.761 | AZ69: 68.915 | BA69: 69.078 | BB69: 69.232 | BC69: 69.464 | BD69: 69.632 | BE69: 69.911 | BF69: 70.135 | BG69: 70.437 | BH69: 70.709 | BI69: 70.974 | BJ69: 71.213 | BK69: 69.79 | BL69: 68.976 | BM69: 71.01 | BN69: 71.633 | BO69: 71.806 | BP69: EGY | BQ69: Middle East & North Africa | BR69: Lower middle income | BS69: Egypt, Arab Rep.
A70: Euro area | B70: EMU | C70: 69.264384 | D70: 69.661111 | E70: 69.636744 | F70: 69.797272 | G70: 70.345967 | H70: 70.429299 | I70: 70.680428 | J70: 70.862232 | K70: 70.771968 | L70: 70.688712 | M70: 71.107633 | N70: 71.258399 | O70: 71.610146 | P70: 71.7218 | Q70: 72.059143 | R70: 72.128255 | S70: 72.455601 | T70: 72.892328 | U70: 73.04526 | V70: 73.384296 | W70: 73.53246 | X70: 73.807725 | Y70: 74.151622 | Z70: 74.222519 | AA70: 74.619749 | AB70: 74.75932 | AC70: 75.053121 | AD70: 75.365742 | AE70: 75.557678 | AF70: 75.743108 | AG70: 75.817671 | AH70: 75.96768 | AI70: 76.307721 | AJ70: 76.413209 | AK70: 76.724179 | AL70: 76.882313 | AM70: 77.148324 | AN70: 77.508868 | AO70: 77.718907 | AP70: 77.945636 | AQ70: 78.199779 | AR70: 78.543543 | AS70: 78.634135 | AT70: 78.655762 | AU70: 79.232162 | AV70: 79.374851 | AW70: 79.807721 | AX70: 80.047779 | AY70: 80.251088 | AZ70: 80.455461 | BA70: 80.698943 | BB70: 81.182634 | BC70: 81.182732 | BD70: 81.467984 | BE70: 81.893061 | BF70: 81.51927 | BG70: 81.907455 | BH70: 81.883804 | BI70: 82.00276 | BJ70: 82.280421 | BK70: 81.487357 | BL70: 81.583933 | BM70: 81.622972 | BN70: 82.255521 | BO70: 82.365842 | BP70: EMU | BS70: Euro area
A71: Eritrea | B71: ERI | C71: 37.443 | D71: 37.912 | E71: 38.346 | F71: 38.833 | G71: 39.184 | H71: 39.576 | I71: 37.634 | J71: 40.151 | K71: 40.483 | L71: 40.792 | M71: 41.162 | N71: 41.527 | O71: 40.723 | P71: 41.131 | Q71: 39.001 | R71: 39.031 | S71: 42.587 | T71: 42.984 | U71: 43.38 | V71: 43.78 | W71: 44.625 | X71: 44.974 | Y71: 44.891 | Z71: 37.173 | AA71: 37.679 | AB71: 38.586 | AC71: 39.541 | AD71: 47.363 | AE71: 48.094 | AF71: 47.802 | AG71: 49.733 | AH71: 50.516 | AI71: 52.436 | AJ71: 53.189 | AK71: 54.027 | AL71: 54.822 | AM71: 55.498 | AN71: 56.155 | AO71: 49.997 | AP71: 44.506 | AQ71: 56.285 | AR71: 58.359 | AS71: 58.941 | AT71: 59.455 | AU71: 60.063 | AV71: 60.628 | AW71: 61.457 | AX71: 61.998 | AY71: 62.422 | AZ71: 63.203 | BA71: 63.665 | BB71: 64.231 | BC71: 64.697 | BD71: 65.005 | BE71: 65.517 | BF71: 65.909 | BG71: 66.242 | BH71: 66.612 | BI71: 66.979 | BJ71: 67.306 | BK71: 66.98 | BL71: 66.94 | BM71: 67.789 | BN71: 68.624 | BO71: 68.893 | BP71: ERI | BQ71: Sub-Saharan Africa | BR71: Low income | BS71: Eritrea
A72: Spain | B72: ESP | C72: 69.109268 | D72: 69.480488 | E72: 69.519024 | F72: 69.68122 | G72: 70.399756 | H72: 70.809268 | I72: 71.055122 | J72: 71.252927 | K72: 71.537805 | L72: 71.057561 | M72: 72.027317 | N72: 71.630244 | O72: 72.818049 | P72: 72.610732 | Q72: 72.969756 | R72: 73.31878 | S72: 73.642683 | T72: 74.131951 | U72: 74.29561 | V72: 74.81878 | W72: 75.349268 | X72: 75.528537 | Y72: 76.134146 | Z72: 75.909024 | AA72: 76.295366 | AB72: 76.259512 | AC72: 76.510488 | AD72: 76.728049 | AE72: 76.747073 | AF72: 76.813659 | AG72: 76.837561 | AH72: 76.97122 | AI72: 77.41 | AJ72: 77.546585 | AK72: 77.901463 | AL72: 77.980732 | AM72: 78.120488 | AN72: 78.604146 | AO72: 78.665854 | AP72: 78.717073 | AQ72: 78.965854 | AR72: 79.368293 | AS72: 79.568293 | AT72: 79.619512 | AU72: 79.870732 | AV72: 80.170732 | AW72: 80.821951 | AX72: 80.873171 | AY72: 81.17561 | AZ72: 81.47561 | BA72: 81.626829 | BB72: 82.47561 | BC72: 82.426829 | BD72: 83.078049 | BE72: 83.229268 | BF72: 82.831707 | BG72: 83.329268 | BH72: 83.282927 | BI72: 83.431707 | BJ72: 83.831707 | BK72: 82.231707 | BL72: 83.178049 | BM72: 83.134146 | BN72: 83.934146 | BO72: 83.887805 | BP72: ESP | BQ72: Europe & Central Asia | BR72: High income | BS72: Spain
A73: Estonia | B73: EST | C73: 68.749268 | D73: 69.077878 | E73: 69.292024 | F73: 69.321561 | G73: 70.072098 | H73: 70.176585 | I73: 70.146463 | J73: 70.432415 | K73: 70.08078 | L73: 69.789463 | M73: 69.92422 | N73: 70.122561 | O73: 69.929195 | P73: 70.230024 | Q73: 70.346195 | R73: 69.708122 | S73: 69.345073 | T73: 69.448951 | U73: 69.297268 | V73: 69.054317 | W73: 69.11478 | X73: 68.978049 | Y73: 69.126829 | Z73: 69.37561 | AA73: 69.278049 | AB73: 69.380488 | AC73: 70.085366 | AD73: 70.643902 | AE73: 70.697561 | AF73: 70.039024 | AG73: 69.47561 | AH73: 69.373171 | AI73: 68.863415 | AJ73: 67.909756 | AK73: 66.5 | AL73: 67.543902 | AM73: 69.612195 | AN73: 69.809756 | AO73: 69.358537 | AP73: 70.063415 | AQ73: 70.417073 | AR73: 70.258537 | AS73: 70.904878 | AT73: 71.317073 | AU73: 71.909756 | AV73: 72.568293 | AW73: 72.691463 | AX73: 72.814634 | AY73: 73.770732 | AZ73: 74.82439 | BA73: 75.429268 | BB73: 76.229268 | BC73: 76.326829 | BD73: 77.141463 | BE73: 77.034146 | BF73: 77.590244 | BG73: 77.641463 | BH73: 78.092683 | BI73: 78.243902 | BJ73: 78.646341 | BK73: 78.595122 | BL73: 76.943902 | BM73: 77.843902 | BN73: 78.792683 | BO73: 79.295122 | BP73: EST | BQ73: Europe & Central Asia | BR73: High income | BS73: Estonia
A74: Ethiopia | B74: ETH | C74: 39.615 | D74: 40.198 | E74: 40.531 | F74: 40.967 | G74: 41.261 | H74: 41.413 | I74: 39.343 | J74: 41.941 | K74: 42.092 | L74: 42.131 | M74: 42.115 | N74: 42.216 | O74: 41.035 | P74: 41.103 | Q74: 39.083 | R74: 38.941 | S74: 41.32 | T74: 41.397 | U74: 41.506 | V74: 42.376 | W74: 42.815 | X74: 43.084 | Y74: 43.434 | Z74: 36.319 | AA74: 36.737 | AB74: 37.747 | AC74: 38.371 | AD74: 45.892 | AE74: 45.682 | AF74: 45.644 | AG74: 45.117 | AH74: 46.657 | AI74: 47.279 | AJ74: 47.676 | AK74: 47.926 | AL74: 48.156 | AM74: 48.697 | AN74: 49.21 | AO74: 49.785 | AP74: 49.486 | AQ74: 50.88 | AR74: 51.428 | AS74: 52.085 | AT74: 52.877 | AU74: 53.735 | AV74: 54.364 | AW74: 55.402 | AX74: 56.566 | AY74: 57.733 | AZ74: 58.715 | BA74: 59.709 | BB74: 60.595 | BC74: 61.443 | BD74: 62.161 | BE74: 62.927 | BF74: 63.592 | BG74: 64.162 | BH74: 64.766 | BI74: 65.257 | BJ74: 65.741 | BK74: 65.969 | BL74: 65.33 | BM74: 66.897 | BN74: 67.315 | BO74: 67.603 | BP74: ETH | BQ74: Sub-Saharan Africa | BS74: Ethiopia
A75: European Union | B75: EUU | C75: 69.067102 | D75: 69.43927 | E75: 69.290908 | F75: 69.648988 | G75: 70.164734 | H75: 70.27719 | I75: 70.591456 | J75: 70.597697 | K75: 70.599292 | L75: 70.424597 | M75: 70.823861 | N75: 70.964843 | O75: 71.348957 | P75: 71.468887 | Q75: 71.782884 | R75: 71.801551 | S75: 72.072651 | T75: 72.395741 | U75: 72.487468 | V75: 72.768603 | W75: 72.792183 | X75: 73.126205 | Y75: 73.406085 | Z75: 73.451232 | AA75: 73.743295 | AB75: 73.819847 | AC75: 74.07671 | AD75: 74.323693 | AE75: 74.530884 | AF75: 74.65997 | AG75: 74.70254 | AH75: 74.81562 | AI75: 75.132047 | AJ75: 75.258692 | AK75: 75.529314 | AL75: 75.674163 | AM75: 75.926812 | AN75: 76.244549 | AO75: 76.513329 | AP75: 76.747962 | AQ75: 77.078245 | AR75: 77.425639 | AS75: 77.534075 | AT75: 77.592375 | AU75: 78.117828 | AV75: 78.275141 | AW75: 78.672128 | AX75: 78.906045 | AY75: 79.129628 | AZ75: 79.362439 | BA75: 79.635431 | BB75: 80.143951 | BC75: 80.165777 | BD75: 80.473432 | BE75: 80.876017 | BF75: 80.570797 | BG75: 80.952979 | BH75: 80.930151 | BI75: 81.031751 | BJ75: 81.319452 | BK75: 80.441475 | BL75: 80.307196 | BM75: 80.713326 | BN75: 81.424933 | BO75: 81.560847 | BP75: EUU | BS75: European Union
A76: Fragile and conflict affected situations | B76: FCS | C76: 46.115194 | D76: 46.506375 | E76: 46.998952 | F76: 47.30914 | G76: 47.676531 | H76: 47.959064 | I76: 48.083322 | J76: 48.390548 | K76: 48.80616 | L76: 49.03949 | M76: 49.471889 | N76: 49.839487 | O76: 49.865982 | P76: 50.268142 | Q76: 50.364246 | R76: 50.512358 | S76: 50.98022 | T76: 51.458301 | U76: 51.541 | V76: 51.815627 | W76: 52.061528 | X76: 52.164101 | Y76: 52.108251 | Z76: 51.577942 | AA76: 51.496371 | AB76: 51.744776 | AC76: 52.300324 | AD76: 53.085509 | AE76: 52.994102 | AF76: 53.374175 | AG76: 53.399368 | AH76: 53.370979 | AI76: 53.549556 | AJ76: 53.981631 | AK76: 54.232635 | AL76: 54.225679 | AM76: 54.237154 | AN76: 54.517824 | AO76: 54.470722 | AP76: 54.903404 | AQ76: 55.488425 | AR76: 55.721269 | AS76: 56.150857 | AT76: 56.446925 | AU76: 56.755745 | AV76: 57.147278 | AW76: 57.594311 | AX76: 58.109575 | AY76: 58.187178 | AZ76: 58.937961 | BA76: 59.343161 | BB76: 59.627636 | BC76: 60.10084 | BD76: 60.454839 | BE76: 60.553692 | BF76: 60.744993 | BG76: 60.986184 | BH76: 61.229683 | BI76: 61.782508 | BJ76: 62.137955 | BK76: 62.066368 | BL76: 61.608681 | BM76: 62.702272 | BN76: 63.349945 | BO76: 63.604841 | BP76: FCS | BS76: Fragile and conflict affected situations
A77: Finland | B77: FIN | C77: 68.819756 | D77: 68.844146 | E77: 68.577805 | F77: 69.012683 | G77: 69.220976 | H77: 68.977805 | I77: 69.477073 | J77: 69.666585 | K77: 69.616341 | L77: 69.503415 | M77: 70.179512 | N77: 70.017561 | O77: 70.707317 | P77: 71.223659 | Q77: 71.134878 | R77: 71.673659 | S77: 71.812927 | T77: 72.350244 | U77: 72.897073 | V77: 73.155366 | W77: 73.44 | X77: 73.746585 | Y77: 74.298049 | Z77: 74.200976 | AA77: 74.519024 | AB77: 74.222927 | AC77: 74.56 | AD77: 74.591951 | AE77: 74.577073 | AF77: 74.792195 | AG77: 74.813171 | AH77: 75.227561 | AI77: 75.455366 | AJ77: 75.705122 | AK77: 76.39561 | AL77: 76.409512 | AM77: 76.693415 | AN77: 76.878537 | AO77: 77.090732 | AP77: 77.29122 | AQ77: 77.465854 | AR77: 77.965854 | AS77: 78.119512 | AT77: 78.368293 | AU77: 78.714634 | AV77: 78.817073 | AW77: 79.214634 | AX77: 79.263415 | AY77: 79.568293 | AZ77: 79.719512 | BA77: 79.870732 | BB77: 80.470732 | BC77: 80.626829 | BD77: 80.97561 | BE77: 81.180488 | BF77: 81.480488 | BG77: 81.429268 | BH77: 81.631707 | BI77: 81.734146 | BJ77: 81.982927 | BK77: 81.931707 | BL77: 81.885366 | BM77: 81.187805 | BN77: 81.585366 | BO77: 82.336585 | BP77: FIN | BQ77: Europe & Central Asia | BR77: High income | BS77: Finland
A78: Fiji | B78: FJI | C78: 58.602 | D78: 59.102 | E78: 59.654 | F78: 60.155 | G78: 60.714 | H78: 61.413 | I78: 61.565 | J78: 61.442 | K78: 61.719 | L78: 61.397 | M78: 61.652 | N78: 61.74 | O78: 61.63 | P78: 60.649 | Q78: 61.194 | R78: 61.689 | S78: 62.1 | T78: 62.691 | U78: 63.065 | V78: 62.305 | W78: 62.406 | X78: 62.255 | Y78: 62.195 | Z78: 62.916 | AA78: 63.238 | AB78: 63.998 | AC78: 63.961 | AD78: 64.278 | AE78: 64.951 | AF78: 65.386 | AG78: 65.056 | AH78: 65.457 | AI78: 65.407 | AJ78: 65.51 | AK78: 65.796 | AL78: 66.007 | AM78: 66.202 | AN78: 66.293 | AO78: 66.536 | AP78: 66.728 | AQ78: 66.194 | AR78: 66.205 | AS78: 65.492 | AT78: 65.653 | AU78: 65.841 | AV78: 65.983 | AW78: 66.126 | AX78: 66.161 | AY78: 66.32 | AZ78: 66.347 | BA78: 66.778 | BB78: 66.88 | BC78: 65.812 | BD78: 66.545 | BE78: 66.581 | BF78: 66.48 | BG78: 66.657 | BH78: 67.06 | BI78: 66.965 | BJ78: 67.009 | BK78: 66.924 | BL78: 64.904 | BM78: 67.148 | BN78: 67.316 | BO78: 67.463 | BP78: FJI | BQ78: East Asia & Pacific | BR78: Upper middle income | BS78: Fiji
A79: France | B79: FRA | C79: 69.868293 | D79: 70.117073 | E79: 70.314634 | F79: 70.514634 | G79: 70.663415 | H79: 70.812195 | I79: 70.960976 | J79: 71.160976 | K79: 71.309756 | L79: 71.458537 | M79: 71.658537 | N79: 71.907317 | O79: 72.107317 | P79: 72.356098 | Q79: 72.604878 | R79: 72.853659 | S79: 73.102439 | T79: 73.35122 | U79: 73.602439 | V79: 73.85122 | W79: 74.05122 | X79: 74.3 | Y79: 74.5 | Z79: 74.8 | AA79: 75 | AB79: 75.3 | AC79: 75.6 | AD79: 75.8 | AE79: 76.1 | AF79: 76.34878 | AG79: 76.6 | AH79: 76.84878 | AI79: 77.1 | AJ79: 77.3 | AK79: 77.64878 | AL79: 77.75122 | AM79: 77.953659 | AN79: 78.304878 | AO79: 78.604878 | AP79: 78.756098 | AQ79: 79.056098 | AR79: 79.158537 | AS79: 79.260976 | AT79: 79.114634 | AU79: 80.163415 | AV79: 80.163415 | AW79: 80.812195 | AX79: 81.112195 | AY79: 81.214634 | AZ79: 81.414634 | BA79: 81.663415 | BB79: 82.114634 | BC79: 81.968293 | BD79: 82.219512 | BE79: 82.719512 | BF79: 82.321951 | BG79: 82.573171 | BH79: 82.57561 | BI79: 82.67561 | BJ79: 82.826829 | BK79: 82.17561 | BL79: 82.32439 | BM79: 82.129268 | BN79: 82.831707 | BO79: 82.980488 | BP79: FRA | BQ79: Europe & Central Asia | BR79: High income | BS79: France
A80: Faroe Islands | B80: FRO | C80: 72.107927 | D80: 72.712122 | E80: 73.17578 | F80: 73.553902 | G80: 73.855927 | H80: 74.106463 | I80: 74.316195 | J80: 74.49961 | K80: 74.696171 | L80: 74.842927 | M80: 74.97661 | N80: 75.117171 | O80: 75.214415 | P80: 75.327244 | Q80: 75.367561 | R80: 75.444341 | S80: 75.512341 | T80: 75.633512 | U80: 75.720024 | V80: 75.76278 | W80: 75.848439 | X80: 75.936854 | Y80: 76.002317 | Z80: 76.057805 | AA80: 76.120341 | AB80: 76.198171 | AC80: 75.163902 | AD80: 75.402768 | AE80: 75.642229 | AF80: 75.881076 | AG80: 76.118802 | AH80: 76.355573 | AI80: 76.591822 | AJ80: 76.828698 | AK80: 77.069454 | AL80: 77.322824 | AM80: 77.561963 | AN80: 77.785441 | AO80: 77.997995 | AP80: 78.208773 | AQ80: 78.411907 | AR80: 78.601729 | AS80: 78.787659 | AT80: 78.984807 | AU80: 79.20498 | AV80: 79.445346 | AW80: 79.689861 | AX80: 79.923824 | AY80: 80.14608 | AZ80: 80.369532 | BA80: 80.604956 | BB80: 80.85181 | BC80: 81.106095 | BD80: 81.356644 | BE80: 81.591205 | BF80: 81.799598 | BG80: 81.962112 | BH80: 82.106293 | BI80: 82.248602 | BJ80: 82.391283 | BK80: 82.534193 | BL80: 82.676322 | BM80: 82.816229 | BN80: 82.95212 | BO80: 83.083246 | BP80: FRO | BQ80: Europe & Central Asia | BR80: High income | BS80: Faroe Islands
A81: Micronesia, Fed. Sts. | B81: FSM | C81: 54.195 | D81: 54.736 | E81: 55.393 | F81: 56.004 | G81: 56.655 | H81: 57.199 | I81: 57.75 | J81: 58.305 | K81: 58.827 | L81: 59.309 | M81: 59.774 | N81: 60.182 | O81: 60.608 | P81: 60.955 | Q81: 61.319 | R81: 61.617 | S81: 61.885 | T81: 62.118 | U81: 62.306 | V81: 62.46 | W81: 62.556 | X81: 62.668 | Y81: 62.747 | Z81: 62.829 | AA81: 62.923 | AB81: 63.028 | AC81: 63.151 | AD81: 63.206 | AE81: 63.461 | AF81: 63.617 | AG81: 63.722 | AH81: 63.881 | AI81: 63.996 | AJ81: 64.041 | AK81: 64.082 | AL81: 64.142 | AM81: 64.253 | AN81: 64.371 | AO81: 64.509 | AP81: 64.626 | AQ81: 64.317 | AR81: 64.801 | AS81: 63.907 | AT81: 64.915 | AU81: 64.898 | AV81: 64.906 | AW81: 64.859 | AX81: 64.844 | AY81: 64.849 | AZ81: 64.865 | BA81: 64.892 | BB81: 64.969 | BC81: 65.08 | BD81: 65.179 | BE81: 65.294 | BF81: 65.306 | BG81: 65.576 | BH81: 65.761 | BI81: 65.943 | BJ81: 66.196 | BK81: 65.878 | BL81: 66.152 | BM81: 66.961 | BN81: 67.198 | BO81: 67.357 | BP81: FSM | BQ81: East Asia & Pacific | BR81: Lower middle income | BS81: Micronesia, Fed. Sts.
A82: Gabon | B82: GAB | C82: 46.443 | D82: 47.115 | E82: 47.777 | F82: 48.425 | G82: 48.994 | H82: 49.71 | I82: 50.322 | J82: 50.928 | K82: 51.545 | L82: 52.127 | M82: 52.697 | N82: 53.259 | O82: 53.811 | P82: 54.352 | Q82: 54.911 | R82: 55.455 | S82: 55.97 | T82: 56.467 | U82: 56.954 | V82: 57.438 | W82: 57.893 | X82: 58.332 | Y82: 58.644 | Z82: 58.994 | AA82: 59.34 | AB82: 59.665 | AC82: 59.956 | AD82: 60.2 | AE82: 60.398 | AF82: 60.584 | AG82: 60.736 | AH82: 60.891 | AI82: 61.013 | AJ82: 61.125 | AK82: 61.183 | AL82: 61.27 | AM82: 61.265 | AN82: 61.395 | AO82: 61.506 | AP82: 61.658 | AQ82: 61.81 | AR82: 61.982 | AS82: 62.175 | AT82: 62.463 | AU82: 62.694 | AV82: 62.978 | AW82: 63.259 | AX82: 63.619 | AY82: 64.011 | AZ82: 64.361 | BA82: 64.715 | BB82: 65.102 | BC82: 65.438 | BD82: 65.751 | BE82: 66.07 | BF82: 66.336 | BG82: 66.583 | BH82: 66.816 | BI82: 67.043 | BJ82: 67.337 | BK82: 67.073 | BL82: 67.072 | BM82: 67.713 | BN82: 68.337 | BO82: 68.511 | BP82: GAB | BQ82: Sub-Saharan Africa | BR82: Upper middle income | BS82: Gabon
A83: United Kingdom | B83: GBR | C83: 71.126829 | D83: 70.878049 | E83: 70.926829 | F83: 70.826829 | G83: 71.62439 | H83: 71.62439 | I83: 71.573171 | J83: 72.12439 | K83: 71.72439 | L83: 71.721951 | M83: 71.973171 | N83: 72.273171 | O83: 72.12439 | P83: 72.32439 | Q83: 72.52439 | R83: 72.72439 | S83: 72.77561 | T83: 73.22439 | U83: 73.17561 | V83: 73.27561 | W83: 73.67561 | X83: 74.026829 | Y83: 74.178049 | Z83: 74.378049 | AA83: 74.778049 | AB83: 74.629268 | AC83: 74.929268 | AD83: 75.280488 | AE83: 75.380488 | AF83: 75.582927 | AG83: 75.880488 | AH83: 76.082927 | AI83: 76.434146 | AJ83: 76.385366 | AK83: 76.885366 | AL83: 76.836585 | AM83: 77.087805 | AN83: 77.210976 | AO83: 77.190244 | AP83: 77.390244 | AQ83: 77.741463 | AR83: 77.992683 | AS83: 78.143902 | AT83: 78.446341 | AU83: 78.746341 | AV83: 79.04878 | AW83: 79.24878 | AX83: 79.44878 | AY83: 79.6 | AZ83: 80.05122 | BA83: 80.402439 | BB83: 80.95122 | BC83: 80.904878 | BD83: 81.004878 | BE83: 81.304878 | BF83: 80.956098 | BG83: 81.156098 | BH83: 81.256098 | BI83: 81.256098 | BJ83: 81.369122 | BK83: 80.331756 | BL83: 80.647317 | BM83: 81.01122 | BN83: 81.238098 | BO83: 81.386854 | BP83: GBR | BQ83: Europe & Central Asia | BR83: High income | BS83: United Kingdom
A84: Georgia | B84: GEO | C84: 61.347 | D84: 61.72 | E84: 62.078 | F84: 62.457 | G84: 62.818 | H84: 63.097 | I84: 63.397 | J84: 63.772 | K84: 64.139 | L84: 64.509 | M84: 64.869 | N84: 65.189 | O84: 65.516 | P84: 65.851 | Q84: 66.18 | R84: 66.512 | S84: 66.894 | T84: 67.246 | U84: 67.597 | V84: 67.942 | W84: 68.273 | X84: 68.741 | Y84: 69.109 | Z84: 69.135 | AA84: 68.795 | AB84: 69.006 | AC84: 69.225 | AD84: 69.219 | AE84: 68.825 | AF84: 68.635 | AG84: 68.679 | AH84: 68.202 | AI84: 67.78 | AJ84: 67.405 | AK84: 68.669 | AL84: 69.398 | AM84: 70.637 | AN84: 69.683 | AO84: 69.787 | AP84: 70.012 | AQ84: 70.091 | AR84: 70.371 | AS84: 70.438 | AT84: 71.377 | AU84: 71.011 | AV84: 70.689 | AW84: 70.983 | AX84: 70.985 | AY84: 70.949 | AZ84: 71.058 | BA84: 71.732 | BB84: 72.485 | BC84: 72.672 | BD84: 73.025 | BE84: 73.105 | BF84: 73.241 | BG84: 73.136 | BH84: 73.435 | BI84: 73.985 | BJ84: 74.165 | BK84: 73.509 | BL84: 71.635 | BM84: 74.141 | BN84: 74.496 | BO84: 74.657 | BP84: GEO | BQ84: Europe & Central Asia | BR84: Upper middle income | BS84: Georgia
A85: Ghana | B85: GHA | C85: 46.942 | D85: 47.127 | E85: 47.335 | F85: 47.476 | G85: 47.637 | H85: 47.689 | I85: 47.708 | J85: 47.734 | K85: 47.758 | L85: 47.895 | M85: 47.888 | N85: 47.949 | O85: 48.274 | P85: 48.577 | Q85: 48.918 | R85: 49.323 | S85: 49.732 | T85: 50.079 | U85: 50.461 | V85: 50.787 | W85: 51.059 | X85: 51.313 | Y85: 51.425 | Z85: 51.78 | AA85: 52.232 | AB85: 52.732 | AC85: 53.276 | AD85: 53.818 | AE85: 54.396 | AF85: 54.936 | AG85: 55.395 | AH85: 55.722 | AI85: 56.055 | AJ85: 56.286 | AK85: 56.234 | AL85: 56.662 | AM85: 56.957 | AN85: 57.241 | AO85: 57.525 | AP85: 57.835 | AQ85: 58.139 | AR85: 58.403 | AS85: 58.709 | AT85: 59.014 | AU85: 59.316 | AV85: 59.638 | AW85: 59.975 | AX85: 60.282 | AY85: 60.578 | AZ85: 60.928 | BA85: 61.297 | BB85: 61.617 | BC85: 61.995 | BD85: 62.397 | BE85: 62.832 | BF85: 63.175 | BG85: 63.522 | BH85: 63.829 | BI85: 64.138 | BJ85: 64.455 | BK85: 64.309 | BL85: 64.286 | BM85: 65.246 | BN85: 65.498 | BO85: 65.695 | BP85: GHA | BQ85: Sub-Saharan Africa | BR85: Lower middle income | BS85: Ghana
A86: Gibraltar | B86: GIB | C86: 70.209 | D86: 70.165 | E86: 70.174 | F86: 70.249 | G86: 70.438 | H86: 70.755 | I86: 71.178 | J86: 71.54 | K86: 71.709 | L86: 71.812 | M86: 71.888 | N86: 72.103 | O86: 72.356 | P86: 72.707 | Q86: 73.053 | R86: 73.322 | S86: 73.443 | T86: 73.479 | U86: 73.512 | V86: 73.585 | W86: 73.755 | X86: 73.999 | Y86: 74.325 | Z86: 74.613 | AA86: 74.935 | AB86: 75.232 | AC86: 75.557 | AD86: 75.871 | AE86: 76.18 | AF86: 76.474 | AG86: 76.814 | AH86: 77.118 | AI86: 77.412 | AJ86: 77.722 | AK86: 78.052 | AL86: 78.345 | AM86: 78.696 | AN86: 79.097 | AO86: 79.477 | AP86: 79.812 | AQ86: 80.145 | AR86: 80.419 | AS86: 80.59 | AT86: 80.713 | AU86: 80.856 | AV86: 80.991 | AW86: 81.103 | AX86: 81.269 | AY86: 81.541 | AZ86: 81.807 | BA86: 82.08 | BB86: 82.333 | BC86: 82.527 | BD86: 82.586 | BE86: 82.644 | BF86: 82.668 | BG86: 82.741 | BH86: 82.858 | BI86: 83.028 | BJ86: 83.183 | BK86: 83.07 | BL86: 80.274 | BM86: 83.517 | BN86: 83.553 | BO86: 83.63 | BP86: GIB | BQ86: Europe & Central Asia | BR86: High income | BS86: Gibraltar
A87: Guinea | B87: GIN | C87: 36.623 | D87: 36.816 | E87: 36.997 | F87: 37.196 | G87: 37.415 | H87: 37.653 | I87: 37.959 | J87: 38.224 | K87: 38.501 | L87: 38.824 | M87: 39.06 | N87: 39.372 | O87: 39.683 | P87: 39.937 | Q87: 40.229 | R87: 40.606 | S87: 41.028 | T87: 41.409 | U87: 41.882 | V87: 42.343 | W87: 42.842 | X87: 43.33 | Y87: 43.863 | Z87: 44.226 | AA87: 44.858 | AB87: 45.31 | AC87: 45.719 | AD87: 46.107 | AE87: 46.478 | AF87: 46.86 | AG87: 47.252 | AH87: 47.781 | AI87: 48.266 | AJ87: 48.819 | AK87: 49.188 | AL87: 49.836 | AM87: 50.546 | AN87: 51.113 | AO87: 51.61 | AP87: 51.987 | AQ87: 52.42 | AR87: 52.669 | AS87: 53.2 | AT87: 53.589 | AU87: 53.975 | AV87: 54.422 | AW87: 54.875 | AX87: 55.233 | AY87: 55.703 | AZ87: 56.052 | BA87: 56.431 | BB87: 56.778 | BC87: 57.117 | BD87: 57.459 | BE87: 57.581 | BF87: 57.899 | BG87: 58.49 | BH87: 58.715 | BI87: 59.043 | BJ87: 59.379 | BK87: 59.35 | BL87: 59.373 | BM87: 60.432 | BN87: 60.74 | BO87: 60.904 | BP87: GIN | BQ87: Sub-Saharan Africa | BR87: Lower middle income | BS87: Guinea
A88: Gambia, The | B88: GMB | C88: 34.574 | D88: 35.063 | E88: 35.599 | F88: 36.086 | G88: 36.579 | H88: 37.12 | I88: 37.559 | J88: 38.063 | K88: 38.533 | L88: 39.004 | M88: 39.532 | N88: 40.048 | O88: 40.549 | P88: 41.088 | Q88: 41.676 | R88: 42.192 | S88: 42.876 | T88: 43.366 | U88: 43.573 | V88: 44.517 | W88: 44.977 | X88: 44.489 | Y88: 46.25 | Z88: 46.892 | AA88: 47.513 | AB88: 48.151 | AC88: 48.798 | AD88: 49.392 | AE88: 50.146 | AF88: 50.725 | AG88: 51.278 | AH88: 51.857 | AI88: 52.477 | AJ88: 53.15 | AK88: 53.768 | AL88: 54.292 | AM88: 54.849 | AN88: 55.225 | AO88: 56.007 | AP88: 56.466 | AQ88: 56.899 | AR88: 57.283 | AS88: 57.736 | AT88: 58.223 | AU88: 58.749 | AV88: 59.11 | AW88: 59.667 | AX88: 60.001 | AY88: 60.473 | AZ88: 60.735 | BA88: 61.167 | BB88: 61.561 | BC88: 61.9 | BD88: 62.252 | BE88: 62.576 | BF88: 62.971 | BG88: 63.386 | BH88: 63.708 | BI88: 64.034 | BJ88: 64.427 | BK88: 64.418 | BL88: 63.847 | BM88: 64.859 | BN88: 65.86 | BO88: 66.057 | BP88: GMB | BQ88: Sub-Saharan Africa | BR88: Low income | BS88: Gambia, The
... A96: Guyana | B96: GUY | C96: 57.51 | D96: 57.912 | E96: 58.303 | F96: 58.644 | G96: 58.958 | H96: 59.137 | I96: 59.329 | J96: 59.53 | K96: 59.69 | L96: 59.835 | M96: 59.961 | N96: 60.068 | O96: 60.133 | P96: 60.211 | Q96: 60.305 | R96: 60.375 | S96: 60.449 | T96: 60.558 | U96: 60.646 | V96: 60.735 | W96: 60.808 | X96: 60.91 | Y96: 61.01 | Z96: 61.157 | AA96: 61.255 | AB96: 61.379 | AC96: 61.521 | AD96: 61.698 | AE96: 61.849 | AF96: 62.054 | AG96: 62.254 | AH96: 62.463 | AI96: 62.816 | AJ96: 63.016 | AK96: 63.007 | AL96: 62.668 | AM96: 62.691 | AN96: 62.879 | AO96: 63.429 | AP96: 63.772 | AQ96: 64.075 | AR96: 64.38 | AS96: 64.183 | AT96: 64.117 | AU96: 64.214 | AV96: 64.392 | AW96: 64.848 | AX96: 65.462 | AY96: 65.721 | AZ96: 66.03 | BA96: 66.204 | BB96: 66.469 | BC96: 66.443 | BD96: 66.71 | BE96: 67.334 | BF96: 67.719 | BG96: 68.069 | BH96: 68.543 | BI96: 68.829 | BJ96: 69.067 | BK96: 67.751 | BL96: 64.323 | BM96: 69.888 | BN96: 70.18 | BO96: 70.319 | BP96: GUY | BQ96: Latin America & Caribbean | BR96: High income | BS96: Guyana
A97: High income | B97: HIC | C97: 68.336473 | D97: 68.70926 | E97: 68.663908 | F97: 68.945032 | G97: 69.385162 | H97: 69.448312 | I97: 69.653209 | J97: 69.972922 | K97: 69.836495 | L97: 69.897467 | M97: 70.202545 | N97: 70.504525 | O97: 70.710901 | P97: 70.863948 | Q97: 71.200916 | R97: 71.392551 | S97: 71.610441 | T97: 71.927976 | U97: 72.059928 | V97: 72.325521 | W97: 72.341234 | X97: 72.687391 | Y97: 73.032088 | Z97: 73.107774 | AA97: 73.296953 | AB97: 73.466652 | AC97: 73.872248 | AD97: 74.108695 | AE97: 74.213601 | AF97: 74.377915 | AG97: 74.473873 | AH97: 74.582387 | AI97: 74.609195 | AJ97: 74.438243 | AK97: 74.630026 | AL97: 74.718827 | AM97: 75.182959 | AN97: 75.571683 | AO97: 75.798357 | AP97: 75.819199 | AQ97: 76.041757 | AR97: 76.314714 | AS97: 76.439404 | AT97: 76.548318 | AU97: 76.989927 | AV97: 77.109684 | AW97: 77.542288 | AX97: 77.863114 | AY97: 78.05284 | AZ97: 78.40498 | BA97: 78.595666 | BB97: 78.921125 | BC97: 79.075341 | BD97: 79.312702 | BE97: 79.565353 | BF97: 79.524319 | BG97: 79.724312 | BH97: 79.853625 | BI97: 79.966639 | BJ97: 80.199264 | BK97: 79.204145 | BL97: 78.798163 | BM97: 79.426777 | BN97: 80.149626 | BO97: 80.394368 | BP97: HIC | BS97: High income
A98: Hong Kong SAR, China | B98: HKG | C98: 65.697122 | D98: 66.441659 | E98: 66.910463 | F98: 67.645171 | G98: 68.219098 | H98: 68.866805 | I98: 69.265854 | J98: 69.827854 | K98: 70.217024 | L98: 70.627171 | M98: 70.934683 | N98: 71.468049 | O98: 71.450976 | P98: 72.090244 | Q98: 72.597805 | R98: 73.362195 | S98: 72.789024 | T98: 73.349268 | U98: 73.540732 | V98: 73.663171 | W98: 74.653415 | X98: 75.349024 | Y98: 75.438537 | Z98: 75.286341 | AA98: 76.009512 | AB98: 76.429268 | AC98: 76.68439 | AD98: 76.897805 | AE98: 77.083415 | AF98: 77.02878 | AG98: 77.370732 | AH98: 77.872927 | AI98: 77.673415 | AJ98: 78.016098 | AK98: 78.543659 | AL98: 78.67878 | AM98: 79.627561 | AN98: 80.112195 | AO98: 80.106829 | AP98: 80.372683 | AQ98: 80.873171 | AR98: 81.419268 | AS98: 81.452195 | AT98: 81.343415 | AU98: 81.799268 | AV98: 81.609024 | AW98: 82.384878 | AX98: 82.366829 | AY98: 82.340488 | AZ98: 82.775122 | BA98: 82.957561 | BB98: 83.411951 | BC98: 83.450244 | BD98: 83.83122 | BE98: 83.93561 | BF98: 84.252683 | BG98: 84.211463 | BH98: 84.69561 | BI98: 84.869756 | BJ98: 85.155854 | BK98: 85.496341 | BL98: 85.532683 | BM98: 83.660976 | BN98: 85.247317 | BO98: 85.392683 | BP98: HKG | BQ98: East Asia & Pacific | BR98: High income | BS98: Hong Kong SAR, China
A99: Honduras | B99: HND | C99: 47.149 | D99: 47.71 | E99: 48.647 | F99: 49.385 | G99: 50.197 | H99: 50.863 | I99: 51.588 | J99: 52.331 | K99: 53.041 | L99: 53.712 | M99: 54.36 | N99: 55.012 | O99: 55.689 | P99: 54.565 | Q99: 52.519 | R99: 57.523 | S99: 58.151 | T99: 58.704 | U99: 59.248 | V99: 59.829 | W99: 60.388 | X99: 61.033 | Y99: 61.688 | Z99: 62.408 | AA99: 62.819 | AB99: 63.223 | AC99: 63.651 | AD99: 64.066 | AE99: 64.393 | AF99: 64.782 | AG99: 65.183 | AH99: 65.584 | AI99: 65.908 | AJ99: 66.074 | AK99: 66.523 | AL99: 66.919 | AM99: 67.263 | AN99: 67.542 | AO99: 62.432 | AP99: 68.005 | AQ99: 68.302 | AR99: 68.491 | AS99: 68.714 | AT99: 68.874 | AU99: 69.05 | AV99: 69.198 | AW99: 69.364 | AX99: 69.539 | AY99: 69.657 | AZ99: 69.823 | BA99: 69.77 | BB99: 70.116 | BC99: 70.46 | BD99: 70.765 | BE99: 71.032 | BF99: 71.323 | BG99: 71.615 | BH99: 71.805 | BI99: 72.001 | BJ99: 72.124 | BK99: 70.864 | BL99: 69.492 | BM99: 72.715 | BN99: 72.884 | BO99: 73.044 | BP99: HND | BQ99: Latin America & Caribbean | BR99: Lower middle income | BS99: Honduras
A100: Heavily indebted poor countries (HIPC) | B100: HPC | C100: 40.799038 | D100: 41.114819 | E100: 41.693417 | F100: 41.931846 | G100: 42.269363 | H100: 42.600484 | I100: 42.718011 | J100: 43.360105 | K100: 43.681765 | L100: 43.97317 | M100: 44.286788 | N100: 44.435617 | O100: 44.246888 | P100: 44.814675 | Q100: 44.892006 | R100: 45.263825 | S100: 45.907538 | T100: 46.268849 | U100: 46.424913 | V100: 46.774531 | W100: 47.196742 | X100: 47.445199 | Y100: 47.627193 | Z100: 46.614137 | AA100: 46.581022 | AB100: 46.990788 | AC100: 47.850986 | AD100: 49.091018 | AE100: 49.38401 | AF100: 49.631539 | AG100: 49.672867 | AH100: 49.639861 | AI100: 49.885745 | AJ100: 50.533608 | AK100: 50.316479 | AL100: 51.116777 | AM100: 51.26012 | AN100: 51.593342 | AO100: 51.685556 | AP100: 52.165512 | AQ100: 53.002777 | AR100: 53.535003 | AS100: 54.057895 | AT100: 54.607738 | AU100: 55.151439 | AV100: 55.777539 | AW100: 56.573949 | AX100: 57.246067 | AY100: 57.855688 | AZ100: 58.239341 | BA100: 58.732594 | BB100: 59.230201 | BC100: 60.085602 | BD100: 60.628343 | BE100: 61.040385 | BF100: 61.561898 | BG100: 62.003891 | BH100: 62.315299 | BI100: 62.798616 | BJ100: 63.089862 | BK100: 63.072806 | BL100: 62.531465 | BM100: 63.840466 | BN100: 64.715916 | BO100: 64.91806 | BP100: HPC | BS100: Heavily indebted poor countries (HIPC)
A101: Croatia | B101: HRV | C101: 65.746488 | D101: 66.346146 | E101: 67.065268 | F101: 67.422146 | G101: 67.848878 | H101: 68.278195 | I101: 68.711829 | J101: 68.845024 | K101: 68.699073 | L101: 68.766293 | M101: 68.989122 | N101: 69.264171 | O101: 69.573927 | P101: 69.923902 | Q101: 70.433341 | R101: 70.001951 | S101: 70.455366 | T101: 70.74439 | U101: 70.53878 | V101: 70.427317 | W101: 70.175366 | X101: 70.34439 | Y101: 70.482683 | Z101: 70.274878 | AA101: 70.218537 | AB101: 70.886098 | AC101: 71.419024 | AD101: 71.470244 | AE101: 71.488293 | AF101: 71.844634 | AG101: 72.170488 | AH101: 72.185366 | AI101: 71.241463 | AJ101: 71.522439 | AK101: 71.803415 | AL101: 72.08439 | AM101: 72.365366 | AN101: 72.495122 | AO101: 72.317073 | AP101: 72.641951 | AQ101: 72.807805 | AR101: 74.512927 | AS101: 74.717317 | AT101: 74.613902 | AU101: 75.520244 | AV101: 75.244634 | AW101: 75.836829 | AX101: 75.70561 | AY101: 75.912195 | AZ101: 76.168293 | BA101: 76.47561 | BB101: 76.77561 | BC101: 77.168293 | BD101: 77.570732 | BE101: 77.72439 | BF101: 77.27561 | BG101: 77.921951 | BH101: 77.726829 | BI101: 77.919512 | BJ101: 78.22439 | BK101: 77.52439 | BL101: 76.42439 | BM101: 77.57561 | BN101: 78.473171 | BO101: 78.929268 | BP101: HRV | BQ101: Europe & Central Asia | BR101: High income | BS101: Croatia
A102: Haiti | B102: HTI | C102: 43.44 | D102: 43.825 | E102: 44.196 | F102: 42.724 | G102: 44.928 | H102: 45.371 | I102: 45.565 | J102: 46.135 | K102: 46.522 | L102: 46.903 | M102: 47.265 | N102: 47.619 | O102: 47.884 | P102: 48.194 | Q102: 48.458 | R102: 48.72 | S102: 48.972 | T102: 49.226 | U102: 49.484 | V102: 49.749 | W102: 49.971 | X102: 50.31 | Y102: 50.626 | Z102: 50.946 | AA102: 51.254 | AB102: 51.583 | AC102: 51.874 | AD102: 52.245 | AE102: 52.554 | AF102: 52.88 | AG102: 53.215 | AH102: 53.524 | AI102: 54.041 | AJ102: 54.478 | AK102: 54.731 | AL102: 55.582 | AM102: 56.111 | AN102: 56.675 | AO102: 57.137 | AP102: 57.692 | AQ102: 58.175 | AR102: 58.591 | AS102: 59.041 | AT102: 59.44 | AU102: 58.517 | AV102: 60.318 | AW102: 60.74 | AX102: 61.09 | AY102: 61.28 | AZ102: 61.694 | BA102: 45.577 | BB102: 61.581 | BC102: 62.273 | BD102: 62.624 | BE102: 62.969 | BF102: 63.224 | BG102: 63.325 | BH102: 63.832 | BI102: 64.077 | BJ102: 64.328 | BK102: 63.773 | BL102: 62.613 | BM102: 63.948 | BN102: 64.936 | BO102: 65.119 | BP102: HTI | BQ102: Latin America & Caribbean | BR102: Lower middle income | BS102: Haiti
A103: Hungary | B103: HUN | C103: 68.003171 | D103: 68.936098 | E103: 67.865854 | F103: 68.874146 | G103: 69.380976 | H103: 69.07122 | I103: 69.822439 | J103: 69.407073 | K103: 69.230244 | L103: 69.314634 | M103: 69.164634 | N103: 69.052439 | O103: 69.664634 | P103: 69.518049 | Q103: 69.248049 | R103: 69.29 | S103: 69.573171 | T103: 69.848049 | U103: 69.393902 | V103: 69.615366 | W103: 69.061707 | X103: 69.139268 | Y103: 69.357805 | Z103: 68.973659 | AA103: 69.025854 | AB103: 68.972195 | AC103: 69.173415 | AD103: 69.65122 | AE103: 70.023415 | AF103: 69.461707 | AG103: 69.31561 | AH103: 69.377073 | AI103: 69.117073 | AJ103: 69.10122 | AK103: 69.469756 | AL103: 69.791707 | AM103: 70.32878 | AN103: 70.702439 | AO103: 70.557805 | AP103: 70.677073 | AQ103: 71.246341 | AR103: 72.24878 | AS103: 72.34878 | AT103: 72.3 | AU103: 72.64878 | AV103: 72.64878 | AW103: 73.097561 | AX103: 73.15122 | AY103: 73.702439 | AZ103: 73.904878 | BA103: 74.207317 | BB103: 74.858537 | BC103: 75.063415 | BD103: 75.565854 | BE103: 75.763415 | BF103: 75.568293 | BG103: 76.063415 | BH103: 75.817073 | BI103: 76.065854 | BJ103: 76.319512 | BK103: 75.419512 | BL103: 74.065854 | BM103: 75.868293 | BN103: 76.570732 | BO103: 76.72439 | BP103: HUN | BQ103: Europe & Central Asia | BR103: High income | BS103: Hungary
A104: IBRD only | B104: IBD | C104: 45.922232 | D104: 48.618886 | E104: 52.517686 | F104: 53.047016 | G104: 53.520724 | H104: 53.227673 | I104: 53.919898 | J104: 54.432445 | K104: 55.135353 | L104: 55.589581 | M104: 56.052323 | N104: 56.643848 | O104: 57.08443 | P104: 57.691511 | Q104: 58.210144 | R104: 58.780743 | S104: 59.116178 | T104: 59.849559 | U104: 60.325813 | V104: 60.814177 | W104: 61.214715 | X104: 61.653051 | Y104: 62.104928 | Z104: 62.572274 | AA104: 62.982063 | AB104: 63.392027 | AC104: 63.86722 | AD104: 64.224298 | AE104: 64.533707 | AF104: 64.890618 | AG104: 65.108272 | AH104: 65.475125 | AI104: 65.724173 | AJ104: 65.975442 | AK104: 66.256073 | AL104: 66.632248 | AM104: 67.025304 | AN104: 67.396741 | AO104: 67.72444 | AP104: 67.967326 | AQ104: 68.286965 | AR104: 68.584714 | AS104: 68.904376 | AT104: 69.172756 | AU104: 69.3984 | AV104: 69.826517 | AW104: 70.150124 | AX104: 70.514245 | AY104: 70.762446 | AZ104: 71.160213 | BA104: 71.50218 | BB104: 71.827033 | BC104: 72.16367 | BD104: 72.463347 | BE104: 72.750965 | BF104: 73.032849 | BG104: 73.259231 | BH104: 73.485761 | BI104: 73.794944 | BJ104: 74.031272 | BK104: 73.295136 | BL104: 71.974203 | BM104: 74.251282 | BN104: 74.517979 | BO104: 74.672909 | BP104: IBD | BS104: IBRD only
A105: IDA & IBRD total | B105: IBT | C105: 45.347942 | D105: 47.655264 | E105: 50.968326 | F105: 51.4612 | G105: 51.952973 | H105: 51.752745 | I105: 52.41419 | J105: 52.913603 | K105: 53.58081 | L105: 54.020161 | M105: 54.309223 | N105: 54.369381 | O105: 55.400562 | P105: 55.973654 | Q105: 56.425122 | R105: 56.918361 | S105: 57.289658 | T105: 57.958131 | U105: 58.395243 | V105: 58.89941 | W105: 59.308244 | X105: 59.713724 | Y105: 60.113602 | Z105: 60.443487 | AA105: 60.783305 | AB105: 61.150767 | AC105: 61.611203 | AD105: 61.999269 | AE105: 62.264564 | AF105: 62.59477 | AG105: 62.772724 | AH105: 62.991225 | AI105: 63.254063 | AJ105: 63.502865 | AK105: 63.72656 | AL105: 64.0772 | AM105: 64.399347 | AN105: 64.732439 | AO105: 65.000598 | AP105: 65.287398 | AQ105: 65.656106 | AR105: 65.966771 | AS105: 66.293696 | AT105: 66.586916 | AU105: 66.823845 | AV105: 67.224748 | AW105: 67.6015 | AX105: 67.966098 | AY105: 68.183519 | AZ105: 68.587127 | BA105: 68.925852 | BB105: 69.234898 | BC105: 69.573326 | BD105: 69.868661 | BE105: 70.120459 | BF105: 70.371721 | BG105: 70.614049 | BH105: 70.830897 | BI105: 71.153016 | BJ105: 71.393931 | BK105: 70.74885 | BL105: 69.667929 | BM105: 71.677599 | BN105: 71.998537 | BO105: 72.132597 | BP105: IBT | BS105: IDA & IBRD total
A106: IDA total | B106: IDA | C106: 42.59808 | D106: 43.102659 | E106: 43.701935 | F106: 44.038516 | G106: 44.635241 | H106: 44.892 | I106: 45.430717 | J106: 45.89545 | K106: 46.425818 | L106: 46.822526 | M106: 46.338705 | N106: 43.986116 | O106: 47.735497 | P106: 48.194176 | Q106: 48.390927 | R106: 48.58914 | S106: 49.174517 | T106: 49.613701 | U106: 49.946715 | V106: 50.596698 | W106: 51.115373 | X106: 51.447663 | Y106: 51.696393 | Z106: 51.523562 | AA106: 51.64819 | AB106: 51.919563 | AC106: 52.397861 | AD106: 52.987416 | AE106: 53.148825 | AF106: 53.449439 | AG106: 53.550863 | AH106: 53.275195 | AI106: 53.697229 | AJ106: 54.052072 | AK106: 54.174008 | AL106: 54.544342 | AM106: 54.721291 | AN106: 55.029637 | AO106: 55.197167 | AP106: 55.754796 | AQ106: 56.409926 | AR106: 56.879176 | AS106: 57.348246 | AT106: 57.841815 | AU106: 58.227206 | AV106: 58.648344 | AW106: 59.312151 | AX106: 59.794049 | AY106: 60.024866 | AZ106: 60.55401 | BA106: 60.987672 | BB106: 61.348631 | BC106: 61.782478 | BD106: 62.141161 | BE106: 62.366898 | BF106: 62.613598 | BG106: 62.991989 | BH106: 63.273744 | BI106: 63.730965 | BJ106: 64.088569 | BK106: 63.802357 | BL106: 63.477424 | BM106: 64.8823 | BN106: 65.453527 | BO106: 65.635124 | BP106: IDA | BS106: IDA total
A107: IDA blend | B107: IDB | C107: 42.543125 | D107: 43.119033 | E107: 43.975047 | F107: 44.560082 | G107: 45.185534 | H107: 45.688687 | I107: 46.384658 | J107: 46.607802 | K107: 47.502404 | L107: 48.02901 | M107: 48.783853 | N107: 47.673053 | O107: 49.823966 | P107: 50.234603 | Q107: 50.640711 | R107: 51.081647 | S107: 51.688386 | T107: 52.147823 | U107: 52.562537 | V107: 53.000967 | W107: 53.551714 | X107: 53.99797 | Y107: 54.352161 | Z107: 54.609944 | AA107: 54.802146 | AB107: 54.920044 | AC107: 54.93852 | AD107: 55.007397 | AE107: 55.03753 | AF107: 55.088193 | AG107: 54.966497 | AH107: 54.835389 | AI107: 54.783651 | AJ107: 54.760376 | AK107: 54.664233 | AL107: 54.645905 | AM107: 54.617097 | AN107: 54.653435 | AO107: 54.896799 | AP107: 55.224966 | AQ107: 55.599272 | AR107: 55.889906 | AS107: 56.270236 | AT107: 56.635913 | AU107: 57.029456 | AV107: 56.998929 | AW107: 57.70162 | AX107: 58.060091 | AY107: 58.414305 | AZ107: 58.750784 | BA107: 59.051513 | BB107: 59.364406 | BC107: 59.630564 | BD107: 59.868573 | BE107: 60.099868 | BF107: 60.294495 | BG107: 60.576166 | BH107: 60.818393 | BI107: 61.074054 | BJ107: 61.325997 | BK107: 60.818007 | BL107: 60.876536 | BM107: 62.128864 | BN107: 62.462164 | BO107: 62.619941 | BP107: IDB | BS107: IDA blend
A108: Indonesia | B108: IDN | C108: 46.835 | D108: 47.385 | E108: 48.141 | F108: 48.742 | G108: 49.44 | H108: 42.762 | I108: 48.406 | J108: 51.309 | K108: 51.888 | L108: 52.588 | M108: 53.254 | N108: 53.823 | O108: 54.364 | P108: 54.916 | Q108: 55.443 | R108: 55.998 | S108: 56.445 | T108: 57.09 | U108: 57.607 | V108: 58.18 | W108: 58.701 | X108: 59.096 | Y108: 59.7 | Z108: 60.343 | AA108: 60.891 | AB108: 61.387 | AC108: 61.736 | AD108: 62.087 | AE108: 62.386 | AF108: 62.883 | AG108: 63.249 | AH108: 63.703 | AI108: 64.182 | AJ108: 64.851 | AK108: 65.041 | AL108: 65.263 | AM108: 65.465 | AN108: 65.774 | AO108: 65.942 | AP108: 66.001 | AQ108: 66.292 | AR108: 66.583 | AS108: 66.954 | AT108: 67.134 | AU108: 65.521 | AV108: 67.531 | AW108: 67.664 | AX108: 67.914 | AY108: 68.085 | AZ108: 68.267 | BA108: 68.364 | BB108: 68.629 | BC108: 68.862 | BD108: 69.064 | BE108: 69.292 | BF108: 69.52 | BG108: 69.733 | BH108: 69.953 | BI108: 70.08 | BJ108: 70.349 | BK108: 68.817 | BL108: 67.452 | BM108: 70.925 | BN108: 71.146 | BO108: 71.288 | BP108: IDN | BQ108: East Asia & Pacific | BR108: Upper middle income | BS108: Indonesia
A109: IDA only | B109: IDX | C109: 42.62332 | D109: 43.095132 | E109: 43.57626 | F109: 43.798187 | G109: 44.381344 | H109: 44.523955 | I109: 44.989447 | J109: 45.565622 | K109: 45.926949 | L109: 46.262758 | M109: 45.201693 | N109: 42.26539 | O109: 46.757315 | P109: 47.236298 | Q109: 47.331908 | R109: 47.410559 | S109: 47.979219 | T109: 48.401058 | U109: 48.687867 | V109: 49.432982 | W109: 49.921725 | X109: 50.180743 | Y109: 50.366139 | Z109: 49.971052 | AA109: 50.055964 | AB109: 50.39697 | AC109: 51.101047 | AD109: 51.95041 | AE109: 52.173444 | AF109: 52.598417 | AG109: 52.811099 | AH109: 52.454977 | AI109: 53.124723 | AJ109: 53.678767 | AK109: 53.915465 | AL109: 54.49071 | AM109: 54.776404 | AN109: 55.228986 | AO109: 55.356642 | AP109: 56.036562 | AQ109: 56.842115 | AR109: 57.408276 | AS109: 57.925426 | AT109: 58.487965 | AU109: 58.870309 | AV109: 59.535555 | AW109: 60.179655 | AX109: 60.730699 | AY109: 60.898029 | AZ109: 61.535023 | BA109: 62.044439 | BB109: 62.433839 | BC109: 62.96017 | BD109: 63.385853 | BE109: 63.608285 | BF109: 63.882192 | BG109: 64.3102 | BH109: 64.609933 | BI109: 65.172942 | BJ109: 65.582914 | BK109: 65.411606 | BL109: 64.876531 | BM109: 66.360075 | BN109: 67.053839 | BO109: 67.242529 | BP109: IDX | BS109: IDA only
A110: Isle of Man | B110: IMN | C110: 64.557 | D110: 64.425 | E110: 64.397 | F110: 64.458 | G110: 64.666 | H110: 64.922 | I110: 65.18 | J110: 65.409 | K110: 65.542 | L110: 65.626 | M110: 65.724 | N110: 65.841 | O110: 65.991 | P110: 66.238 | Q110: 66.478 | R110: 66.76 | S110: 67.051 | T110: 67.357 | U110: 67.689 | V110: 68.071 | W110: 68.446 | X110: 68.811 | Y110: 69.142 | Z110: 69.457 | AA110: 69.754 | AB110: 70.02 | AC110: 70.34 | AD110: 70.685 | AE110: 71.057 | AF110: 71.406 | AG110: 71.8 | AH110: 72.183 | AI110: 72.544 | AJ110: 72.822 | AK110: 73.14 | AL110: 73.371 | AM110: 73.634 | AN110: 73.9 | AO110: 74.204 | AP110: 74.469 | AQ110: 74.842 | AR110: 75.289 | AS110: 75.785 | AT110: 76.319 | AU110: 76.876 | AV110: 77.453 | AW110: 77.971 | AX110: 78.451 | AY110: 78.899 | AZ110: 79.303 | BA110: 79.613 | BB110: 79.836 | BC110: 80.007 | BD110: 80.12 | BE110: 80.199 | BF110: 80.267 | BG110: 80.391 | BH110: 80.506 | BI110: 80.614 | BJ110: 80.74 | BK110: 80.591 | BL110: 80.42 | BM110: 80.956 | BN110: 80.999 | BO110: 81.091 | BP110: IMN | BQ110: Europe & Central Asia | BR110: High income | BS110: Isle of Man
A111: India | B111: IND | C111: 45.61 | D111: 45.824 | E111: 46.133 | F111: 46.458 | G111: 46.742 | H111: 45.558 | I111: 45.884 | J111: 46.184 | K111: 47.925 | L111: 48.26 | M111: 48.585 | N111: 48.902 | O111: 49.213 | P111: 49.642 | Q111: 50.259 | R111: 50.761 | S111: 51.302 | T111: 51.822 | U111: 52.42 | V111: 53.014 | W111: 53.593 | X111: 54.173 | Y111: 54.735 | Z111: 55.283 | AA111: 55.813 | AB111: 56.324 | AC111: 56.819 | AD111: 57.291 | AE111: 57.744 | AF111: 58.196 | AG111: 58.618 | AH111: 59.032 | AI111: 59.445 | AJ111: 59.823 | AK111: 60.237 | AL111: 60.63 | AM111: 61.027 | AN111: 61.439 | AO111: 61.852 | AP111: 62.284 | AQ111: 62.749 | AR111: 63.158 | AS111: 63.649 | AT111: 64.086 | AU111: 64.484 | AV111: 64.939 | AW111: 65.373 | AX111: 65.803 | AY111: 66.247 | AZ111: 66.7 | BA111: 67.162 | BB111: 67.623 | BC111: 68.076 | BD111: 68.499 | BE111: 68.932 | BF111: 69.326 | BG111: 69.709 | BH111: 70.068 | BI111: 70.415 | BJ111: 70.746 | BK111: 70.156 | BL111: 67.282 | BM111: 71.698 | BN111: 72.003 | BO111: 72.235 | BP111: IND | BQ111: South Asia | BR111: Lower middle income | BS111: India
A112: Ireland | B112: IRL | C112: 70.194268 | D112: 69.678293 | E112: 69.991049 | F112: 70.230098 | G112: 70.489927 | H112: 70.695 | I112: 70.216951 | J112: 71.245366 | K112: 70.941 | L112: 70.852829 | M112: 70.901561 | N112: 71.675854 | O112: 71.021756 | P112: 71.239976 | Q112: 71.175561 | R112: 71.753049 | S112: 71.85661 | T112: 71.99739 | U112: 71.996317 | V112: 72.268024 | W112: 72.595415 | X112: 72.95178 | Y112: 73.209049 | Z112: 73.240098 | AA112: 73.663732 | AB112: 73.621902 | AC112: 73.665537 | AD112: 74.431902 | AE112: 74.439415 | AF112: 74.45522 | AG112: 74.846073 | AH112: 75.025 | AI112: 75.415098 | AJ112: 75.292195 | AK112: 75.786634 | AL112: 75.469317 | AM112: 75.831707 | AN112: 75.985366 | AO112: 76.180488 | AP112: 76.082927 | AQ112: 76.536585 | AR112: 77.134146 | AS112: 77.634146 | AT112: 78.139024 | AU112: 78.539024 | AV112: 78.943902 | AW112: 79.241463 | AX112: 79.641463 | AY112: 80.095122 | AZ112: 80.190244 | BA112: 80.743902 | BB112: 80.746341 | BC112: 80.846341 | BD112: 80.94878 | BE112: 81.34878 | BF112: 81.453659 | BG112: 81.653659 | BH112: 82.156098 | BI112: 82.204878 | BJ112: 82.702439 | BK112: 82.456098 | BL112: 82.253659 | BM112: 82.509756 | BN112: 82.807317 | BO112: 83.009756 | BP112: IRL | BQ112: Europe & Central Asia | BR112: High income | BS112: Ireland
A113: Not classified | B113: INX
A114: Iran, Islamic Rep. | B114: IRN | C114: 43.297 | D114: 43.9 | E114: 43.769 | F114: 45.105 | G114: 45.735 | H114: 46.372 | I114: 47.072 | J114: 47.803 | K114: 47.946 | L114: 49.382 | M114: 50.222 | N114: 51.12 | O114: 51.729 | P114: 52.944 | Q114: 53.862 | R114: 54.819 | S114: 55.771 | T114: 56.66 | U114: 56.042 | V114: 58.453 | W114: 58.369 | X114: 56.625 | Y114: 57.633 | Z114: 58.518 | AA114: 60.875 | AB114: 61.537 | AC114: 62.136 | AD114: 62.685 | AE114: 63.255 | AF114: 65.314 | AG114: 64.066 | AH114: 66.233 | AI114: 66.653 | AJ114: 67.037 | AK114: 67.49 | AL114: 67.904 | AM114: 68.328 | AN114: 68.649 | AO114: 69.214 | AP114: 69.686 | AQ114: 70.166 | AR114: 70.619 | AS114: 71.112 | AT114: 70.464 | AU114: 72.04 | AV114: 72.446 | AW114: 72.895 | AX114: 73.299 | AY114: 73.683 | AZ114: 74.041 | BA114: 74.39 | BB114: 74.721 | BC114: 75.039 | BD114: 75.349 | BE114: 75.635 | BF114: 75.907 | BG114: 76.155 | BH114: 76.396 | BI114: 76.621 | BJ114: 76.855 | BK114: 74.141 | BL114: 73.752 | BM114: 76.799 | BN114: 77.654 | BO114: 77.854 | BP114: IRN | BQ114: Middle East & North Africa | BR114: Upper middle income | BS114: Iran, Islamic Rep.
A115: Iraq | B115: IRQ | C115: 51.462 | D115: 52.339 | E115: 53.482 | F115: 54.36 | G115: 55.245 | H115: 56.387 | I115: 57.321 | J115: 58.422 | K115: 58.969 | L115: 59.64 | M115: 60.532 | N115: 61.333 | O115: 61.816 | P115: 62.344 | Q115: 60.995 | R115: 61.434 | S115: 63.569 | T115: 63.896 | U115: 64.175 | V115: 64.417 | W115: 60.916 | X115: 58.652 | Y115: 58.977 | Z115: 59.287 | AA115: 59.544 | AB115: 59.8 | AC115: 60.031 | AD115: 60.259 | AE115: 56.692 | AF115: 57.501 | AG115: 57.587 | AH115: 61.338 | AI115: 65.344 | AJ115: 65.31 | AK115: 65.027 | AL115: 64.761 | AM115: 64.618 | AN115: 64.241 | AO115: 64.405 | AP115: 64.532 | AQ115: 64.86 | AR115: 65.292 | AS115: 65.724 | AT115: 64.834 | AU115: 64.634 | AV115: 64.899 | AW115: 64.029 | AX115: 64.428 | AY115: 66.465 | AZ115: 67.834 | BA115: 68.092 | BB115: 68.435 | BC115: 68.827 | BD115: 69.047 | BE115: 69.679 | BF115: 69.977 | BG115: 68.683 | BH115: 69.788 | BI115: 71.116 | BJ115: 71.245 | BK115: 69.651 | BL115: 70.704 | BM115: 72.037 | BN115: 72.324 | BO115: 72.424 | BP115: IRQ | BQ115: Middle East & North Africa | BR115: Upper middle income | BS115: Iraq
A116: Iceland | B116: ISL | C116: 74.040073 | D116: 73.503415 | E116: 73.721951 | F116: 73.042927 | G116: 73.541707 | H116: 73.86878 | I116: 73.300488 | J116: 73.783171 | K116: 74.005854 | L116: 73.776341 | M116: 73.933902 | N116: 73.570488 | O116: 74.455854 | P116: 74.450976 | Q116: 74.511707 | R116: 75.57878 | S116: 76.972195 | T116: 76.373659 | U116: 76.649268 | V116: 76.773171 | W116: 76.846585 | X116: 76.521463 | Y116: 77.037805 | Z116: 76.84561 | AA116: 77.576585 | AB116: 77.602439 | AC116: 77.990732 | AD116: 77.339024 | AE116: 77.082927 | AF116: 78.140976 | AG116: 78.036341 | AH116: 77.991951 | AI116: 78.760244 | AJ116: 78.934634 | AK116: 79.247073 | AL116: 77.98439 | AM116: 78.777805 | AN116: 78.885366 | AO116: 79.602439 | AP116: 79.35122 | AQ116: 79.653659 | AR116: 80.690244 | AS116: 80.502439 | AT116: 80.963415 | AU116: 80.997561 | AV116: 81.502439 | AW116: 81.158537 | AX116: 81.453659 | AY116: 81.609756 | AZ116: 81.75122 | BA116: 81.897561 | BB116: 82.358537 | BC116: 82.917073 | BD116: 82.060976 | BE116: 82.860976 | BF116: 82.468293 | BG116: 82.204878 | BH116: 82.660976 | BI116: 82.860976 | BJ116: 83.163415 | BK116: 83.063415 | BL116: 83.165854 | BM116: 82.119512 | BN116: 82.456098 | BO116: 82.809756 | BP116: ISL | BQ116: Europe & Central Asia | BR116: High income | BS116: Iceland
A117: Israel | B117: ISR | D117: 72.006585 | E117: 72.112195 | I117: 72.28561 | J117: 71.509756 | K117: 71.056585 | L117: 70.970488 | M117: 71.213415 | N117: 71.719024 | O117: 71.078049 | P117: 71.693415 | Q117: 71.661707 | R117: 72.045122 | S117: 72.956098 | T117: 72.958537 | U117: 73.207317 | V117: 73.507317 | W117: 73.87561 | X117: 74.260976 | Y117: 74.109756 | Z117: 74.458537 | AA117: 74.807317 | AB117: 75.207317 | AC117: 74.956098 | AD117: 75.258537 | AE117: 74.436585 | AF117: 76.307317 | AG117: 76.607317 | AH117: 76.758537 | AI117: 76.504878 | AJ117: 77.153659 | AK117: 77.402439 | AL117: 77.45122 | AM117: 78.104878 | AN117: 78 | AO117: 78.14878 | AP117: 78.658537 | AQ117: 78.953659 | AR117: 79.407317 | AS117: 79.45122 | AT117: 79.64878 | AU117: 80.146341 | AV117: 80.15122 | AW117: 80.553659 | AX117: 80.504878 | AY117: 80.95122 | AZ117: 81.404878 | BA117: 81.602439 | BB117: 81.656098 | BC117: 81.704878 | BD117: 82.056098 | BE117: 82.153659 | BF117: 82.05122 | BG117: 82.407317 | BH117: 82.55122 | BI117: 82.802439 | BJ117: 82.804878 | BK117: 82.64878 | BL117: 82.5 | BM117: 82.7 | BN117: 83.195122 | BO117: 83.197561 | BP117: ISR | BQ117: Middle East & North Africa | BR117: High income | BS117: Israel
A118: Italy | B118: ITA | C118: 69.123902 | D118: 69.760244 | E118: 69.149756 | F118: 69.248049 | G118: 70.311707 | H118: 70.171707 | I118: 70.926098 | J118: 70.956585 | K118: 70.78 | L118: 70.811951 | M118: 71.55878 | N118: 71.806829 | O118: 72.075366 | P118: 72.026341 | Q118: 72.73439 | R118: 72.647317 | S118: 72.991951 | T118: 73.364634 | U118: 73.693171 | V118: 74.002683 | W118: 73.943171 | X118: 74.353902 | Y118: 74.814634 | Z118: 74.640244 | AA118: 75.389512 | AB118: 75.470732 | AC118: 75.770732 | AD118: 76.219512 | AE118: 76.370732 | AF118: 76.819512 | AG118: 76.970732 | AH118: 77.019512 | AI118: 77.419512 | AJ118: 77.721951 | AK118: 77.921951 | AL118: 78.170732 | AM118: 78.521951 | AN118: 78.82439 | AO118: 78.97561 | AP118: 79.42439 | AQ118: 79.778049 | AR118: 80.126829 | AS118: 80.229268 | AT118: 79.982927 | AU118: 80.780488 | AV118: 80.782927 | AW118: 81.282927 | AX118: 81.434146 | AY118: 81.485366 | AZ118: 81.636585 | BA118: 82.036585 | BB118: 82.187805 | BC118: 82.239024 | BD118: 82.690244 | BE118: 83.090244 | BF118: 82.543902 | BG118: 83.243902 | BH118: 82.946341 | BI118: 83.346341 | BJ118: 83.497561 | BK118: 82.195122 | BL118: 82.646341 | BM118: 82.7 | BN118: 83.35122 | BO118: 83.95122 | BP118: ITA | BQ118: Europe & Central Asia | BR118: High income | BS118: Italy
A119: Jamaica | B119: JAM | C119: 63.828 | D119: 64.257 | E119: 64.619 | F119: 64.999 | G119: 65.347 | H119: 65.663 | I119: 65.928 | J119: 66.086 | K119: 66.319 | L119: 66.516 | M119: 66.731 | N119: 66.997 | O119: 67.304 | P119: 67.607 | Q119: 67.913 | R119: 68.168 | S119: 68.412 | T119: 68.586 | U119: 68.739 | V119: 68.813 | W119: 68.992 | X119: 69.12 | Y119: 69.253 | Z119: 69.546 | AA119: 69.809 | AB119: 70.101 | AC119: 70.446 | AD119: 70.87 | AE119: 71.161 | AF119: 71.512 | AG119: 71.705 | AH119: 71.787 | AI119: 71.816 | AJ119: 71.758 | AK119: 71.624 | AL119: 71.488 | AM119: 71.328 | AN119: 71.216 | AO119: 71.17 | AP119: 71.189 | AQ119: 71.281 | AR119: 71.287 | AS119: 71.478 | AT119: 71.585 | AU119: 71.542 | AV119: 71.493 | AW119: 71.395 | AX119: 71.405 | AY119: 71.502 | AZ119: 71.717 | BA119: 71.979 | BB119: 72.245 | BC119: 72.405 | BD119: 72.435 | BE119: 72.357 | BF119: 72.214 | BG119: 72.052 | BH119: 71.879 | BI119: 71.606 | BJ119: 71.532 | BK119: 71.452 | BL119: 69.085 | BM119: 71.481 | BN119: 71.479 | BO119: 71.606 | BP119: JAM | BQ119: Latin America & Caribbean | BR119: Upper middle income | BS119: Jamaica
A120: Jordan | B120: JOR | C120: 52.678 | D120: 53.68 | E120: 54.633 | F120: 55.489 | G120: 56.456 | H120: 57.317 | I120: 57.762 | J120: 58.97 | K120: 59.767 | L120: 60.504 | M120: 59.833 | N120: 61.772 | O120: 62.477 | P120: 63.065 | Q120: 63.611 | R120: 64.148 | S120: 64.654 | T120: 65.127 | U120: 65.602 | V120: 66.049 | W120: 66.493 | X120: 66.92 | Y120: 67.36 | Z120: 67.778 | AA120: 68.206 | AB120: 68.587 | AC120: 68.962 | AD120: 69.297 | AE120: 69.605 | AF120: 69.865 | AG120: 70.094 | AH120: 70.24 | AI120: 70.4 | AJ120: 70.568 | AK120: 70.738 | AL120: 70.915 | AM120: 71.105 | AN120: 71.324 | AO120: 71.521 | AP120: 71.737 | AQ120: 71.926 | AR120: 72.141 | AS120: 72.359 | AT120: 72.585 | AU120: 72.788 | AV120: 72.977 | AW120: 73.225 | AX120: 73.407 | AY120: 73.563 | AZ120: 73.707 | BA120: 73.797 | BB120: 73.929 | BC120: 74.087 | BD120: 74.282 | BE120: 74.606 | BF120: 75.06 | BG120: 75.55 | BH120: 76.071 | BI120: 76.491 | BJ120: 76.865 | BK120: 75.583 | BL120: 74.204 | BM120: 77.088 | BN120: 77.814 | BO120: 77.981 | BP120: JOR | BQ120: Middle East & North Africa | BR120: Lower middle income | BS120: Jordan
A121: Japan | B121: JPN | C121: 67.69561 | D121: 68.351951 | E121: 68.634878 | F121: 69.712439 | G121: 70.206585 | H121: 70.266829 | I121: 70.915854 | J121: 71.466098 | K121: 71.610976 | L121: 71.858049 | M121: 71.919756 | N121: 72.809024 | O121: 73.153659 | P121: 73.295122 | Q121: 73.672195 | R121: 74.247073 | S121: 74.686585 | T121: 75.255854 | U121: 75.584634 | V121: 76.10878 | W121: 75.989024 | X121: 76.394878 | Y121: 76.873659 | Z121: 76.921951 | AA121: 77.29122 | AB121: 77.560488 | AC121: 78.010488 | AD121: 78.429512 | AE121: 78.349756 | AF121: 78.768537 | AG121: 78.837073 | AH121: 79.036829 | AI121: 79.080244 | AJ121: 79.303659 | AK121: 79.696829 | AL121: 79.536098 | AM121: 80.219756 | AN121: 80.424146 | AO121: 80.501463 | AP121: 80.460976 | AQ121: 81.076098 | AR121: 81.416341 | AS121: 81.690732 | AT121: 81.76 | AU121: 82.030244 | AV121: 81.955122 | AW121: 82.321951 | AX121: 82.507073 | AY121: 82.587561 | AZ121: 82.931463 | BA121: 82.842683 | BB121: 82.59122 | BC121: 83.096098 | BD121: 83.331951 | BE121: 83.587805 | BF121: 83.793902 | BG121: 83.984878 | BH121: 84.099756 | BI121: 84.210976 | BJ121: 84.356341 | BK121: 84.56 | BL121: 84.44561 | BM121: 83.996341 | BN121: 84.04122 | BO121: 84.036341 | BP121: JPN | BQ121: East Asia & Pacific | BR121: High income | BS121: Japan
A122: Kazakhstan | B122: KAZ | C122: 57.946 | D122: 58.169 | E122: 58.392 | F122: 58.612 | G122: 58.83 | H122: 59.042 | I122: 59.247 | J122: 59.446 | K122: 59.643 | L122: 59.843 | M122: 60.049 | N122: 60.262 | O122: 60.48 | P122: 60.697 | Q122: 60.908 | R122: 61.11 | S122: 61.301 | T122: 61.517 | U122: 61.765 | V122: 62.072 | W122: 62.516 | X122: 62.996 | Y122: 63.586 | Z122: 64.224 | AA122: 64.839 | AB122: 65.376 | AC122: 65.788 | AD122: 65.996 | AE122: 66.032 | AF122: 65.915 | AG122: 65.701 | AH122: 65.379 | AI122: 64.978 | AJ122: 64.538 | AK122: 64.108 | AL122: 63.717 | AM122: 63.455 | AN122: 63.318 | AO122: 63.349 | AP122: 63.528 | AQ122: 63.793 | AR122: 64.108 | AS122: 64.441 | AT122: 64.753 | AU122: 65.04 | AV122: 65.356 | AW122: 65.722 | AX122: 66.18 | AY122: 66.759 | AZ122: 67.46 | BA122: 68.257 | BB122: 69.108 | BC122: 69.939 | BD122: 70.719 | BE122: 71.415 | BF122: 72.024 | BG122: 72.549 | BH122: 72.996 | BI122: 73.369 | BJ122: 73.658 | BK122: 71.195 | BL122: 70.131 | BM122: 73.503 | BN122: 74.402 | BO122: 74.531 | BP122: KAZ | BQ122: Europe & Central Asia | BR122: Upper middle income | BS122: Kazakhstan
...

Sheet Avg
A3: Row Labels | B3: Average of 2024 | C3: Average of 2020
B4: 72.106629 | C4: 70.508778
A5: East Asia & Pacific | B5: 74.114659 | C5: 73.433013
A6: Europe & Central Asia | B6: 79.26316 | C6: 77.751736
A7: Latin America & Caribbean | B7: 75.519823 | C7: 73.800964
A8: Middle East & North Africa | B8: 75.925572 | C8: 74.081405
A9: North America | B9: 81.162764 | C9: 79.988829
A10: South Asia | B10: 75.003333 | C10: 73.096167
A11: Sub-Saharan Africa | B11: 64.778003 | C11: 62.97966
A12: Grand Total | B12: 73.659383 | C12: 72.130009

Sheet Fact_WorldBank (2)
A1: Country Name | B1: Country Code | C1: Year | D1: Value
A2: Aruba | B2: ABW | C2: 1960 | D2: 64.049
A3: Aruba | B3: ABW | C3: 1961 | D3: 64.215
A4: Aruba | B4: ABW | C4: 1962 | D4: 64.602
A5: Aruba | B5: ABW | C5: 1963 | D5: 64.944
A6: Aruba | B6: ABW | C6: 1964 | D6: 65.303
A7: Aruba | B7: ABW | C7: 1965 | D7: 65.615
A8: Aruba | B8: ABW | C8: 1966 | D8: 66.126
A9: Aruba | B9: ABW | C9: 1967 | D9: 66.385
A10: Aruba | B10: ABW | C10: 1968 | D10: 66.744
A11: Aruba | B11: ABW | C11: 1969 | D11: 67.098
A12: Aruba | B12: ABW | C12: 1970 | D12: 67.44
A13: Aruba | B13: ABW | C13: 1971 | D13: 67.783
... A17192: Zimbabwe | B17192: ZWE | C17192: 2024 | D17192: 63.064

Sheet Dim_Year
A1: Year
A2: 1960
A3: 1961
A4: 1962
A5: 1963
A6: 1964
A7: 1965
A8: 1966
A9: 1967
A10: 1968
A11: 1969
A12: 1970
A13: 1971
... A17192: 2024

Sheet LifeExpctClean
A1: Country Name | B1: Country Code | C1: 1960 | D1: 1961 | E1: 1962 | F1: 1963 | G1: 1964 | H1: 1965 | I1: 1966 | J1: 1967 | K1: 1968 | L1: 1969 | M1: 1970 | N1: 1971 | O1: 1972 | P1: 1973 | Q1: 1974 | R1: 1975 | S1: 1976 | T1: 1977 | U1: 1978 | V1: 1979 | W1: 1980 | X1: 1981 | Y1: 1982 | Z1: 1983 | AA1: 1984 | AB1: 1985 | AC1: 1986 | AD1: 1987 | AE1: 1988 | AF1: 1989 | AG1: 1990 | AH1: 1991 | AI1: 1992 | AJ1: 1993 | AK1: 1994 | AL1: 1995 | AM1: 1996 | AN1: 1997 | AO1: 1998 | AP1: 1999 | AQ1: 2000 | AR1: 2001 | AS1: 2002 | AT1: 2003 | AU1: 2004 | AV1: 2005 | AW1: 2006 | AX1: 2007 | AY1: 2008 | AZ1: 2009 | BA1: 2010 | BB1: 2011 | BC1: 2012 | BD1: 2013 | BE1: 2014 | BF1: 2015 | BG1: 2016 | BH1: 2017 | BI1: 2018 | BJ1: 2019 | BK1: 2020 | BL1: 2021 | BM1: 2022 | BN1: 2023 | BO1: 2024 | BP1: Region | BQ1: Income Level
A2: Aruba | B2: ABW | C2: 64.049 | D2: 64.215 | E2: 64.602 | F2: 64.944 | G2: 65.303 | H2: 65.615 | I2: 66.126 | J2: 66.385 | K2: 66.744 | L2: 67.098 | M2: 67.44 | N2: 67.783 | O2: 68.335 | P2: 68.862 | Q2: 69.278 | R2: 69.564 | S2: 69.808 | T2: 70.054 | U2: 70.271 | V2: 70.507 | W2: 70.771 | X2: 71.344 | Y2: 71.485 | Z2: 71.606 | AA2: 71.711 | AB2: 71.792 | AC2: 71.831 | AD2: 72.448 | AE2: 72.519 | AF2: 72.531 | AG2: 72.546 | AH2: 72.592 | AI2: 72.717 | AJ2: 72.777 | AK2: 72.796 | AL2: 72.832 | AM2: 72.856 | AN2: 72.904 | AO2: 72.94 | AP2: 72.857 | AQ2: 72.939 | AR2: 73.044 | AS2: 73.135 | AT2: 73.236 | AU2: 73.223 | AV2: 73.415 | AW2: 73.498 | AX2: 73.642 | AY2: 73.783 | AZ2: 73.974 | BA2: 74.297 | BB2: 74.578 | BC2: 74.841 | BD2: 75.072 | BE2: 75.261 | BF2: 75.405 | BG2: 75.54 | BH2: 75.62 | BI2: 75.88 | BJ2: 76.019 | BK2: 75.406 | BL2: 73.655 | BM2: 76.226 | BN2: 76.353 | BO2: 76.5
A3: Africa Eastern and Southern | B3: AFE | C3: 44.169658 | D3: 44.468838 | E3: 44.87789 | F3: 45.160583 | G3: 45.535695 | H3: 45.770723 | I3: 45.765725 | J3: 46.440745 | K3: 46.738632 | L3: 46.977476 | M3: 47.248006 | N3: 47.464016 | O3: 47.166792 | P3: 47.746608 | Q3: 47.744328 | R3: 47.968548 | S3: 48.568138 | T3: 48.860725 | U3: 48.983917 | V3: 49.416988 | W3: 49.816713 | X3: 50.020493 | Y3: 50.290829 | Z3: 48.904096 | AA3: 48.997959 | AB3: 49.392902 | AC3: 50.009761 | AD3: 51.068943 | AE3: 50.876607 | AF3: 51.265874 | AG3: 51.096326 | AH3: 50.873244 | AI3: 50.715946 | AJ3: 51.073762 | AK3: 50.966589 | AL3: 51.482057 | AM3: 51.35319 | AN3: 51.570887 | AO3: 51.317955 | AP3: 51.807077 | AQ3: 52.557342 | AR3: 52.875536 | AS3: 53.206744 | AT3: 53.678305 | AU3: 54.192928 | AV3: 54.807681 | AW3: 55.693515 | AX3: 56.484353 | AY3: 57.240106 | AZ3: 58.095527 | BA3: 58.827279 | BB3: 59.200004 | BC3: 60.249512 | BD3: 60.89574 | BE3: 61.251436 | BF3: 61.713031 | BG3: 62.167981 | BH3: 62.591275 | BI3: 63.330691 | BJ3: 63.857261 | BK3: 63.766484 | BL3: 62.979999 | BM3: 64.487152 | BN3: 65.146228 | BO3: 65.34993
A4: Afghanistan | B4: AFG | C4: 32.799 | D4: 33.291 | E4: 33.757 | F4: 34.201 | G4: 34.673 | H4: 35.124 | I4: 35.583 | J4: 36.042 | K4: 36.51 | L4: 36.979 | M4: 37.46 | N4: 37.932 | O4: 38.423 | P4: 38.951 | Q4: 39.469 | R4: 39.994 | S4: 40.518 | T4: 41.082 | U4: 40.086 | V4: 38.844 | W4: 39.258 | X4: 39.406 | Y4: 36.058 | Z4: 36.517 | AA4: 31.473 | AB4: 32.132 | AC4: 38.4 | AD4: 38.831 | AE4: 43.238 | AF4: 44.496 | AG4: 45.118 | AH4: 45.521 | AI4: 46.569 | AJ4: 51.021 | AK4: 50.969 | AL4: 52.103 | AM4: 52.83 | AN4: 53.212 | AO4: 52.487 | AP4: 54.532 | AQ4: 55.005 | AR4: 55.511 | AS4: 56.225 | AT4: 57.171 | AU4: 57.81 | AV4: 58.247 | AW4: 58.553 | AX4: 58.956 | AY4: 59.708 | AZ4: 60.248 | BA4: 60.702 | BB4: 61.25 | BC4: 61.735 | BD4: 62.188 | BE4: 62.26 | BF4: 62.27 | BG4: 62.646 | BH4: 62.406 | BI4: 62.443 | BJ4: 62.941 | BK4: 61.454 | BL4: 60.417 | BM4: 65.617 | BN4: 66.035 | BO4: 66.289 | BP4: Middle East & North Africa | BQ4: Low income
A5: Africa Western and Central | B5: AFW | C5: 37.779636 | D5: 38.058973 | E5: 38.681792 | F5: 38.936918 | G5: 39.19458 | H5: 39.479784 | I5: 39.719265 | J5: 39.529359 | K5: 40.25889 | L5: 40.567814 | M5: 41.277939 | N5: 41.730102 | O5: 42.356132 | P5: 42.868104 | Q5: 43.437155 | R5: 43.967079 | S5: 44.75257 | T5: 45.362264 | U5: 45.876278 | V5: 46.328507 | W5: 46.696229 | X5: 47.075219 | Y5: 47.373942 | Z5: 47.619559 | AA5: 47.797646 | AB5: 47.944482 | AC5: 48.038163 | AD5: 48.139567 | AE5: 48.371525 | AF5: 48.496155 | AG5: 48.459467 | AH5: 48.531229 | AI5: 48.688726 | AJ5: 48.855051 | AK5: 48.859717 | AL5: 49.027301 | AM5: 49.11178 | AN5: 49.21897 | AO5: 49.45259 | AP5: 49.823913 | AQ5: 50.29817 | AR5: 50.677996 | AS5: 51.108247 | AT5: 51.578364 | AU5: 52.106342 | AV5: 52.55603 | AW5: 52.978931 | AX5: 53.482672 | AY5: 53.916483 | AZ5: 53.852486 | BA5: 54.603593 | BB5: 54.964195 | BC5: 55.292945 | BD5: 55.55511 | BE5: 55.69563 | BF5: 56.038519 | BG5: 56.392598 | BH5: 56.626622 | BI5: 57.037104 | BJ5: 57.149956 | BK5: 57.364736 | BL5: 57.362736 | BM5: 57.98785 | BN5: 58.85574 | BO5: 59.049811
A6: Angola | B6: AGO | C6: 37.933 | D6: 36.902 | E6: 37.168 | F6: 37.419 | G6: 37.704 | H6: 37.968 | I6: 38.258 | J6: 38.616 | K6: 38.968 | L6: 39.329 | M6: 39.688 | N6: 40.076 | O6: 40.469 | P6: 40.871 | Q6: 41.26 | R6: 40.817 | S6: 40.812 | T6: 41.215 | U6: 41.573 | V6: 41.913 | W6: 42.242 | X6: 42.556 | Y6: 42.857 | Z6: 41.972 | AA6: 42.245 | AB6: 42.495 | AC6: 42.739 | AD6: 40.786 | AE6: 41.471 | AF6: 41.698 | AG6: 41.854 | AH6: 43.812 | AI6: 42.267 | AJ6: 42.19 | AK6: 43.567 | AL6: 46.139 | AM6: 46.418 | AN6: 46.688 | AO6: 45.452 | AP6: 45.808 | AQ6: 46.501 | AR6: 47.032 | AS6: 47.874 | AT6: 50.218 | AU6: 51.123 | AV6: 52.13 | AW6: 52.965 | AX6: 54.2 | AY6: 55.281 | AZ6: 56.225 | BA6: 57.242 | BB6: 58.093 | BC6: 58.916 | BD6: 59.705 | BE6: 60.396 | BF6: 61.042 | BG6: 61.619 | BH6: 62.122 | BI6: 62.622 | BJ6: 63.051 | BK6: 63.116 | BL6: 62.958 | BM6: 64.246 | BN6: 64.617 | BO6: 64.805 | BP6: Sub-Saharan Africa | BQ6: Lower middle income
A7: Albania | B7: ALB | C7: 56.413 | D7: 57.488 | E7: 58.494 | F7: 59.479 | G7: 60.404 | H7: 61.273 | I7: 62.149 | J7: 62.976 | K7: 63.788 | L7: 64.538 | M7: 65.234 | N7: 65.896 | O7: 66.526 | P7: 67.107 | Q7: 67.633 | R7: 68.12 | S7: 68.57 | T7: 68.992 | U7: 69.367 | V7: 69.617 | W7: 69.903 | X7: 70.145 | Y7: 70.425 | Z7: 70.705 | AA7: 70.984 | AB7: 71.282 | AC7: 71.665 | AD7: 71.981 | AE7: 72.217 | AF7: 72.457 | AG7: 72.71 | AH7: 73.001 | AI7: 73.303 | AJ7: 73.638 | AK7: 73.837 | AL7: 74.022 | AM7: 74.113 | AN7: 73.383 | AO7: 74.357 | AP7: 74.568 | AQ7: 74.826 | AR7: 75.083 | AS7: 75.299 | AT7: 75.557 | AU7: 75.951 | AV7: 76.427 | AW7: 76.994 | AX7: 77.691 | AY7: 78.248 | AZ7: 78.509 | BA7: 78.414 | BB7: 78.303 | BC7: 78.084 | BD7: 77.995 | BE7: 78.029 | BF7: 78.358 | BG7: 78.643 | BH7: 78.9 | BI7: 79.238 | BJ7: 79.467 | BK7: 77.824 | BL7: 76.844 | BM7: 78.769 | BN7: 79.602 | BO7: 79.776 | BP7: Europe & Central Asia | BQ7: Upper middle income
A8: Andorra | B8: AND | C8: 72.094 | D8: 72.573 | E8: 72.993 | F8: 73.298 | G8: 73.624 | H8: 73.856 | I8: 74.02 | J8: 74.119 | K8: 74.22 | L8: 74.296 | M8: 74.452 | N8: 74.615 | O8: 74.864 | P8: 75.096 | Q8: 75.34 | R8: 75.567 | S8: 75.869 | T8: 76.154 | U8: 76.488 | V8: 76.819 | W8: 77.137 | X8: 77.391 | Y8: 77.617 | Z8: 77.787 | AA8: 77.916 | AB8: 78.006 | AC8: 78.107 | AD8: 78.189 | AE8: 78.364 | AF8: 78.557 | AG8: 78.961 | AH8: 79.346 | AI8: 79.794 | AJ8: 80.186 | AK8: 80.587 | AL8: 80.804 | AM8: 81.009 | AN8: 81.145 | AO8: 81.28 | AP8: 81.55 | AQ8: 81.863 | AR8: 82.162 | AS8: 82.448 | AT8: 82.718 | AU8: 82.815 | AV8: 83.086 | AW8: 83.374 | AX8: 83.632 | AY8: 83.855 | AZ8: 84.1 | BA8: 84.197 | BB8: 84.296 | BC8: 84.334 | BD8: 84.406 | BE8: 84.485 | BF8: 84.532 | BG8: 84.489 | BH8: 84.359 | BI8: 84.242 | BJ8: 84.098 | BK8: 79.418 | BL8: 82.331 | BM8: 84.016 | BN8: 84.041 | BO8: 84.188 | BP8: Europe & Central Asia | BQ8: High income
A9: Arab World | B9: ARB | C9: 44.794056 | D9: 45.545371 | E9: 45.993769 | F9: 46.979338 | G9: 47.570034 | H9: 48.117159 | I9: 48.625424 | J9: 49.092434 | K9: 49.657787 | L9: 50.148857 | M9: 50.692871 | N9: 51.318319 | O9: 51.89371 | P9: 52.30196 | Q9: 52.92555 | R9: 53.420351 | S9: 53.850649 | T9: 55.081922 | U9: 55.757128 | V9: 56.479748 | W9: 57.006353 | X9: 57.569166 | Y9: 57.870235 | Z9: 58.637607 | AA9: 59.329582 | AB9: 59.989461 | AC9: 60.918684 | AD9: 61.620809 | AE9: 61.671533 | AF9: 62.298247 | AG9: 62.755973 | AH9: 62.827507 | AI9: 63.575576 | AJ9: 64.60128 | AK9: 64.850083 | AL9: 65.202506 | AM9: 65.526889 | AN9: 65.852992 | AO9: 66.193579 | AP9: 66.549934 | AQ9: 66.8907 | AR9: 67.240617 | AS9: 67.58063 | AT9: 67.650335 | AU9: 67.733103 | AV9: 68.040502 | AW9: 68.491265 | AX9: 68.879226 | AY9: 69.258133 | AZ9: 69.706904 | BA9: 69.807322 | BB9: 69.363338 | BC9: 69.842317 | BD9: 70.192106 | BE9: 70.535067 | BF9: 70.658012 | BG9: 70.896488 | BH9: 71.112856 | BI9: 71.4313 | BJ9: 71.839893 | BK9: 70.726559 | BL9: 70.404114 | BM9: 71.876096 | BN9: 72.444678 | BO9: 72.721805
A10: United Arab Emirates | B10: ARE | C10: 50.651 | D10: 51.596 | E10: 52.546 | F10: 53.509 | G10: 54.495 | H10: 55.512 | I10: 56.572 | J10: 57.648 | K10: 58.727 | L10: 59.764 | M10: 60.78 | N10: 61.753 | O10: 62.675 | P10: 63.542 | Q10: 64.351 | R10: 65.105 | S10: 65.806 | T10: 66.471 | U10: 67.083 | V10: 67.645 | W10: 68.157 | X10: 68.622 | Y10: 69.056 | Z10: 69.448 | AA10: 69.802 | AB10: 70.123 | AC10: 70.41 | AD10: 70.623 | AE10: 70.808 | AF10: 70.96 | AG10: 71.074 | AH10: 71.144 | AI10: 71.166 | AJ10: 71.159 | AK10: 71.204 | AL10: 71.392 | AM10: 71.82 | AN10: 72.559 | AO10: 73.66 | AP10: 74.982 | AQ10: 76.347 | AR10: 77.621 | AS10: 78.721 | AT10: 79.6 | AU10: 80.272 | AV10: 80.779 | AW10: 81.155 | AX10: 81.438 | AY10: 81.591 | AZ10: 81.679 | BA10: 81.886 | BB10: 81.898 | BC10: 81.913 | BD10: 81.95 | BE10: 81.99 | BF10: 82.076 | BG10: 82.195 | BH10: 82.388 | BI10: 82.449 | BJ10: 82.596 | BK10: 81.936 | BL10: 79.083 | BM10: 80.487 | BN10: 82.909 | BO10: 83.069 | BP10: Middle East & North Africa | BQ10: High income
A11: Argentina | B11: ARG | C11: 64.242 | D11: 64.631 | E11: 64.618 | F11: 64.855 | G11: 64.816 | H11: 65.053 | I11: 65.398 | J11: 65.467 | K11: 65.234 | L11: 65.085 | M11: 65.647 | N11: 65.619 | O11: 65.953 | P11: 66.186 | Q11: 66.405 | R11: 66.965 | S11: 67.03 | T11: 67.595 | U11: 67.999 | V11: 68.434 | W11: 68.576 | X11: 68.858 | Y11: 68.973 | Z11: 69.29 | AA11: 69.353 | AB11: 69.879 | AC11: 70.281 | AD11: 70.699 | AE11: 71.097 | AF11: 71.502 | AG11: 71.615 | AH11: 72.02 | AI11: 72.096 | AJ11: 72.303 | AK11: 72.732 | AL11: 72.864 | AM11: 73.056 | AN11: 73.407 | AO11: 73.412 | AP11: 73.683 | AQ11: 73.91 | AR11: 74.154 | AS11: 74.312 | AT11: 74.307 | AU11: 74.871 | AV11: 75.231 | AW11: 75.279 | AX11: 74.783 | AY11: 75.428 | AZ11: 75.577 | BA11: 75.68 | BB11: 76.1 | BC11: 75.802 | BD11: 75.829 | BE11: 76.268 | BF11: 76.6 | BG11: 76.105 | BH11: 76.543 | BI11: 76.77 | BJ11: 76.847 | BK11: 75.878 | BL11: 73.948 | BM11: 75.806 | BN11: 77.395 | BO11: 77.543 | BP11: Latin America & Caribbean | BQ11: Upper middle income
A12: Armenia | B12: ARM | C12: 59.063 | D12: 59.494098 | E12: 59.916683 | F12: 60.328268 | G12: 60.723829 | H12: 61.099341 | I12: 61.453829 | J12: 61.784756 | K12: 62.093634 | L12: 62.379951 | M12: 62.644707 | N12: 62.888902 | O12: 63.114488 | P12: 63.330927 | Q12: 63.546756 | R12: 63.767878 | S12: 64.001488 | T12: 64.253951 | U12: 64.526195 | V12: 64.820829 | W12: 65.138561 | X12: 65.482488 | Y12: 65.850927 | Z12: 66.229244 | AA12: 66.591366 | AB12: 66.915268 | AC12: 67.178 | AD12: 67.359073 | AE12: 52.600122 | AF12: 67.518561 | AG12: 67.549366 | AH12: 67.627049 | AI12: 67.718537 | AJ12: 67.973195 | AK12: 68.271805 | AL12: 68.628488 | AM12: 69.006122 | AN12: 69.393829 | AO12: 69.799341 | AP12: 70.198951 | AQ12: 72.880488 | AR12: 72.97561 | AS12: 72.826829 | AT12: 72.826829 | AU12: 73.026829 | AV12: 73.07561 | AW12: 72.82439 | AX12: 72.873171 | AY12: 73.073171 | AZ12: 73.073171 | BA12: 73.173171 | BB12: 73.817073 | BC12: 74.119512 | BD12: 74.621951 | BE12: 74.873171 | BF12: 74.870732 | BG12: 74.868293 | BH12: 75.217073 | BI12: 75.619512 | BJ12: 76.221951 | BK12: 73.37561 | BL12: 72.278049 | BM12: 74.765854 | BN12: 77.465854 | BO12: 78.319512 | BP12: Europe & Central Asia | BQ12: Upper middle income
A13: American Samoa | B13: ASM | C13: 65.053 | D13: 65.648 | E13: 66.008 | F13: 66.161 | G13: 66.135 | H13: 65.996 | I13: 58.284 | J13: 65.807 | K13: 65.847 | L13: 66.05 | M13: 66.364 | N13: 66.77 | O13: 67.186 | P13: 67.604 | Q13: 67.95 | R13: 68.256 | S13: 68.475 | T13: 68.701 | U13: 68.881 | V13: 69.114 | W13: 69.413 | X13: 69.731 | Y13: 69.975 | Z13: 70.163 | AA13: 70.326 | AB13: 70.532 | AC13: 70.704 | AD13: 70.828 | AE13: 70.883 | AF13: 70.929 | AG13: 71.107 | AH13: 71.312 | AI13: 71.511 | AJ13: 71.54 | AK13: 71.569 | AL13: 71.565 | AM13: 71.576 | AN13: 71.606 | AO13: 71.542 | AP13: 71.484 | AQ13: 71.443 | AR13: 71.573 | AS13: 71.755 | AT13: 71.698 | AU13: 72.277 | AV13: 72.382 | AW13: 72.397 | AX13: 72.365 | AY13: 72.43 | AZ13: 70.839 | BA13: 72.587 | BB13: 72.662 | BC13: 72.709 | BD13: 72.769 | BE13: 72.687 | BF13: 72.654 | BG13: 72.64 | BH13: 72.801 | BI13: 72.794 | BJ13: 72.751 | BK13: 72.672 | BL13: 72.708 | BM13: 72.752 | BN13: 72.852 | BO13: 72.992 | BP13: East Asia & Pacific | BQ13: High income
A14: Antigua and Barbuda | B14: ATG | C14: 62.635 | D14: 63.335 | E14: 63.995 | F14: 64.697 | G14: 65.428 | H14: 66.171 | I14: 66.902 | J14: 67.586 | K14: 68.23 | L14: 68.827 | M14: 69.371 | N14: 69.861 | O14: 70.304 | P14: 70.71 | Q14: 71.095 | R14: 71.447 | S14: 71.794 | T14: 72.149 | U14: 72.5 | V14: 72.823 | W14: 73.094 | X14: 73.32 | Y14: 73.525 | Z14: 73.684 | AA14: 73.808 | AB14: 73.873 | AC14: 73.893 | AD14: 73.873 | AE14: 73.811 | AF14: 73.628 | AG14: 73.602 | AH14: 73.472 | AI14: 73.386 | AJ14: 73.39 | AK14: 73.493 | AL14: 73.576 | AM14: 73.839 | AN14: 74.045 | AO14: 74.187 | AP14: 74.456 | AQ14: 74.819 | AR14: 75.108 | AS14: 75.237 | AT14: 75.313 | AU14: 75.329 | AV14: 75.364 | AW14: 75.506 | AX14: 75.72 | AY14: 76.075 | AZ14: 76.386 | BA14: 76.701 | BB14: 77.023 | BC14: 77.1 | BD14: 77.05 | BE14: 76.912 | BF14: 76.892 | BG14: 76.968 | BH14: 77.03 | BI14: 77.132 | BJ14: 77.168 | BK14: 77.161 | BL14: 77.197 | BM14: 77.483 | BN14: 77.598 | BO14: 77.766 | BP14: Latin America & Caribbean | BQ14: High income
A15: Australia | B15: AUS | C15: 70.817073 | D15: 70.973171 | E15: 70.942439 | F15: 70.911707 | G15: 70.880976 | H15: 70.850244 | I15: 70.819512 | J15: 70.869268 | K15: 70.919024 | L15: 70.96878 | M15: 71.018537 | N15: 71.068293 | O15: 71.457561 | P15: 71.846829 | Q15: 72.236098 | R15: 72.625366 | S15: 73.014634 | T15: 73.34439 | U15: 73.674146 | V15: 74.003902 | W15: 74.333659 | X15: 74.663415 | Y15: 74.904878 | Z15: 75.146341 | AA15: 75.387805 | AB15: 75.629268 | AC15: 75.870732 | AD15: 76.151707 | AE15: 76.432683 | AF15: 76.713659 | AG15: 76.994634 | AH15: 77.27561 | AI15: 77.378049 | AJ15: 77.878049 | AK15: 77.878049 | AL15: 77.829268 | AM15: 78.078049 | AN15: 78.480488 | AO15: 78.631707 | AP15: 78.931707 | AQ15: 79.234146 | AR15: 79.634146 | AS15: 79.936585 | AT15: 80.239024 | AU15: 80.490244 | AV15: 80.841463 | AW15: 81.041463 | AX15: 81.292683 | AY15: 81.395122 | AZ15: 81.543902 | BA15: 81.695122 | BB15: 81.895122 | BC15: 82.046341 | BD15: 82.14878 | BE15: 82.3 | BF15: 82.4 | BG15: 82.44878 | BH15: 82.5 | BI15: 82.74878 | BJ15: 82.9 | BK15: 83.2 | BL15: 83.3 | BM15: 83.2 | BN15: 83.05122 | BO15: 83.05122 | BP15: East Asia & Pacific | BQ15: High income
A16: Austria | B16: AUT | C16: 68.58561 | D16: 69.577317 | E16: 69.309512 | F16: 69.443659 | G16: 69.921951 | H16: 69.722195 | I16: 70.045854 | J16: 69.917805 | K16: 70.057561 | L16: 69.833171 | M16: 69.914634 | N16: 70.114634 | O16: 70.463415 | P16: 71.014634 | Q16: 71.012195 | R16: 71.114634 | S16: 71.565854 | T16: 71.914634 | U16: 72.012195 | V16: 72.312195 | W16: 72.463415 | X16: 72.812195 | Y16: 72.960976 | Z16: 73.012195 | AA16: 73.612195 | AB16: 73.814634 | AC16: 74.317073 | AD16: 74.768293 | AE16: 75.217073 | AF16: 75.265854 | AG16: 75.568293 | AH16: 75.617073 | AI16: 75.817073 | AJ16: 76.068293 | AK16: 76.419512 | AL16: 76.668293 | AM16: 76.870732 | AN16: 77.319512 | AO16: 77.670732 | AP16: 77.87561 | AQ16: 78.126829 | AR16: 78.57561 | AS16: 78.678049 | AT16: 78.631707 | AU16: 79.180488 | AV16: 79.331707 | AW16: 79.880488 | AX16: 80.180488 | AY16: 80.431707 | AZ16: 80.331707 | BA16: 80.580488 | BB16: 80.982927 | BC16: 80.936585 | BD16: 81.136585 | BE16: 81.490244 | BF16: 81.190244 | BG16: 81.641463 | BH16: 81.643902 | BI16: 81.692683 | BJ16: 81.895122 | BK16: 81.192683 | BL16: 81.190244 | BM16: 81.295122 | BN16: 81.792683 | BO16: 81.995122 | BP16: Europe & Central Asia | BQ16: High income
A17: Azerbaijan | B17: AZE | C17: 50.862 | D17: 51.435 | E17: 52.053 | F17: 52.696 | G17: 53.292 | H17: 53.884 | I17: 54.485 | J17: 55.032 | K17: 55.563 | L17: 56.08 | M17: 56.586 | N17: 57.043 | O17: 57.503 | P17: 57.926 | Q17: 58.332 | R17: 58.687 | S17: 59.477 | T17: 59.972 | U17: 60.494 | V17: 60.931 | W17: 61.433 | X17: 61.908 | Y17: 62.23 | Z17: 62.479 | AA17: 62.084 | AB17: 62.674 | AC17: 62.603 | AD17: 62.824 | AE17: 62.672 | AF17: 62.945 | AG17: 62.75 | AH17: 62.544 | AI17: 60.773 | AJ17: 61.426 | AK17: 60.277 | AL17: 61.931 | AM17: 62.66 | AN17: 62.953 | AO17: 63.75 | AP17: 64.733 | AQ17: 65.377 | AR17: 66.043 | AS17: 66.769 | AT17: 67.036 | AU17: 67.488 | AV17: 67.71 | AW17: 68.489 | AX17: 68.659 | AY17: 69.355 | AZ17: 69.874 | BA17: 70.309 | BB17: 70.565 | BC17: 71.08 | BD17: 71.485 | BE17: 71.93 | BF17: 72.349 | BG17: 72.568 | BH17: 72.694 | BI17: 73.016 | BJ17: 73.29 | BK17: 70.312 | BL17: 70.999 | BM17: 74.125 | BN17: 74.429 | BO17: 74.576 | BP17: Europe & Central Asia | BQ17: Upper middle income
A18: Burundi | B18: BDI | C18: 43.262 | D18: 43.364 | E18: 43.492 | F18: 43.559 | G18: 43.601 | H18: 41.844 | I18: 43.529 | J18: 43.332 | K18: 43.405 | L18: 43 | M18: 43.225 | N18: 43.172 | O18: 25.777 | P18: 37.409 | Q18: 43.337 | R18: 43.445 | S18: 43.691 | T18: 43.97 | U18: 44.404 | V18: 45.038 | W18: 45.731 | X18: 46.412 | Y18: 47.012 | Z18: 47.433 | AA18: 47.687 | AB18: 47.662 | AC18: 47.402 | AD18: 47.066 | AE18: 42.889 | AF18: 45.745 | AG18: 45.184 | AH18: 44.66 | AI18: 44.469 | AJ18: 37.221 | AK18: 44.515 | AL18: 44.589 | AM18: 44.807 | AN18: 45.721 | AO18: 46.678 | AP18: 47.627 | AQ18: 47.617 | AR18: 48.509 | AS18: 49.924 | AT18: 50.997 | AU18: 52.217 | AV18: 53.053 | AW18: 53.962 | AX18: 54.832 | AY18: 55.581 | AZ18: 56.422 | BA18: 57.088 | BB18: 57.804 | BC18: 58.501 | BD18: 59.179 | BE18: 59.764 | BF18: 60.107 | BG18: 60.789 | BH18: 61.345 | BI18: 61.806 | BJ18: 62.18 | BK18: 62.569 | BL18: 62.101 | BM18: 62.882 | BN18: 63.651 | BO18: 63.818 | BP18: Sub-Saharan Africa | BQ18: Low income
A19: Belgium | B19: BEL | C19: 69.701951 | D19: 70.520976 | E19: 70.219512 | F19: 70.051463 | G19: 70.755122 | H19: 70.625366 | I19: 70.706341 | J19: 71.012927 | K19: 70.693171 | L19: 70.764878 | M19: 70.971951 | N19: 71.060488 | O19: 71.405122 | P19: 71.635366 | Q19: 71.985854 | R19: 71.97122 | S19: 72.119756 | T19: 72.773902 | U19: 72.698049 | V19: 73.193659 | W19: 73.207073 | X19: 73.621707 | Y19: 73.888049 | Z19: 73.869024 | AA19: 74.404878 | AB19: 74.520244 | AC19: 74.731707 | AD19: 75.365854 | AE19: 75.565854 | AF19: 75.632683 | AG19: 76.051951 | AH19: 76.192195 | AI19: 76.35122 | AJ19: 76.345366 | AK19: 76.691707 | AL19: 76.840732 | AM19: 77.187317 | AN19: 77.370732 | AO19: 77.473171 | AP19: 77.619512 | AQ19: 77.721951 | AR19: 77.973171 | AS19: 78.07561 | AT19: 78.129268 | AU19: 78.878049 | AV19: 78.980488 | AW19: 79.380488 | AX19: 79.782927 | AY19: 79.680488 | AZ19: 80.034146 | BA19: 80.182927 | BB19: 80.585366 | BC19: 80.385366 | BD19: 80.587805 | BE19: 81.287805 | BF19: 80.992683 | BG19: 81.439024 | BH19: 81.492683 | BI19: 81.595122 | BJ19: 81.995122 | BK19: 80.695122 | BL19: 81.790244 | BM19: 81.74878 | BN19: 82.4 | BO19: 82.3 | BP19: Europe & Central Asia | BQ19: High income
A20: Benin | B20: BEN | C20: 38.775 | D20: 39.233 | E20: 39.643 | F20: 40.081 | G20: 40.502 | H20: 40.971 | I20: 41.274 | J20: 41.759 | K20: 42.182 | L20: 42.591 | M20: 43.029 | N20: 43.391 | O20: 43.928 | P20: 44.435 | Q20: 44.876 | R20: 45.405 | S20: 45.952 | T20: 46.504 | U20: 46.941 | V20: 47.362 | W20: 47.747 | X20: 48.122 | Y20: 48.493 | Z20: 48.845 | AA20: 49.399 | AB20: 49.959 | AC20: 50.632 | AD20: 51.258 | AE20: 52.019 | AF20: 52.45 | AG20: 53.02 | AH20: 53.441 | AI20: 54.137 | AJ20: 54.612 | AK20: 54.988 | AL20: 55.366 | AM20: 55.648 | AN20: 55.986 | AO20: 56.154 | AP20: 56.336 | AQ20: 56.594 | AR20: 56.654 | AS20: 56.851 | AT20: 57.092 | AU20: 57.346 | AV20: 57.738 | AW20: 57.966 | AX20: 58.249 | AY20: 58.099 | AZ20: 58.258 | BA20: 58.387 | BB20: 58.462 | BC20: 58.559 | BD20: 58.863 | BE20: 59.008 | BF20: 59.123 | BG20: 59.283 | BH20: 59.528 | BI20: 59.71 | BJ20: 59.888 | BK20: 60.154 | BL20: 59.61 | BM20: 60.475 | BN20: 60.774 | BO20: 60.961 | BP20: Sub-Saharan Africa | BQ20: Lower middle income
A21: Burkina Faso | B21: BFA | C21: 36.074 | D21: 36.361 | E21: 36.753 | F21: 37.093 | G21: 37.399 | H21: 37.758 | I21: 38.091 | J21: 38.432 | K21: 38.76 | L21: 39.023 | M21: 39.54 | N21: 39.853 | O21: 40.399 | P21: 40.947 | Q21: 41.711 | R21: 42.486 | S21: 43.327 | T21: 44.167 | U21: 44.995 | V21: 45.702 | W21: 46.465 | X21: 46.866 | Y21: 47.633 | Z21: 48.061 | AA21: 48.464 | AB21: 48.748 | AC21: 48.987 | AD21: 49.097 | AE21: 49.215 | AF21: 49.27 | AG21: 49.315 | AH21: 49.33 | AI21: 49.378 | AJ21: 49.412 | AK21: 49.469 | AL21: 49.554 | AM21: 49.693 | AN21: 49.56 | AO21: 50.163 | AP21: 50.463 | AQ21: 50.808 | AR21: 51.188 | AS21: 51.447 | AT21: 51.959 | AU21: 52.6 | AV21: 53.271 | AW21: 53.784 | AX21: 54.377 | AY21: 55.199 | AZ21: 55.791 | BA21: 56.343 | BB21: 57.001 | BC21: 57.457 | BD21: 57.903 | BE21: 58.331 | BF21: 58.778 | BG21: 59.173 | BH21: 59.578 | BI21: 59.972 | BJ21: 60.184 | BK21: 60.454 | BL21: 60.046 | BM21: 60.7 | BN21: 61.092 | BO21: 61.292 | BP21: Sub-Saharan Africa | BQ21: Low income
... A37: Canada | B37: CAN | C37: 71.133171 | D37: 71.346098 | E37: 71.367073 | F37: 71.380732 | G37: 71.776341 | H37: 71.872195 | I37: 72.00439 | J37: 72.207805 | K37: 72.353415 | L37: 72.501463 | M37: 72.700488 | N37: 73.029268 | O37: 72.933902 | P37: 73.162683 | Q37: 73.237561 | R37: 73.521707 | S37: 73.856098 | T37: 74.21561 | U37: 74.529756 | V37: 74.866341 | W37: 75.102195 | X37: 75.497805 | Y37: 75.725122 | Z37: 76.060488 | AA37: 76.331951 | AB37: 76.327317 | AC37: 76.463902 | AD37: 76.77878 | AE37: 76.85878 | AF37: 77.124878 | AG37: 77.436585 | AH37: 77.593415 | AI37: 77.838049 | AJ37: 77.704878 | AK37: 77.871707 | AL37: 77.977317 | AM37: 78.220244 | AN37: 78.412439 | AO37: 78.623659 | AP37: 78.839024 | AQ37: 79.166829 | AR37: 79.398049 | AS37: 79.530732 | AT37: 79.715122 | AU37: 79.992195 | AV37: 80.112683 | AW37: 80.543659 | AX37: 80.543659 | AY37: 80.724634 | AZ37: 81.066098 | BA37: 81.322195 | BB37: 81.482683 | BC37: 81.663659 | BD37: 81.744878 | BE37: 81.78439 | BF37: 81.825854 | BG37: 81.94 | BH37: 81.807805 | BI37: 81.803659 | BJ37: 82.158537 | BK37: 81.53 | BL37: 81.451463 | BM37: 81.094878 | BN37: 81.626341 | BO37: 82.108049 | BP37: North America | BQ37: High income
A38: Central Europe and the Baltics | B38: CEB | C38: 67.943473 | D38: 68.244951 | E38: 67.723736 | F38: 68.701 | G38: 69.195417 | H38: 69.350174 | I38: 69.856985 | J38: 69.355379 | K38: 69.573536 | L38: 69.066603 | M38: 69.345324 | N38: 69.511244 | O38: 69.971171 | P38: 70.109598 | Q38: 70.36857 | R38: 70.180888 | S38: 70.326408 | T38: 70.247694 | U38: 70.149887 | V38: 70.251482 | W38: 69.89341 | X38: 70.37205 | Y38: 70.455473 | Z38: 70.389785 | AA38: 70.349115 | AB38: 70.312883 | AC38: 70.565136 | AD38: 70.611763 | AE38: 70.861708 | AF38: 70.731972 | AG38: 70.656331 | AH38: 70.575221 | AI38: 70.732837 | AJ38: 70.845987 | AK38: 70.869544 | AL38: 71.025421 | AM38: 71.336058 | AN38: 71.517258 | AO38: 71.898238 | AP38: 72.184561 | AQ38: 72.719725 | AR38: 73.096148 | AS38: 73.242415 | AT38: 73.382253 | AU38: 73.730435 | AV38: 73.844995 | AW38: 74.092603 | AX38: 74.250649 | AY38: 74.575953 | AZ38: 74.930364 | BA38: 75.293966 | BB38: 75.888475 | BC38: 76.003394 | BD38: 76.374735 | BE38: 76.68877 | BF38: 76.575512 | BG38: 76.970306 | BH38: 76.929789 | BI38: 76.976438 | BJ38: 77.265914 | BK38: 76.01627 | BL38: 74.723283 | BM38: 76.652299 | BN38: 77.758038 | BO38: 77.918095
A39: Switzerland | B39: CHE | C39: 71.313415 | D39: 71.644878 | E39: 71.196098 | F39: 71.187561 | G39: 72.077805 | H39: 72.201707 | I39: 72.33561 | J39: 72.636585 | K39: 72.590244 | L39: 72.612683 | M39: 73.020244 | N39: 73.130732 | O39: 73.64439 | P39: 73.940976 | Q39: 74.287073 | R39: 74.66561 | S39: 74.785366 | T39: 75.238049 | U39: 75.187317 | V39: 75.466098 | W39: 75.459268 | X39: 75.693171 | Y39: 76.033902 | Z39: 76.03122 | AA39: 76.608537 | AB39: 76.733659 | AC39: 76.899024 | AD39: 77.197561 | AE39: 77.226585 | AF39: 77.42122 | AG39: 77.242439 | AH39: 77.514634 | AI39: 77.806098 | AJ39: 78.085366 | AK39: 78.35 | AL39: 78.417073 | AM39: 78.896098 | AN39: 79.079512 | AO39: 79.32439 | AP39: 79.580488 | AQ39: 79.680488 | AR39: 80.180488 | AS39: 80.385366 | AT39: 80.536585 | AU39: 81.087805 | AV39: 81.236585 | AW39: 81.490244 | AX39: 81.741463 | AY39: 81.992683 | AZ39: 82.043902 | BA39: 82.246341 | BB39: 82.695122 | BC39: 82.697561 | BD39: 82.797561 | BE39: 83.197561 | BF39: 82.897561 | BG39: 83.602439 | BH39: 83.55122 | BI39: 83.753659 | BJ39: 83.904878 | BK39: 83 | BL39: 83.75122 | BM39: 83.604878 | BN39: 84.156098 | BO39: 84.407317 | BP39: Europe & Central Asia | BQ39: High income
A40: Channel Islands | B40: CHI | C40: 72.5 | D40: 71.6 | E40: 72 | F40: 72.2 | G40: 72 | H40: 71.6 | I40: 72.3 | J40: 72.2 | K40: 71.7 | L40: 71.7 | M40: 71.8 | N40: 72 | O40: 72 | P40: 72.7 | Q40: 72.5 | R40: 72.6 | S40: 72.7 | T40: 72.9 | U40: 73.1 | V40: 73.2 | W40: 73.9 | X40: 73.8 | Y40: 73.1 | Z40: 74.9 | AA40: 75.2 | AB40: 75.3 | AC40: 75.4 | AD40: 75.7 | AE40: 76 | AF40: 76.5 | AG40: 76.3 | AH40: 76.5 | AI40: 77.1 | AJ40: 76.8 | AK40: 77 | AL40: 77.7 | AM40: 77.8 | AN40: 78.2 | AO40: 78.5 | AP40: 79.1 | AQ40: 78.8 | AR40: 79 | AS40: 79.1 | AT40: 79.4 | AU40: 79.8 | AV40: 80.1 | AW40: 80.4 | AX40: 80.6 | AY40: 80.8 | AZ40: 81 | BA40: 81.2 | BB40: 81.4 | BC40: 81.3 | BD40: 81.5 | BE40: 81.6 | BF40: 81.4 | BG40: 81.2 | BH40: 81 | BI40: 81.1 | BJ40: 81.2 | BK40: 80.9 | BL40: 80.3 | BM40: 81 | BN40: 81.1 | BO40: 81.2 | BP40: Europe & Central Asia | BQ40: High income
A41: Chile | B41: CHL | C41: 57.216 | D41: 57.309 | E41: 57.811 | F41: 58.349 | G41: 58.812 | H41: 59.473 | I41: 60.373 | J41: 61.054 | K41: 61.68 | L41: 62.341 | M41: 62.634 | N41: 63.072 | O41: 63.717 | P41: 64.42 | Q41: 65.085 | R41: 66.037 | S41: 66.819 | T41: 67.529 | U41: 68.042 | V41: 68.858 | W41: 69.475 | X41: 69.822 | Y41: 70.291 | Z41: 70.83 | AA41: 71.215 | AB41: 71.615 | AC41: 72.061 | AD41: 72.466 | AE41: 72.788 | AF41: 73.188 | AG41: 73.675 | AH41: 74.082 | AI41: 74.367 | AJ41: 74.679 | AK41: 74.973 | AL41: 75.298 | AM41: 75.555 | AN41: 75.826 | AO41: 76.324 | AP41: 76.738 | AQ41: 77.128 | AR41: 77.58 | AS41: 77.84 | AT41: 77.884 | AU41: 78.276 | AV41: 78.459 | AW41: 78.533 | AX41: 78.652 | AY41: 78.752 | AZ41: 78.89 | BA41: 79.095 | BB41: 79.236 | BC41: 79.221 | BD41: 79.551 | BE41: 79.714 | BF41: 80.008 | BG41: 80.295 | BH41: 80.61 | BI41: 80.559 | BJ41: 80.324 | BK41: 79.349 | BL41: 78.876 | BM41: 79.176 | BN41: 81.167 | BO41: 81.359 | BP41: Latin America & Caribbean | BQ41: High income
A42: China | B42: CHN | C42: 33.419 | D42: 40.158 | E42: 50.959 | F42: 51.67 | G42: 52.343 | H42: 53.001 | I42: 53.662 | J42: 54.401 | K42: 55.191 | L42: 55.988 | M42: 56.824 | N42: 57.731 | O42: 58.579 | P42: 59.496 | Q42: 60.241 | R42: 60.952 | S42: 61.225 | T42: 62.458 | U42: 63.102 | V42: 63.704 | W42: 64.243 | X42: 64.778 | Y42: 65.249 | Z42: 65.728 | AA42: 66.148 | AB42: 66.532 | AC42: 66.887 | AD42: 67.263 | AE42: 67.607 | AF42: 67.93 | AG42: 68.155 | AH42: 68.61 | AI42: 69.059 | AJ42: 69.492 | AK42: 69.835 | AL42: 70.363 | AM42: 70.823 | AN42: 71.227 | AO42: 71.601 | AP42: 71.952 | AQ42: 72.288 | AR42: 72.675 | AS42: 73.034 | AT42: 73.385 | AU42: 73.727 | AV42: 74.085 | AW42: 74.404 | AX42: 74.789 | AY42: 74.833 | AZ42: 75.317 | BA42: 75.668 | BB42: 75.889 | BC42: 76.2 | BD42: 76.452 | BE42: 76.714 | BF42: 76.975 | BG42: 77.214 | BH42: 77.235 | BI42: 77.709 | BJ42: 77.94 | BK42: 78.019 | BL42: 78.117 | BM42: 78.202 | BN42: 77.953 | BO42: 78.017 | BP42: East Asia & Pacific | BQ42: Upper middle income
A43: Cote d'Ivoire | B43: CIV | C43: 37.244 | D43: 37.923 | E43: 38.62 | F43: 39.315 | G43: 39.966 | H43: 40.643 | I43: 41.297 | J43: 41.959 | K43: 42.648 | L43: 43.345 | M43: 44.045 | N43: 44.783 | O43: 45.575 | P43: 46.372 | Q43: 47.207 | R43: 48.03 | S43: 48.863 | T43: 49.624 | U43: 50.361 | V43: 50.983 | W43: 51.437 | X43: 51.791 | Y43: 52.09 | Z43: 52.352 | AA43: 52.648 | AB43: 52.861 | AC43: 53.009 | AD43: 53.118 | AE43: 53.062 | AF43: 52.955 | AG43: 52.796 | AH43: 52.621 | AI43: 52.429 | AJ43: 52.247 | AK43: 52.005 | AL43: 51.713 | AM43: 51.596 | AN43: 51.498 | AO43: 51.22 | AP43: 51.273 | AQ43: 51.393 | AR43: 51.428 | AS43: 51.544 | AT43: 51.443 | AU43: 51.939 | AV43: 52.432 | AW43: 52.885 | AX43: 53.452 | AY43: 54.179 | AZ43: 54.744 | BA43: 55.282 | BB43: 55.972 | BC43: 56.57 | BD43: 57.057 | BE43: 57.772 | BF43: 58.281 | BG43: 58.814 | BH43: 59.315 | BI43: 59.795 | BJ43: 60.274 | BK43: 60.14 | BL43: 60.29 | BM43: 61.562 | BN43: 61.944 | BO43: 62.11 | BP43: Sub-Saharan Africa | BQ43: Lower middle income
A44: Cameroon | B44: CMR | C44: 34.667 | D44: 35.186 | E44: 42.599 | F44: 43.074 | G44: 43.596 | H44: 44.175 | I44: 44.839 | J44: 45.602 | K44: 46.389 | L44: 47.191 | M44: 47.954 | N44: 48.577 | O44: 49.12 | P44: 49.517 | Q44: 49.734 | R44: 49.891 | S44: 50.017 | T44: 50.13 | U44: 50.319 | V44: 50.535 | W44: 50.852 | X44: 51.227 | Y44: 51.801 | Z44: 52.447 | AA44: 52.886 | AB44: 53.465 | AC44: 53.572 | AD44: 54.188 | AE44: 54.359 | AF44: 54.389 | AG44: 54.348 | AH44: 54.168 | AI44: 54.053 | AJ44: 53.872 | AK44: 53.537 | AL44: 53.347 | AM44: 53.2 | AN44: 53.105 | AO44: 53.043 | AP44: 53.166 | AQ44: 53.338 | AR44: 53.598 | AS44: 53.922 | AT44: 54.253 | AU44: 54.578 | AV44: 54.904 | AW44: 55.301 | AX44: 55.71 | AY44: 56.116 | AZ44: 56.486 | BA44: 56.965 | BB44: 57.482 | BC44: 58.17 | BD44: 58.73 | BE44: 59.13 | BF44: 59.687 | BG44: 60.293 | BH44: 60.817 | BI44: 61.189 | BJ44: 61.695 | BK44: 61.674 | BL44: 61.146 | BM44: 62.443 | BN44: 63.7 | BO44: 63.968 | BP44: Sub-Saharan Africa | BQ44: Lower middle income
A45: Congo, Dem. Rep. | B45: COD | C45: 40.752 | D45: 40.161 | E45: 40.382 | F45: 40.604 | G45: 40.099 | H45: 40.767 | I45: 42.169 | J45: 42.339 | K45: 42.667 | L45: 42.959 | M45: 43.3 | N45: 43.578 | O45: 43.869 | P45: 44.09 | Q45: 44.311 | R45: 44.53 | S45: 44.695 | T45: 44.866 | U45: 44.628 | V45: 45.278 | W45: 45.543 | X45: 45.726 | Y45: 45.946 | Z45: 46.207 | AA45: 46.514 | AB45: 46.663 | AC45: 47.016 | AD45: 47.362 | AE45: 47.755 | AF45: 48.149 | AG45: 48.538 | AH45: 48.944 | AI45: 49.323 | AJ45: 49.621 | AK45: 49.88 | AL45: 50.381 | AM45: 49.376 | AN45: 50.461 | AO45: 49.664 | AP45: 50.089 | AQ45: 51.887 | AR45: 52.205 | AS45: 52.371 | AT45: 52.952 | AU45: 53.534 | AV45: 54.001 | AW45: 54.498 | AX45: 54.954 | AY45: 55.388 | AZ45: 55.798 | BA45: 56.411 | BB45: 56.911 | BC45: 57.35 | BD45: 57.795 | BE45: 58.236 | BF45: 58.658 | BG45: 59.081 | BH45: 59.495 | BI45: 59.926 | BJ45: 60.242 | BK45: 60.428 | BL45: 60.044 | BM45: 60.979 | BN45: 61.895 | BO45: 62.074 | BP45: Sub-Saharan Africa | BQ45: Low income
A46: Congo, Rep. | B46: COG | C46: 47.595 | D46: 48.351 | E46: 49.038 | F46: 49.729 | G46: 50.363 | H46: 50.996 | I46: 51.557 | J46: 51.91 | K46: 52.62 | L46: 53.114 | M46: 53.555 | N46: 53.983 | O46: 54.361 | P46: 54.744 | Q46: 55.053 | R46: 55.402 | S46: 55.699 | T46: 56.027 | U46: 56.248 | V46: 56.524 | W46: 56.803 | X46: 57.065 | Y46: 57.236 | Z46: 57.428 | AA46: 57.54 | AB46: 57.608 | AC46: 57.633 | AD46: 57.59 | AE46: 57.493 | AF46: 57.292 | AG46: 57.07 | AH46: 56.764 | AI46: 56.483 | AJ46: 56.041 | AK46: 55.641 | AL46: 55.474 | AM46: 55.24 | AN46: 48.575 | AO46: 52.551 | AP46: 54.427 | AQ46: 55.371 | AR46: 55.885 | AS46: 56.414 | AT46: 57.131 | AU46: 57.957 | AV46: 58.73 | AW46: 59.474 | AX46: 60.05 | AY46: 60.79 | AZ46: 61.215 | BA46: 61.731 | BB46: 62.286 | BC46: 62.662 | BD46: 62.969 | BE46: 63.349 | BF46: 63.662 | BG46: 63.911 | BH46: 64.203 | BI46: 64.472 | BJ46: 63.152 | BK46: 64.391 | BL46: 64.192 | BM46: 65 | BN46: 65.772 | BO46: 66.001 | BP46: Sub-Saharan Africa | BQ46: Lower middle income
A47: Colombia | B47: COL | C47: 56.609 | D47: 57.203 | E47: 57.737 | F47: 58.296 | G47: 58.77 | H47: 59.247 | I47: 59.713 | J47: 60.15 | K47: 60.572 | L47: 61.031 | M47: 61.465 | N47: 62.005 | O47: 62.53 | P47: 62.991 | Q47: 63.497 | R47: 64.012 | S47: 64.642 | T47: 65.237 | U47: 65.827 | V47: 66.162 | W47: 66.693 | X47: 67.189 | Y47: 67.861 | Z47: 68.121 | AA47: 68.308 | AB47: 65.359 | AC47: 68.303 | AD47: 68.166 | AE47: 68.301 | AF47: 68.616 | AG47: 68.701 | AH47: 68.772 | AI47: 68.764 | AJ47: 69.083 | AK47: 69.422 | AL47: 69.81 | AM47: 70.209 | AN47: 70.632 | AO47: 70.924 | AP47: 70.913 | AQ47: 70.905 | AR47: 71.185 | AS47: 71.537 | AT47: 72.309 | AU47: 72.76 | AV47: 73.156 | AW47: 73.497 | AX47: 73.751 | AY47: 74.206 | AZ47: 74.531 | BA47: 74.876 | BB47: 75.18 | BC47: 75.611 | BD47: 75.834 | BE47: 75.95 | BF47: 76.067 | BG47: 76.228 | BH47: 76.418 | BI47: 76.579 | BJ47: 76.793 | BK47: 74.757 | BL47: 72.698 | BM47: 76.508 | BN47: 77.725 | BO47: 77.913 | BP47: Latin America & Caribbean | BQ47: Upper middle income
A48: Comoros | B48: COM | C48: 40.777 | D48: 41.157 | E48: 41.534 | F48: 41.909 | G48: 42.328 | H48: 42.676 | I48: 43.153 | J48: 43.593 | K48: 44.101 | L48: 44.643 | M48: 45.226 | N48: 45.849 | O48: 46.463 | P48: 47.045 | Q48: 47.609 | R48: 46.866 | S48: 48.645 | T48: 49.17 | U48: 49.702 | V48: 50.126 | W48: 50.681 | X48: 51.211 | Y48: 51.75 | Z48: 52.121 | AA48: 52.784 | AB48: 53.263 | AC48: 53.756 | AD48: 54.134 | AE48: 54.678 | AF48: 54.983 | AG48: 55.62 | AH48: 56.104 | AI48: 56.576 | AJ48: 57.026 | AK48: 57.458 | AL48: 57.83 | AM48: 58.151 | AN48: 58.228 | AO48: 58.301 | AP48: 58.853 | AQ48: 58.941 | AR48: 59.587 | AS48: 59.723 | AT48: 60.24 | AU48: 60.557 | AV48: 60.883 | AW48: 61.229 | AX48: 61.475 | AY48: 61.955 | AZ48: 62.302 | BA48: 62.747 | BB48: 63.105 | BC48: 63.463 | BD48: 63.839 | BE48: 64.143 | BF48: 64.473 | BG48: 64.792 | BH48: 65.127 | BI48: 65.401 | BJ48: 65.662 | BK48: 65.756 | BL48: 65.201 | BM48: 66.481 | BN48: 66.777 | BO48: 67.023 | BP48: Sub-Saharan Africa | BQ48: Lower middle income
A49: Cabo Verde | B49: CPV | C49: 48.713 | D49: 49.419 | E49: 50.239 | F49: 51.145 | G49: 52.089 | H49: 53.04 | I49: 53.922 | J49: 54.716 | K49: 55.426 | L49: 56.038 | M49: 56.559 | N49: 57.027 | O49: 57.486 | P49: 57.979 | Q49: 58.432 | R49: 58.976 | S49: 59.396 | T49: 59.986 | U49: 60.381 | V49: 60.726 | W49: 61.031 | X49: 61.299 | Y49: 61.519 | Z49: 61.767 | AA49: 61.829 | AB49: 62.281 | AC49: 62.584 | AD49: 62.91 | AE49: 63.242 | AF49: 63.566 | AG49: 63.869 | AH49: 64.066 | AI49: 64.253 | AJ49: 64.458 | AK49: 64.648 | AL49: 63.691 | AM49: 65.521 | AN49: 66.082 | AO49: 66.714 | AP49: 67.409 | AQ49: 68.117 | AR49: 68.707 | AS49: 69.447 | AT49: 70.006 | AU49: 70.499 | AV49: 70.936 | AW49: 71.341 | AX49: 71.487 | AY49: 71.888 | AZ49: 72.142 | BA49: 72.507 | BB49: 72.913 | BC49: 73.315 | BD49: 73.481 | BE49: 73.788 | BF49: 74.096 | BG49: 74.35 | BH49: 74.71 | BI49: 74.84 | BJ49: 75.449 | BK49: 73.818 | BL49: 74.424 | BM49: 75.907 | BN49: 76.059 | BO49: 76.224 | BP49: Sub-Saharan Africa | BQ49: Upper middle income
A50: Costa Rica | B50: CRI | C50: 63.463 | D50: 63.86 | E50: 64.232 | F50: 64.326 | G50: 64.493 | H50: 64.76 | I50: 65.096 | J50: 65.552 | K50: 65.78 | L50: 66.363 | M50: 66.787 | N50: 67.413 | O50: 68.014 | P50: 68.731 | Q50: 69.446 | R50: 70.253 | S50: 70.946 | T50: 71.519 | U50: 72.029 | V50: 72.537 | W50: 73.034 | X50: 73.441 | Y50: 73.865 | Z50: 74.245 | AA50: 74.581 | AB50: 74.765 | AC50: 74.949 | AD50: 75.224 | AE50: 75.546 | AF50: 75.85 | AG50: 76.094 | AH50: 76.237 | AI50: 76.385 | AJ50: 76.315 | AK50: 76.329 | AL50: 76.44 | AM50: 76.428 | AN50: 76.603 | AO50: 76.869 | AP50: 77.058 | AQ50: 77.317 | AR50: 77.609 | AS50: 77.939 | AT50: 78.214 | AU50: 78.512 | AV50: 78.877 | AW50: 79.049 | AX50: 79.098 | AY50: 79.18 | AZ50: 79.372 | BA50: 79.354 | BB50: 79.624 | BC50: 79.925 | BD50: 80.189 | BE50: 80.231 | BF50: 80.407 | BG50: 79.988 | BH50: 79.994 | BI50: 80.09 | BJ50: 80.296 | BK50: 79.725 | BL50: 78.05 | BM50: 79.316 | BN50: 80.799 | BO50: 80.996 | BP50: Latin America & Caribbean | BQ50: High income
A51: Caribbean small states | B51: CSS | C51: 60.296076 | D51: 60.671113 | E51: 61.366755 | F51: 61.717282 | G51: 62.116938 | H51: 62.427899 | I51: 62.688492 | J51: 62.919213 | K51: 63.147976 | L51: 63.33756 | M51: 63.491125 | N51: 63.642161 | O51: 63.85759 | P51: 64.052426 | Q51: 64.263256 | R51: 64.483005 | S51: 64.756251 | T51: 64.972608 | U51: 65.124541 | V51: 65.347242 | W51: 65.501582 | X51: 65.663476 | Y51: 65.778323 | Z51: 65.84727 | AA51: 66.13987 | AB51: 66.30206 | AC51: 66.411303 | AD51: 66.570945 | AE51: 66.74044 | AF51: 66.9248 | AG51: 67.045151 | AH51: 67.219377 | AI51: 67.353289 | AJ51: 67.475565 | AK51: 67.521661 | AL51: 67.555572 | AM51: 67.626402 | AN51: 67.736543 | AO51: 67.984923 | AP51: 68.209564 | AQ51: 68.397676 | AR51: 68.661972 | AS51: 68.899714 | AT51: 69.087649 | AU51: 69.36097 | AV51: 69.632051 | AW51: 69.934423 | AX51: 70.293733 | AY51: 70.549997 | AZ51: 70.797738 | BA51: 71.011437 | BB51: 71.266093 | BC51: 71.401914 | BD51: 71.569251 | BE51: 71.773941 | BF51: 71.864102 | BG51: 72.051636 | BH51: 72.173104 | BI51: 72.221085 | BJ51: 72.12926 | BK51: 71.939436 | BL51: 69.922811 | BM51: 72.832292 | BN51: 73.171645 | BO51: 73.312667
A52: Cuba | B52: CUB | C52: 63.316 | D52: 63.743 | E52: 64.374 | F52: 64.347 | G52: 65.264 | H52: 65.636 | I52: 66.074 | J52: 66.514 | K52: 66.944 | L52: 67.358 | M52: 67.935 | N52: 68.432 | O52: 68.949 | P52: 69.347 | Q52: 69.867 | R52: 70.375 | S52: 70.878 | T52: 71.411 | U52: 71.89 | V52: 72.272 | W52: 72.603 | X52: 72.996 | Y52: 73.439 | Z52: 73.564 | AA52: 73.552 | AB52: 73.464 | AC52: 73.558 | AD52: 73.596 | AE52: 73.724 | AF52: 73.69 | AG52: 73.823 | AH52: 73.757 | AI52: 73.846 | AJ52: 73.874 | AK52: 74.092 | AL52: 74.346 | AM52: 74.69 | AN52: 75.064 | AO52: 75.412 | AP52: 75.719 | AQ52: 75.922 | AR52: 76.429 | AS52: 76.766 | AT52: 77.405 | AU52: 77.326 | AV52: 77.54 | AW52: 77.406 | AX52: 77.55 | AY52: 77.589 | AZ52: 77.584 | BA52: 77.876 | BB52: 78.051 | BC52: 78.162 | BD52: 78.028 | BE52: 77.825 | BF52: 77.745 | BG52: 77.571 | BH52: 77.3 | BI52: 77.426 | BJ52: 77.413 | BK52: 77.407 | BL52: 73.201 | BM52: 77.629 | BN52: 78.085 | BO52: 78.264 | BP52: Latin America & Caribbean | BQ52: Upper middle income
A53: Curacao | B53: CUW | C53: 65.406 | D53: 65.745 | E53: 66.027 | F53: 66.312 | G53: 66.59 | H53: 66.862 | I53: 67.136 | J53: 67.405 | K53: 67.67 | L53: 67.929 | M53: 68.23 | N53: 68.505 | O53: 68.811 | P53: 69.092 | Q53: 69.394 | R53: 69.672 | S53: 69.951 | T53: 70.202 | U53: 70.445 | V53: 70.716 | W53: 70.951 | X53: 71.175 | Y53: 71.377 | Z53: 71.534 | AA53: 71.715 | AB53: 71.867 | AC53: 71.996 | AD53: 72.139 | AE53: 72.23 | AF53: 72.151 | AG53: 72.439 | AH53: 72.536 | AI53: 72.65 | AJ53: 72.703 | AK53: 72.791 | AL53: 72.831 | AM53: 72.945 | AN53: 73.035 | AO53: 73.084 | AP53: 73.174 | AQ53: 73.283 | AR53: 73.36 | AS53: 73.472 | AT53: 73.603 | AU53: 73.735 | AV53: 73.873 | AW53: 73.978 | AX53: 74.137 | AY53: 74.314 | AZ53: 74.485 | BA53: 75.117 | BB53: 75.576 | BC53: 75.96 | BD53: 76.239 | BE53: 76.384 | BF53: 76.482 | BG53: 76.322 | BH53: 76.423 | BI53: 76.493 | BJ53: 76.492 | BK53: 76.501 | BL53: 75.686 | BM53: 76.729 | BN53: 76.8 | BO53: 76.989 | BP53: Latin America & Caribbean | BQ53: High income
A54: Cayman Islands | B54: CYM | C54: 58.782 | D54: 59.426 | E54: 60.09 | F54: 60.78 | G54: 61.436 | H54: 62.186 | I54: 62.841 | J54: 63.205 | K54: 63.597 | L54: 63.965 | M54: 64.383 | N54: 64.827 | O54: 65.365 | P54: 65.889 | Q54: 66.489 | R54: 67.044 | S54: 67.549 | T54: 68.08 | U54: 68.533 | V54: 69.02 | W54: 69.487 | X54: 69.951 | Y54: 70.407 | Z54: 70.839 | AA54: 71.187 | AB54: 71.558 | AC54: 71.869 | AD54: 72.13 | AE54: 72.351 | AF54: 72.545 | AG54: 72.744 | AH54: 72.911 | AI54: 73.088 | AJ54: 73.25 | AK54: 73.42 | AL54: 73.597 | AM54: 73.74 | AN54: 73.904 | AO54: 74.08 | AP54: 74.232 | AQ54: 74.378 | AR54: 74.529 | AS54: 74.609 | AT54: 74.639 | AU54: 74.596 | AV54: 74.863 | AW54: 75 | AX54: 75.152 | AY54: 75.386 | AZ54: 75.671 | BA54: 76.069 | BB54: 76.562 | BC54: 77.121 | BD54: 77.652 | BE54: 77.865 | BF54: 78.119 | BG54: 78.367 | BH54: 78.615 | BI54: 78.835 | BJ54: 79.052 | BK54: 79.23 | BL54: 79.3 | BM54: 79.984 | BN54: 80.358 | BO54: 80.54 | BP54: Latin America & Caribbean | BQ54: High income
A55: Cyprus | B55: CYP | C55: 63.32 | D55: 64.076 | E55: 64.72 | F55: 61.779 | G55: 62.24 | H55: 66.124 | I55: 66.489 | J55: 66.906 | K55: 67.251 | L55: 67.599 | M55: 68.05 | N55: 68.351 | O55: 68.629 | P55: 69.005 | Q55: 54.551 | R55: 70.336 | S55: 70.805 | T55: 71.258 | U55: 71.741 | V55: 72.179 | W55: 72.844 | X55: 73.053 | Y55: 73.518 | Z55: 73.708 | AA55: 74 | AB55: 74.64 | AC55: 74.93 | AD55: 75.264 | AE55: 75.39 | AF55: 75.841 | AG55: 76.044 | AH55: 76.246 | AI55: 76.291 | AJ55: 76.294 | AK55: 76.383 | AL55: 76.583 | AM55: 76.88 | AN55: 77.119 | AO55: 77.164 | AP55: 77.572 | AQ55: 77.9 | AR55: 78.185 | AS55: 78.758 | AT55: 78.908 | AU55: 79.007 | AV55: 79.198 | AW55: 79.456 | AX55: 79.798 | AY55: 79.906 | AZ55: 80.375 | BA55: 80.632 | BB55: 80.855 | BC55: 81.128 | BD55: 81.317 | BE55: 81.337 | BF55: 81.464 | BG55: 81.534 | BH55: 81.543 | BI55: 81.556 | BJ55: 81.454 | BK55: 81.23 | BL55: 80.573 | BM55: 80.434 | BN55: 81.648 | BO55: 81.821 | BP55: Europe & Central Asia | BQ55: High income
A56: Czechia | B56: CZE | C56: 70.34878 | D56: 70.512683 | E56: 69.786829 | F56: 70.30439 | G56: 70.459512 | H56: 70.163171 | I56: 70.384878 | J56: 70.264146 | K56: 69.840732 | L56: 69.367073 | M56: 69.440244 | N56: 69.677073 | O56: 70.176585 | P56: 70.022683 | Q56: 70.086585 | R56: 70.414634 | S56: 70.532683 | T56: 70.573415 | U56: 70.643902 | V56: 70.749512 | W56: 70.278049 | X56: 70.722195 | Y56: 70.807805 | Z56: 70.591463 | AA56: 70.837561 | AB56: 71.046341 | AC56: 70.997317 | AD56: 71.44561 | AE56: 71.641463 | AF56: 71.67561 | AG56: 71.383902 | AH56: 71.898293 | AI56: 72.271707 | AJ56: 72.767805 | AK56: 72.972683 | AL56: 73.074878 | AM56: 73.714634 | AN56: 73.824878 | AO56: 74.514634 | AP56: 74.668293 | AQ56: 74.968293 | AR56: 75.173171 | AS56: 75.221951 | AT56: 75.170732 | AU56: 75.721951 | AV56: 75.92439 | AW56: 76.52439 | AX56: 76.72439 | AY56: 76.97561 | AZ56: 77.078049 | BA56: 77.42439 | BB56: 77.873171 | BC56: 78.07561 | BD56: 78.17561 | BE56: 78.82439 | BF56: 78.578049 | BG56: 79.026829 | BH56: 78.978049 | BI56: 79.029268 | BJ56: 79.229268 | BK56: 78.226829 | BL56: 77.221951 | BM56: 78.929268 | BN56: 79.826829 | BO56: 79.978049 | BP56: Europe & Central Asia | BQ56: High income
A57: Germany | B57: DEU | C57: 69.064073 | D57: 69.644878 | E57: 69.79922 | F57: 69.914073 | G57: 70.435561 | H57: 70.410366 | I57: 70.521585 | J57: 70.731732 | K57: 70.378463 | L57: 70.228805 | M57: 70.447195 | N57: 70.676756 | O57: 70.906707 | P57: 71.112805 | Q57: 71.418927 | R57: 71.259244 | S57: 71.71222 | T57: 72.307317 | U57: 72.290415 | V57: 72.630171 | W57: 72.800317 | X57: 73.04022 | Y57: 73.333146 | Z57: 73.622146 | AA57: 74.072293 | AB57: 74.189098 | AC57: 74.396829 | AD57: 74.807024 | AE57: 74.998732 | AF57: 75.191537 | AG57: 75.085634 | AH57: 75.319512 | AI57: 75.819512 | AJ57: 75.870732 | AK57: 76.270732 | AL57: 76.421951 | AM57: 76.673171 | AN57: 77.073171 | AO57: 77.47561 | AP57: 77.726829 | AQ57: 77.926829 | AR57: 78.329268 | AS57: 78.229268 | AT57: 78.380488 | AU57: 78.680488 | AV57: 78.931707 | AW57: 79.131707 | AX57: 79.534146 | AY57: 79.736585 | AZ57: 79.836585 | BA57: 79.987805 | BB57: 80.436585 | BC57: 80.539024 | BD57: 80.490244 | BE57: 81.090244 | BF57: 80.641463 | BG57: 80.990244 | BH57: 80.992683 | BI57: 80.892683 | BJ57: 81.292683 | BK57: 81.041463 | BL57: 80.790244 | BM57: 80.608049 | BN57: 81.041463 | BO57: 80.792683 | BP57: Europe & Central Asia | BQ57: High income
A58: Djibouti | B58: DJI | C58: 43.421 | D58: 43.781 | E58: 44.092 | F58: 44.442 | G58: 44.812 | H58: 45.234 | I58: 45.62 | J58: 46.103 | K58: 46.552 | L58: 47.067 | M58: 47.536 | N58: 47.259 | O58: 48.532 | P58: 49.097 | Q58: 49.52 | R58: 49.923 | S58: 50.335 | T58: 50.755 | U58: 51.172 | V58: 51.597 | W58: 52.046 | X58: 52.355 | Y58: 52.893 | Z58: 53.334 | AA58: 53.745 | AB58: 54.075 | AC58: 54.494 | AD58: 54.832 | AE58: 55.133 | AF58: 55.369 | AG58: 55.469 | AH58: 55.194 | AI58: 54.375 | AJ58: 55.734 | AK58: 55.592 | AL58: 56.234 | AM58: 56.33 | AN58: 56.207 | AO58: 56.426 | AP58: 56.564 | AQ58: 56.734 | AR58: 57.506 | AS58: 57.824 | AT58: 58.041 | AU58: 58.103 | AV58: 58.548 | AW58: 58.962 | AX58: 59.362 | AY58: 59.815 | AZ58: 60.351 | BA58: 60.743 | BB58: 61.337 | BC58: 61.719 | BD58: 62.116 | BE58: 62.427 | BF58: 62.833 | BG58: 63.335 | BH58: 63.71 | BI58: 64.105 | BJ58: 64.381 | BK58: 64.2 | BL58: 63.83 | BM58: 65.54 | BN58: 65.987 | BO58: 66.202 | BP58: Middle East & North Africa | BQ58: Lower middle income
A59: Dominica | B59: DMA | C59: 60.076 | D59: 61.022 | E59: 61.894 | F59: 62.612 | G59: 63.278 | H59: 63.913 | I59: 64.457 | J59: 64.856 | K59: 65.277 | L59: 65.704 | M59: 66.208 | N59: 66.763 | O59: 67.468 | P59: 68.097 | Q59: 68.585 | R59: 69.059 | S59: 69.411 | T59: 69.715 | U59: 70.115 | V59: 69.195 | W59: 71.013 | X59: 71.46 | Y59: 71.749 | Z59: 72.005 | AA59: 71.913 | AB59: 71.918 | AC59: 71.671 | AD59: 71.368 | AE59: 70.974 | AF59: 70.663 | AG59: 70.471 | AH59: 70.398 | AI59: 70.473 | AJ59: 70.612 | AK59: 70.777 | AL59: 70.832 | AM59: 71.039 | AN59: 71.195 | AO59: 71.352 | AP59: 71.527 | AQ59: 71.715 | AR59: 71.862 | AS59: 71.927 | AT59: 71.942 | AU59: 71.987 | AV59: 72.016 | AW59: 72.007 | AX59: 71.901 | AY59: 71.945 | AZ59: 71.835 | BA59: 71.68 | BB59: 71.517 | BC59: 71.391 | BD59: 71.228 | BE59: 71.189 | BF59: 69.968 | BG59: 71.189 | BH59: 68.62 | BI59: 71.378 | BJ59: 71.305 | BK59: 71.269 | BL59: 69.832 | BM59: 71.081 | BN59: 71.132 | BO59: 71.294 | BP59: Latin America & Caribbean | BQ59: Upper middle income
A60: Denmark | B60: DNK | C60: 72.176585 | D60: 72.438293 | E60: 72.319756 | F60: 72.400488 | G60: 72.485122 | H60: 72.370732 | I60: 72.444146 | J60: 72.922195 | K60: 73.121463 | L60: 73.220976 | M60: 73.343415 | N60: 73.414634 | O60: 73.439024 | P60: 73.682195 | Q60: 73.808293 | R60: 74.075122 | S60: 73.739756 | T60: 74.632439 | U60: 74.392927 | V60: 74.219268 | W60: 74.101707 | X60: 74.230488 | Y60: 74.55122 | Z60: 74.420488 | AA60: 74.562195 | AB60: 74.427561 | AC60: 74.579756 | AD60: 74.69122 | AE60: 74.771707 | AF60: 74.799756 | AG60: 74.805366 | AH60: 75.157805 | AI60: 75.194146 | AJ60: 75.116829 | AK60: 75.375122 | AL60: 75.212683 | AM60: 75.591463 | AN60: 75.945122 | AO60: 76.139024 | AP60: 76.341463 | AQ60: 76.592683 | AR60: 76.792683 | AS60: 76.895122 | AT60: 77.143902 | AU60: 77.492683 | AV60: 77.843902 | AW60: 78.095122 | AX60: 78.195122 | AY60: 78.446341 | AZ60: 78.597561 | BA60: 79.1 | BB60: 79.8 | BC60: 80.05122 | BD60: 80.3 | BE60: 80.7 | BF60: 80.702439 | BG60: 80.853659 | BH60: 81.102439 | BI60: 80.953659 | BJ60: 81.45122 | BK60: 81.602439 | BL60: 81.404878 | BM60: 81.304878 | BN60: 81.753659 | BO60: 82.253659 | BP60: Europe & Central Asia | BQ60: High income
A61: Dominican Republic | B61: DOM | C61: 51.705 | D61: 52.447 | E61: 53.199 | F61: 53.754 | G61: 54.653 | H61: 52.842 | I61: 55.965 | J61: 56.646 | K61: 57.272 | L61: 57.886 | M61: 58.493 | N61: 59.09 | O61: 59.661 | P61: 60.228 | Q61: 60.757 | R61: 61.254 | S61: 61.739 | T61: 62.2 | U61: 62.624 | V61: 62.425 | W61: 63.391 | X61: 63.776 | Y61: 64.198 | Z61: 64.63 | AA61: 65.134 | AB61: 65.614 | AC61: 66.059 | AD61: 66.49 | AE61: 66.914 | AF61: 67.331 | AG61: 67.746 | AH61: 68.154 | AI61: 68.525 | AJ61: 68.86 | AK61: 69.16 | AL61: 69.394 | AM61: 69.595 | AN61: 69.809 | AO61: 69.875 | AP61: 70.178 | AQ61: 70.365 | AR61: 70.553 | AS61: 70.719 | AT61: 70.856 | AU61: 70.73 | AV61: 71.043 | AW61: 71.054 | AX61: 71.097 | AY61: 71.331 | AZ61: 71.587 | BA61: 72.039 | BB61: 72.496 | BC61: 72.817 | BD61: 73.038 | BE61: 73.145 | BF61: 72.982 | BG61: 72.889 | BH61: 73.37 | BI61: 73.555 | BJ61: 73.112 | BK61: 72.636 | BL61: 71.757 | BM61: 74.211 | BN61: 73.72 | BO61: 73.868 | BP61: Latin America & Caribbean | BQ61: Upper middle income
A62: Algeria | B62: DZA | C62: 40.839 | D62: 40.792 | E62: 39.527 | F62: 43.143 | G62: 42.987 | H62: 42.846 | I62: 42.745 | J62: 42.731 | K62: 42.806 | L62: 42.991 | M62: 43.328 | N62: 43.782 | O62: 44.384 | P62: 45.102 | Q62: 45.953 | R62: 46.921 | S62: 48.034 | T62: 49.249 | U62: 50.615 | V62: 52.409 | W62: 54.512 | X62: 57.422 | Y62: 59.594 | Z62: 61.251 | AA62: 62.722 | AB62: 64.155 | AC62: 65.273 | AD62: 66.13 | AE62: 66.91 | AF62: 67.461 | AG62: 67.658 | AH62: 67.692 | AI62: 67.725 | AJ62: 67.797 | AK62: 67.284 | AL62: 67.691 | AM62: 68.219 | AN62: 68.859 | AO62: 69.327 | AP62: 70.088 | AQ62: 70.576 | AR62: 71.025 | AS62: 71.644 | AT62: 71.906 | AU62: 72.536 | AV62: 72.836 | AW62: 73.116 | AX62: 73.346 | AY62: 73.618 | AZ62: 73.871 | BA62: 74.144 | BB62: 74.383 | BC62: 74.609 | BD62: 74.809 | BE62: 74.992 | BF62: 75.159 | BG62: 75.31 | BH62: 75.431 | BI62: 75.555 | BJ62: 75.682 | BK62: 73.257 | BL62: 75.208 | BM62: 76.129 | BN62: 76.261 | BO62: 76.475 | BP62: Middle East & North Africa | BQ62: Upper middle income
A63: East Asia & Pacific (excluding high income) | B63: EAP | C63: 37.84668 | D63: 43.071859 | E63: 51.168112 | F63: 51.768145 | G63: 52.417159 | H63: 52.258198 | I63: 53.393359 | J63: 54.289215 | K63: 54.832459 | L63: 55.628545 | M63: 56.320393 | N63: 57.130371 | O63: 57.715651 | P63: 58.622846 | Q63: 59.239289 | R63: 59.986851 | S63: 60.357347 | T63: 61.415143 | U63: 62.007544 | V63: 62.685172 | W63: 63.211273 | X63: 63.699859 | Y63: 64.175366 | Z63: 64.655678 | AA63: 65.086305 | AB63: 65.485224 | AC63: 65.838034 | AD63: 66.218323 | AE63: 66.562681 | AF63: 66.903771 | AG63: 67.150584 | AH63: 67.566 | AI63: 68.000611 | AJ63: 68.423224 | AK63: 68.721178 | AL63: 69.030878 | AM63: 69.425739 | AN63: 69.794844 | AO63: 70.127762 | AP63: 70.422659 | AQ63: 70.735707 | AR63: 71.074092 | AS63: 71.39675 | AT63: 71.803996 | AU63: 71.858801 | AV63: 72.398327 | AW63: 72.65187 | AX63: 72.993754 | AY63: 72.924138 | AZ63: 73.467788 | BA63: 73.761639 | BB63: 73.985745 | BC63: 74.259787 | BD63: 74.485932 | BE63: 74.719453 | BF63: 74.951124 | BG63: 75.155912 | BH63: 75.239671 | BI63: 75.578286 | BJ63: 75.768969 | BK63: 75.697639 | BL63: 75.278142 | BM63: 75.932541 | BN63: 75.880683 | BO63: 75.959316
A64: Early-demographic dividend | B64: EAR | C64: 46.913414 | D64: 47.404937 | E64: 47.850475 | F64: 48.254031 | G64: 48.735986 | H64: 47.751614 | I64: 48.755611 | J64: 49.435347 | K64: 50.43708 | L64: 50.83672 | M64: 50.756227 | N64: 50.131965 | O64: 51.945658 | P64: 52.360569 | Q64: 52.806231 | R64: 53.223031 | S64: 53.743027 | T64: 54.313194 | U64: 54.825594 | V64: 55.521188 | W64: 56.068907 | X64: 56.524472 | Y64: 57.019749 | Z64: 57.451068 | AA64: 57.98943 | AB64: 58.476397 | AC64: 58.931153 | AD64: 59.526278 | AE64: 59.908348 | AF64: 60.347993 | AG64: 60.638326 | AH64: 60.9285 | AI64: 61.396685 | AJ64: 61.73757 | AK64: 61.977301 | AL64: 62.404529 | AM64: 62.742784 | AN64: 63.098742 | AO64: 63.436967 | AP64: 63.77938 | AQ64: 64.21961 | AR64: 64.556705 | AS64: 64.968075 | AT64: 65.279155 | AU64: 65.513239 | AV64: 65.979786 | AW64: 66.39193 | AX64: 66.760547 | AY64: 67.021819 | AZ64: 67.496408 | BA64: 67.824443 | BB64: 68.260038 | BC64: 68.609463 | BD64: 68.962838 | BE64: 69.324976 | BF64: 69.630548 | BG64: 69.948484 | BH64: 70.272995 | BI64: 70.548666 | BJ64: 70.842406 | BK64: 69.880131 | BL64: 68.179099 | BM64: 71.430455 | BN64: 71.796245 | BO64: 72.008031
A65: East Asia & Pacific | B65: EAS | C65: 41.707757 | D65: 46.321922 | E65: 53.310067 | F65: 53.910616 | G65: 54.511616 | H65: 54.382812 | I65: 55.382885 | J65: 56.318455 | K65: 56.78074 | L65: 57.497752 | M65: 58.107419 | N65: 58.895135 | O65: 59.433912 | P65: 60.238248 | Q65: 60.814616 | R65: 61.524708 | S65: 61.888864 | T65: 62.863032 | U65: 63.416217 | V65: 64.055218 | W65: 64.519653 | X65: 64.99152 | Y65: 65.452367 | Z65: 65.882113 | AA65: 66.305254 | AB65: 66.687001 | AC65: 67.039383 | AD65: 67.411771 | AE65: 67.713452 | AF65: 68.049712 | AG65: 68.282549 | AH65: 68.675193 | AI65: 69.065106 | AJ65: 69.464568 | AK65: 69.760996 | AL65: 70.024398 | AM65: 70.433304 | AN65: 70.790129 | AO65: 71.099637 | AP65: 71.367553 | AQ65: 71.702832 | AR65: 72.041306 | AS65: 72.357106 | AT65: 72.734691 | AU65: 72.812661 | AV65: 73.298435 | AW65: 73.564044 | AX65: 73.894851 | AY65: 73.848163 | AZ65: 74.368347 | BA65: 74.629979 | BB65: 74.825283 | BC65: 75.105973 | BD65: 75.334773 | BE65: 75.564427 | BF65: 75.792601 | BG65: 75.987017 | BH65: 76.078992 | BI65: 76.391423 | BJ65: 76.586241 | BK65: 76.543395 | BL65: 76.152941 | BM65: 76.676717 | BN65: 76.657202 | BO65: 76.737895
A66: Europe & Central Asia (excluding high income) | B66: ECA | C66: 60.894038 | D66: 61.428816 | E66: 61.773325 | F66: 62.165329 | G66: 62.537912 | H66: 62.823863 | I66: 63.064576 | J66: 63.302164 | K66: 63.424744 | L66: 63.573619 | M66: 63.751075 | N66: 63.969152 | O66: 64.248819 | P66: 64.448485 | Q66: 64.625976 | R66: 64.741856 | S66: 64.885995 | T66: 65.109954 | U66: 65.306668 | V66: 65.490551 | W66: 65.756334 | X66: 66.002425 | Y66: 66.301253 | Z66: 66.535624 | AA66: 66.762754 | AB66: 67.237909 | AC66: 67.660854 | AD66: 67.952052 | AE66: 67.851143 | AF66: 68.262835 | AG66: 68.207885 | AH66: 68.057856 | AI66: 67.251633 | AJ66: 67.059263 | AK66: 67.307492 | AL66: 67.444737 | AM66: 67.720885 | AN66: 68.043246 | AO66: 68.339075 | AP66: 68.20278 | AQ66: 68.857053 | AR66: 69.090278 | AS66: 69.318731 | AT66: 69.587902 | AU66: 69.791149 | AV66: 69.959515 | AW66: 70.217866 | AX66: 70.557979 | AY66: 70.974318 | AZ66: 71.442292 | BA66: 71.912591 | BB66: 72.15095 | BC66: 72.673598 | BD66: 73.125829 | BE66: 73.419516 | BF66: 73.755408 | BG66: 74.031377 | BH66: 74.403354 | BI66: 74.592799 | BJ66: 74.815834 | BK66: 73.553687 | BL66: 72.882376 | BM66: 74.573168 | BN66: 74.790189 | BO66: 75.142498
A67: Europe & Central Asia | B67: ECS | C67: 67.419602 | D67: 67.735031 | E67: 67.693324 | F67: 68.040633 | G67: 68.525532 | H67: 68.593802 | I67: 68.808013 | J67: 68.863904 | K67: 68.826157 | L67: 68.680544 | M67: 68.979213 | N67: 69.154155 | O67: 69.385225 | P67: 69.495152 | Q67: 69.709259 | R67: 69.647127 | S67: 69.771666 | T67: 69.993348 | U67: 70.070479 | V67: 70.205516 | W67: 70.281688 | X67: 70.56516 | Y67: 70.872259 | Z67: 70.922763 | AA67: 71.062996 | AB67: 71.302507 | AC67: 71.811678 | AD67: 72.026726 | AE67: 72.105706 | AF67: 72.224994 | AG67: 72.194388 | AH67: 72.15369 | AI67: 71.854327 | AJ67: 71.531617 | AK67: 71.687124 | AL67: 71.830264 | AM67: 72.249924 | AN67: 72.645301 | AO67: 72.914693 | AP67: 72.838967 | AQ67: 73.113712 | AR67: 73.355824 | AS67: 73.446412 | AT67: 73.562747 | AU67: 73.988037 | AV67: 74.153645 | AW67: 74.639772 | AX67: 75.008654 | AY67: 75.302314 | AZ67: 75.689199 | BA67: 75.995356 | BB67: 76.479369 | BC67: 76.680497 | BD67: 77.032439 | BE67: 77.353579 | BF67: 77.330938 | BG67: 77.681282 | BH67: 77.899015 | BI67: 78.031841 | BJ67: 78.303872 | BK67: 77.175491 | BL67: 76.728643 | BM67: 77.834452 | BN67: 78.391133 | BO67: 78.598685
A68: Ecuador | B68: ECU | C68: 53.396 | D68: 54.052 | E68: 54.681 | F68: 55.322 | G68: 55.95 | H68: 56.524 | I68: 57.019 | J68: 57.482 | K68: 57.946 | L68: 58.267 | M68: 58.85 | N68: 59.343 | O68: 59.816 | P68: 60.306 | Q68: 60.7 | R68: 61.085 | S68: 61.425 | T68: 61.935 | U68: 62.397 | V68: 62.854 | W68: 63.326 | X68: 63.809 | Y68: 64.271 | Z68: 64.659 | AA68: 65.202 | AB68: 65.625 | AC68: 66.123 | AD68: 66.587 | AE68: 67.038 | AF68: 67.817 | AG68: 68.445 | AH68: 69.04 | AI68: 69.468 | AJ68: 70.07 | AK68: 70.876 | AL68: 71.349 | AM68: 71.82 | AN68: 72.007 | AO68: 71.949 | AP68: 71.92 | AQ68: 72.09 | AR68: 72.571 | AS68: 73.164 | AT68: 73.632 | AU68: 73.868 | AV68: 73.909 | AW68: 74.01 | AX68: 74.226 | AY68: 74.709 | AZ68: 74.901 | BA68: 75.188 | BB68: 75.179 | BC68: 75.486 | BD68: 75.832 | BE68: 76.141 | BF68: 76.222 | BG68: 76.094 | BH68: 76.22 | BI68: 77.248 | BJ68: 77.286 | BK68: 72.004 | BL68: 72.746 | BM68: 76.577 | BN68: 77.392 | BO68: 77.579 | BP68: Latin America & Caribbean | BQ68: Upper middle income
A69: Egypt, Arab Rep. | B69: EGY | C69: 44.436 | D69: 45.146 | E69: 45.844 | F69: 46.493 | G69: 47.075 | H69: 47.577 | I69: 47.988 | J69: 48.13 | K69: 48.602 | L69: 48.7 | M69: 49 | N69: 49.48 | O69: 49.908 | P69: 50.098 | Q69: 51.044 | R69: 51.734 | S69: 52.484 | T69: 53.272 | U69: 54.075 | V69: 54.876 | W69: 55.673 | X69: 56.454 | Y69: 57.219 | Z69: 57.967 | AA69: 58.697 | AB69: 59.405 | AC69: 60.085 | AD69: 60.736 | AE69: 61.358 | AF69: 61.949 | AG69: 62.513 | AH69: 63.059 | AI69: 63.585 | AJ69: 64.147 | AK69: 64.663 | AL69: 65.214 | AM69: 65.733 | AN69: 66.207 | AO69: 66.635 | AP69: 67.01 | AQ69: 67.332 | AR69: 67.612 | AS69: 67.846 | AT69: 68.045 | AU69: 68.211 | AV69: 68.355 | AW69: 68.493 | AX69: 68.627 | AY69: 68.761 | AZ69: 68.915 | BA69: 69.078 | BB69: 69.232 | BC69: 69.464 | BD69: 69.632 | BE69: 69.911 | BF69: 70.135 | BG69: 70.437 | BH69: 70.709 | BI69: 70.974 | BJ69: 71.213 | BK69: 69.79 | BL69: 68.976 | BM69: 71.01 | BN69: 71.633 | BO69: 71.806 | BP69: Middle East & North Africa | BQ69: Lower middle income
A70: Euro area | B70: EMU | C70: 69.264384 | D70: 69.661111 | E70: 69.636744 | F70: 69.797272 | G70: 70.345967 | H70: 70.429299 | I70: 70.680428 | J70: 70.862232 | K70: 70.771968 | L70: 70.688712 | M70: 71.107633 | N70: 71.258399 | O70: 71.610146 | P70: 71.7218 | Q70: 72.059143 | R70: 72.128255 | S70: 72.455601 | T70: 72.892328 | U70: 73.04526 | V70: 73.384296 | W70: 73.53246 | X70: 73.807725 | Y70: 74.151622 | Z70: 74.222519 | AA70: 74.619749 | AB70: 74.75932 | AC70: 75.053121 | AD70: 75.365742 | AE70: 75.557678 | AF70: 75.743108 | AG70: 75.817671 | AH70: 75.96768 | AI70: 76.307721 | AJ70: 76.413209 | AK70: 76.724179 | AL70: 76.882313 | AM70: 77.148324 | AN70: 77.508868 | AO70: 77.718907 | AP70: 77.945636 | AQ70: 78.199779 | AR70: 78.543543 | AS70: 78.634135 | AT70: 78.655762 | AU70: 79.232162 | AV70: 79.374851 | AW70: 79.807721 | AX70: 80.047779 | AY70: 80.251088 | AZ70: 80.455461 | BA70: 80.698943 | BB70: 81.182634 | BC70: 81.182732 | BD70: 81.467984 | BE70: 81.893061 | BF70: 81.51927 | BG70: 81.907455 | BH70: 81.883804 | BI70: 82.00276 | BJ70: 82.280421 | BK70: 81.487357 | BL70: 81.583933 | BM70: 81.622972 | BN70: 82.255521 | BO70: 82.365842
A71: Eritrea | B71: ERI | C71: 37.443 | D71: 37.912 | E71: 38.346 | F71: 38.833 | G71: 39.184 | H71: 39.576 | I71: 37.634 | J71: 40.151 | K71: 40.483 | L71: 40.792 | M71: 41.162 | N71: 41.527 | O71: 40.723 | P71: 41.131 | Q71: 39.001 | R71: 39.031 | S71: 42.587 | T71: 42.984 | U71: 43.38 | V71: 43.78 | W71: 44.625 | X71: 44.974 | Y71: 44.891 | Z71: 37.173 | AA71: 37.679 | AB71: 38.586 | AC71: 39.541 | AD71: 47.363 | AE71: 48.094 | AF71: 47.802 | AG71: 49.733 | AH71: 50.516 | AI71: 52.436 | AJ71: 53.189 | AK71: 54.027 | AL71: 54.822 | AM71: 55.498 | AN71: 56.155 | AO71: 49.997 | AP71: 44.506 | AQ71: 56.285 | AR71: 58.359 | AS71: 58.941 | AT71: 59.455 | AU71: 60.063 | AV71: 60.628 | AW71: 61.457 | AX71: 61.998 | AY71: 62.422 | AZ71: 63.203 | BA71: 63.665 | BB71: 64.231 | BC71: 64.697 | BD71: 65.005 | BE71: 65.517 | BF71: 65.909 | BG71: 66.242 | BH71: 66.612 | BI71: 66.979 | BJ71: 67.306 | BK71: 66.98 | BL71: 66.94 | BM71: 67.789 | BN71: 68.624 | BO71: 68.893 | BP71: Sub-Saharan Africa | BQ71: Low income
A72: Spain | B72: ESP | C72: 69.109268 | D72: 69.480488 | E72: 69.519024 | F72: 69.68122 | G72: 70.399756 | H72: 70.809268 | I72: 71.055122 | J72: 71.252927 | K72: 71.537805 | L72: 71.057561 | M72: 72.027317 | N72: 71.630244 | O72: 72.818049 | P72: 72.610732 | Q72: 72.969756 | R72: 73.31878 | S72: 73.642683 | T72: 74.131951 | U72: 74.29561 | V72: 74.81878 | W72: 75.349268 | X72: 75.528537 | Y72: 76.134146 | Z72: 75.909024 | AA72: 76.295366 | AB72: 76.259512 | AC72: 76.510488 | AD72: 76.728049 | AE72: 76.747073 | AF72: 76.813659 | AG72: 76.837561 | AH72: 76.97122 | AI72: 77.41 | AJ72: 77.546585 | AK72: 77.901463 | AL72: 77.980732 | AM72: 78.120488 | AN72: 78.604146 | AO72: 78.665854 | AP72: 78.717073 | AQ72: 78.965854 | AR72: 79.368293 | AS72: 79.568293 | AT72: 79.619512 | AU72: 79.870732 | AV72: 80.170732 | AW72: 80.821951 | AX72: 80.873171 | AY72: 81.17561 | AZ72: 81.47561 | BA72: 81.626829 | BB72: 82.47561 | BC72: 82.426829 | BD72: 83.078049 | BE72: 83.229268 | BF72: 82.831707 | BG72: 83.329268 | BH72: 83.282927 | BI72: 83.431707 | BJ72: 83.831707 | BK72: 82.231707 | BL72: 83.178049 | BM72: 83.134146 | BN72: 83.934146 | BO72: 83.887805 | BP72: Europe & Central Asia | BQ72: High income
A73: Estonia | B73: EST | C73: 68.749268 | D73: 69.077878 | E73: 69.292024 | F73: 69.321561 | G73: 70.072098 | H73: 70.176585 | I73: 70.146463 | J73: 70.432415 | K73: 70.08078 | L73: 69.789463 | M73: 69.92422 | N73: 70.122561 | O73: 69.929195 | P73: 70.230024 | Q73: 70.346195 | R73: 69.708122 | S73: 69.345073 | T73: 69.448951 | U73: 69.297268 | V73: 69.054317 | W73: 69.11478 | X73: 68.978049 | Y73: 69.126829 | Z73: 69.37561 | AA73: 69.278049 | AB73: 69.380488 | AC73: 70.085366 | AD73: 70.643902 | AE73: 70.697561 | AF73: 70.039024 | AG73: 69.47561 | AH73: 69.373171 | AI73: 68.863415 | AJ73: 67.909756 | AK73: 66.5 | AL73: 67.543902 | AM73: 69.612195 | AN73: 69.809756 | AO73: 69.358537 | AP73: 70.063415 | AQ73: 70.417073 | AR73: 70.258537 | AS73: 70.904878 | AT73: 71.317073 | AU73: 71.909756 | AV73: 72.568293 | AW73: 72.691463 | AX73: 72.814634 | AY73: 73.770732 | AZ73: 74.82439 | BA73: 75.429268 | BB73: 76.229268 | BC73: 76.326829 | BD73: 77.141463 | BE73: 77.034146 | BF73: 77.590244 | BG73: 77.641463 | BH73: 78.092683 | BI73: 78.243902 | BJ73: 78.646341 | BK73: 78.595122 | BL73: 76.943902 | BM73: 77.843902 | BN73: 78.792683 | BO73: 79.295122 | BP73: Europe & Central Asia | BQ73: High income
A74: Ethiopia | B74: ETH | C74: 39.615 | D74: 40.198 | E74: 40.531 | F74: 40.967 | G74: 41.261 | H74: 41.413 | I74: 39.343 | J74: 41.941 | K74: 42.092 | L74: 42.131 | M74: 42.115 | N74: 42.216 | O74: 41.035 | P74: 41.103 | Q74: 39.083 | R74: 38.941 | S74: 41.32 | T74: 41.397 | U74: 41.506 | V74: 42.376 | W74: 42.815 | X74: 43.084 | Y74: 43.434 | Z74: 36.319 | AA74: 36.737 | AB74: 37.747 | AC74: 38.371 | AD74: 45.892 | AE74: 45.682 | AF74: 45.644 | AG74: 45.117 | AH74: 46.657 | AI74: 47.279 | AJ74: 47.676 | AK74: 47.926 | AL74: 48.156 | AM74: 48.697 | AN74: 49.21 | AO74: 49.785 | AP74: 49.486 | AQ74: 50.88 | AR74: 51.428 | AS74: 52.085 | AT74: 52.877 | AU74: 53.735 | AV74: 54.364 | AW74: 55.402 | AX74: 56.566 | AY74: 57.733 | AZ74: 58.715 | BA74: 59.709 | BB74: 60.595 | BC74: 61.443 | BD74: 62.161 | BE74: 62.927 | BF74: 63.592 | BG74: 64.162 | BH74: 64.766 | BI74: 65.257 | BJ74: 65.741 | BK74: 65.969 | BL74: 65.33 | BM74: 66.897 | BN74: 67.315 | BO74: 67.603 | BP74: Sub-Saharan Africa
A75: European Union | B75: EUU | C75: 69.067102 | D75: 69.43927 | E75: 69.290908 | F75: 69.648988 | G75: 70.164734 | H75: 70.27719 | I75: 70.591456 | J75: 70.597697 | K75: 70.599292 | L75: 70.424597 | M75: 70.823861 | N75: 70.964843 | O75: 71.348957 | P75: 71.468887 | Q75: 71.782884 | R75: 71.801551 | S75: 72.072651 | T75: 72.395741 | U75: 72.487468 | V75: 72.768603 | W75: 72.792183 | X75: 73.126205 | Y75: 73.406085 | Z75: 73.451232 | AA75: 73.743295 | AB75: 73.819847 | AC75: 74.07671 | AD75: 74.323693 | AE75: 74.530884 | AF75: 74.65997 | AG75: 74.70254 | AH75: 74.81562 | AI75: 75.132047 | AJ75: 75.258692 | AK75: 75.529314 | AL75: 75.674163 | AM75: 75.926812 | AN75: 76.244549 | AO75: 76.513329 | AP75: 76.747962 | AQ75: 77.078245 | AR75: 77.425639 | AS75: 77.534075 | AT75: 77.592375 | AU75: 78.117828 | AV75: 78.275141 | AW75: 78.672128 | AX75: 78.906045 | AY75: 79.129628 | AZ75: 79.362439 | BA75: 79.635431 | BB75: 80.143951 | BC75: 80.165777 | BD75: 80.473432 | BE75: 80.876017 | BF75: 80.570797 | BG75: 80.952979 | BH75: 80.930151 | BI75: 81.031751 | BJ75: 81.319452 | BK75: 80.441475 | BL75: 80.307196 | BM75: 80.713326 | BN75: 81.424933 | BO75: 81.560847
A76: Fragile and conflict affected situations | B76: FCS | C76: 46.115194 | D76: 46.506375 | E76: 46.998952 | F76: 47.30914 | G76: 47.676531 | H76: 47.959064 | I76: 48.083322 | J76: 48.390548 | K76: 48.80616 | L76: 49.03949 | M76: 49.471889 | N76: 49.839487 | O76: 49.865982 | P76: 50.268142 | Q76: 50.364246 | R76: 50.512358 | S76: 50.98022 | T76: 51.458301 | U76: 51.541 | V76: 51.815627 | W76: 52.061528 | X76: 52.164101 | Y76: 52.108251 | Z76: 51.577942 | AA76: 51.496371 | AB76: 51.744776 | AC76: 52.300324 | AD76: 53.085509 | AE76: 52.994102 | AF76: 53.374175 | AG76: 53.399368 | AH76: 53.370979 | AI76: 53.549556 | AJ76: 53.981631 | AK76: 54.232635 | AL76: 54.225679 | AM76: 54.237154 | AN76: 54.517824 | AO76: 54.470722 | AP76: 54.903404 | AQ76: 55.488425 | AR76: 55.721269 | AS76: 56.150857 | AT76: 56.446925 | AU76: 56.755745 | AV76: 57.147278 | AW76: 57.594311 | AX76: 58.109575 | AY76: 58.187178 | AZ76: 58.937961 | BA76: 59.343161 | BB76: 59.627636 | BC76: 60.10084 | BD76: 60.454839 | BE76: 60.553692 | BF76: 60.744993 | BG76: 60.986184 | BH76: 61.229683 | BI76: 61.782508 | BJ76: 62.137955 | BK76: 62.066368 | BL76: 61.608681 | BM76: 62.702272 | BN76: 63.349945 | BO76: 63.604841
A77: Finland | B77: FIN | C77: 68.819756 | D77: 68.844146 | E77: 68.577805 | F77: 69.012683 | G77: 69.220976 | H77: 68.977805 | I77: 69.477073 | J77: 69.666585 | K77: 69.616341 | L77: 69.503415 | M77: 70.179512 | N77: 70.017561 | O77: 70.707317 | P77: 71.223659 | Q77: 71.134878 | R77: 71.673659 | S77: 71.812927 | T77: 72.350244 | U77: 72.897073 | V77: 73.155366 | W77: 73.44 | X77: 73.746585 | Y77: 74.298049 | Z77: 74.200976 | AA77: 74.519024 | AB77: 74.222927 | AC77: 74.56 | AD77: 74.591951 | AE77: 74.577073 | AF77: 74.792195 | AG77: 74.813171 | AH77: 75.227561 | AI77: 75.455366 | AJ77: 75.705122 | AK77: 76.39561 | AL77: 76.409512 | AM77: 76.693415 | AN77: 76.878537 | AO77: 77.090732 | AP77: 77.29122 | AQ77: 77.465854 | AR77: 77.965854 | AS77: 78.119512 | AT77: 78.368293 | AU77: 78.714634 | AV77: 78.817073 | AW77: 79.214634 | AX77: 79.263415 | AY77: 79.568293 | AZ77: 79.719512 | BA77: 79.870732 | BB77: 80.470732 | BC77: 80.626829 | BD77: 80.97561 | BE77: 81.180488 | BF77: 81.480488 | BG77: 81.429268 | BH77: 81.631707 | BI77: 81.734146 | BJ77: 81.982927 | BK77: 81.931707 | BL77: 81.885366 | BM77: 81.187805 | BN77: 81.585366 | BO77: 82.336585 | BP77: Europe & Central Asia | BQ77: High income
A78: Fiji | B78: FJI | C78: 58.602 | D78: 59.102 | E78: 59.654 | F78: 60.155 | G78: 60.714 | H78: 61.413 | I78: 61.565 | J78: 61.442 | K78: 61.719 | L78: 61.397 | M78: 61.652 | N78: 61.74 | O78: 61.63 | P78: 60.649 | Q78: 61.194 | R78: 61.689 | S78: 62.1 | T78: 62.691 | U78: 63.065 | V78: 62.305 | W78: 62.406 | X78: 62.255 | Y78: 62.195 | Z78: 62.916 | AA78: 63.238 | AB78: 63.998 | AC78: 63.961 | AD78: 64.278 | AE78: 64.951 | AF78: 65.386 | AG78: 65.056 | AH78: 65.457 | AI78: 65.407 | AJ78: 65.51 | AK78: 65.796 | AL78: 66.007 | AM78: 66.202 | AN78: 66.293 | AO78: 66.536 | AP78: 66.728 | AQ78: 66.194 | AR78: 66.205 | AS78: 65.492 | AT78: 65.653 | AU78: 65.841 | AV78: 65.983 | AW78: 66.126 | AX78: 66.161 | AY78: 66.32 | AZ78: 66.347 | BA78: 66.778 | BB78: 66.88 | BC78: 65.812 | BD78: 66.545 | BE78: 66.581 | BF78: 66.48 | BG78: 66.657 | BH78: 67.06 | BI78: 66.965 | BJ78: 67.009 | BK78: 66.924 | BL78: 64.904 | BM78: 67.148 | BN78: 67.316 | BO78: 67.463 | BP78: East Asia & Pacific | BQ78: Upper middle income
A79: France | B79: FRA | C79: 69.868293 | D79: 70.117073 | E79: 70.314634 | F79: 70.514634 | G79: 70.663415 | H79: 70.812195 | I79: 70.960976 | J79: 71.160976 | K79: 71.309756 | L79: 71.458537 | M79: 71.658537 | N79: 71.907317 | O79: 72.107317 | P79: 72.356098 | Q79: 72.604878 | R79: 72.853659 | S79: 73.102439 | T79: 73.35122 | U79: 73.602439 | V79: 73.85122 | W79: 74.05122 | X79: 74.3 | Y79: 74.5 | Z79: 74.8 | AA79: 75 | AB79: 75.3 | AC79: 75.6 | AD79: 75.8 | AE79: 76.1 | AF79: 76.34878 | AG79: 76.6 | AH79: 76.84878 | AI79: 77.1 | AJ79: 77.3 | AK79: 77.64878 | AL79: 77.75122 | AM79: 77.953659 | AN79: 78.304878 | AO79: 78.604878 | AP79: 78.756098 | AQ79: 79.056098 | AR79: 79.158537 | AS79: 79.260976 | AT79: 79.114634 | AU79: 80.163415 | AV79: 80.163415 | AW79: 80.812195 | AX79: 81.112195 | AY79: 81.214634 | AZ79: 81.414634 | BA79: 81.663415 | BB79: 82.114634 | BC79: 81.968293 | BD79: 82.219512 | BE79: 82.719512 | BF79: 82.321951 | BG79: 82.573171 | BH79: 82.57561 | BI79: 82.67561 | BJ79: 82.826829 | BK79: 82.17561 | BL79: 82.32439 | BM79: 82.129268 | BN79: 82.831707 | BO79: 82.980488 | BP79: Europe & Central Asia | BQ79: High income
A80: Faroe Islands | B80: FRO | C80: 72.107927 | D80: 72.712122 | E80: 73.17578 | F80: 73.553902 | G80: 73.855927 | H80: 74.106463 | I80: 74.316195 | J80: 74.49961 | K80: 74.696171 | L80: 74.842927 | M80: 74.97661 | N80: 75.117171 | O80: 75.214415 | P80: 75.327244 | Q80: 75.367561 | R80: 75.444341 | S80: 75.512341 | T80: 75.633512 | U80: 75.720024 | V80: 75.76278 | W80: 75.848439 | X80: 75.936854 | Y80: 76.002317 | Z80: 76.057805 | AA80: 76.120341 | AB80: 76.198171 | AC80: 75.163902 | AD80: 75.402768 | AE80: 75.642229 | AF80: 75.881076 | AG80: 76.118802 | AH80: 76.355573 | AI80: 76.591822 | AJ80: 76.828698 | AK80: 77.069454 | AL80: 77.322824 | AM80: 77.561963 | AN80: 77.785441 | AO80: 77.997995 | AP80: 78.208773 | AQ80: 78.411907 | AR80: 78.601729 | AS80: 78.787659 | AT80: 78.984807 | AU80: 79.20498 | AV80: 79.445346 | AW80: 79.689861 | AX80: 79.923824 | AY80: 80.14608 | AZ80: 80.369532 | BA80: 80.604956 | BB80: 80.85181 | BC80: 81.106095 | BD80: 81.356644 | BE80: 81.591205 | BF80: 81.799598 | BG80: 81.962112 | BH80: 82.106293 | BI80: 82.248602 | BJ80: 82.391283 | BK80: 82.534193 | BL80: 82.676322 | BM80: 82.816229 | BN80: 82.95212 | BO80: 83.083246 | BP80: Europe & Central Asia | BQ80: High income
A81: Micronesia, Fed. Sts. | B81: FSM | C81: 54.195 | D81: 54.736 | E81: 55.393 | F81: 56.004 | G81: 56.655 | H81: 57.199 | I81: 57.75 | J81: 58.305 | K81: 58.827 | L81: 59.309 | M81: 59.774 | N81: 60.182 | O81: 60.608 | P81: 60.955 | Q81: 61.319 | R81: 61.617 | S81: 61.885 | T81: 62.118 | U81: 62.306 | V81: 62.46 | W81: 62.556 | X81: 62.668 | Y81: 62.747 | Z81: 62.829 | AA81: 62.923 | AB81: 63.028 | AC81: 63.151 | AD81: 63.206 | AE81: 63.461 | AF81: 63.617 | AG81: 63.722 | AH81: 63.881 | AI81: 63.996 | AJ81: 64.041 | AK81: 64.082 | AL81: 64.142 | AM81: 64.253 | AN81: 64.371 | AO81: 64.509 | AP81: 64.626 | AQ81: 64.317 | AR81: 64.801 | AS81: 63.907 | AT81: 64.915 | AU81: 64.898 | AV81: 64.906 | AW81: 64.859 | AX81: 64.844 | AY81: 64.849 | AZ81: 64.865 | BA81: 64.892 | BB81: 64.969 | BC81: 65.08 | BD81: 65.179 | BE81: 65.294 | BF81: 65.306 | BG81: 65.576 | BH81: 65.761 | BI81: 65.943 | BJ81: 66.196 | BK81: 65.878 | BL81: 66.152 | BM81: 66.961 | BN81: 67.198 | BO81: 67.357 | BP81: East Asia & Pacific | BQ81: Lower middle income
A82: Gabon | B82: GAB | C82: 46.443 | D82: 47.115 | E82: 47.777 | F82: 48.425 | G82: 48.994 | H82: 49.71 | I82: 50.322 | J82: 50.928 | K82: 51.545 | L82: 52.127 | M82: 52.697 | N82: 53.259 | O82: 53.811 | P82: 54.352 | Q82: 54.911 | R82: 55.455 | S82: 55.97 | T82: 56.467 | U82: 56.954 | V82: 57.438 | W82: 57.893 | X82: 58.332 | Y82: 58.644 | Z82: 58.994 | AA82: 59.34 | AB82: 59.665 | AC82: 59.956 | AD82: 60.2 | AE82: 60.398 | AF82: 60.584 | AG82: 60.736 | AH82: 60.891 | AI82: 61.013 | AJ82: 61.125 | AK82: 61.183 | AL82: 61.27 | AM82: 61.265 | AN82: 61.395 | AO82: 61.506 | AP82: 61.658 | AQ82: 61.81 | AR82: 61.982 | AS82: 62.175 | AT82: 62.463 | AU82: 62.694 | AV82: 62.978 | AW82: 63.259 | AX82: 63.619 | AY82: 64.011 | AZ82: 64.361 | BA82: 64.715 | BB82: 65.102 | BC82: 65.438 | BD82: 65.751 | BE82: 66.07 | BF82: 66.336 | BG82: 66.583 | BH82: 66.816 | BI82: 67.043 | BJ82: 67.337 | BK82: 67.073 | BL82: 67.072 | BM82: 67.713 | BN82: 68.337 | BO82: 68.511 | BP82: Sub-Saharan Africa | BQ82: Upper middle income
A83: United Kingdom | B83: GBR | C83: 71.126829 | D83: 70.878049 | E83: 70.926829 | F83: 70.826829 | G83: 71.62439 | H83: 71.62439 | I83: 71.573171 | J83: 72.12439 | K83: 71.72439 | L83: 71.721951 | M83: 71.973171 | N83: 72.273171 | O83: 72.12439 | P83: 72.32439 | Q83: 72.52439 | R83: 72.72439 | S83: 72.77561 | T83: 73.22439 | U83: 73.17561 | V83: 73.27561 | W83: 73.67561 | X83: 74.026829 | Y83: 74.178049 | Z83: 74.378049 | AA83: 74.778049 | AB83: 74.629268 | AC83: 74.929268 | AD83: 75.280488 | AE83: 75.380488 | AF83: 75.582927 | AG83: 75.880488 | AH83: 76.082927 | AI83: 76.434146 | AJ83: 76.385366 | AK83: 76.885366 | AL83: 76.836585 | AM83: 77.087805 | AN83: 77.210976 | AO83: 77.190244 | AP83: 77.390244 | AQ83: 77.741463 | AR83: 77.992683 | AS83: 78.143902 | AT83: 78.446341 | AU83: 78.746341 | AV83: 79.04878 | AW83: 79.24878 | AX83: 79.44878 | AY83: 79.6 | AZ83: 80.05122 | BA83: 80.402439 | BB83: 80.95122 | BC83: 80.904878 | BD83: 81.004878 | BE83: 81.304878 | BF83: 80.956098 | BG83: 81.156098 | BH83: 81.256098 | BI83: 81.256098 | BJ83: 81.369122 | BK83: 80.331756 | BL83: 80.647317 | BM83: 81.01122 | BN83: 81.238098 | BO83: 81.386854 | BP83: Europe & Central Asia | BQ83: High income
A84: Georgia | B84: GEO | C84: 61.347 | D84: 61.72 | E84: 62.078 | F84: 62.457 | G84: 62.818 | H84: 63.097 | I84: 63.397 | J84: 63.772 | K84: 64.139 | L84: 64.509 | M84: 64.869 | N84: 65.189 | O84: 65.516 | P84: 65.851 | Q84: 66.18 | R84: 66.512 | S84: 66.894 | T84: 67.246 | U84: 67.597 | V84: 67.942 | W84: 68.273 | X84: 68.741 | Y84: 69.109 | Z84: 69.135 | AA84: 68.795 | AB84: 69.006 | AC84: 69.225 | AD84: 69.219 | AE84: 68.825 | AF84: 68.635 | AG84: 68.679 | AH84: 68.202 | AI84: 67.78 | AJ84: 67.405 | AK84: 68.669 | AL84: 69.398 | AM84: 70.637 | AN84: 69.683 | AO84: 69.787 | AP84: 70.012 | AQ84: 70.091 | AR84: 70.371 | AS84: 70.438 | AT84: 71.377 | AU84: 71.011 | AV84: 70.689 | AW84: 70.983 | AX84: 70.985 | AY84: 70.949 | AZ84: 71.058 | BA84: 71.732 | BB84: 72.485 | BC84: 72.672 | BD84: 73.025 | BE84: 73.105 | BF84: 73.241 | BG84: 73.136 | BH84: 73.435 | BI84: 73.985 | BJ84: 74.165 | BK84: 73.509 | BL84: 71.635 | BM84: 74.141 | BN84: 74.496 | BO84: 74.657 | BP84: Europe & Central Asia | BQ84: Upper middle income
A85: Ghana | B85: GHA | C85: 46.942 | D85: 47.127 | E85: 47.335 | F85: 47.476 | G85: 47.637 | H85: 47.689 | I85: 47.708 | J85: 47.734 | K85: 47.758 | L85: 47.895 | M85: 47.888 | N85: 47.949 | O85: 48.274 | P85: 48.577 | Q85: 48.918 | R85: 49.323 | S85: 49.732 | T85: 50.079 | U85: 50.461 | V85: 50.787 | W85: 51.059 | X85: 51.313 | Y85: 51.425 | Z85: 51.78 | AA85: 52.232 | AB85: 52.732 | AC85: 53.276 | AD85: 53.818 | AE85: 54.396 | AF85: 54.936 | AG85: 55.395 | AH85: 55.722 | AI85: 56.055 | AJ85: 56.286 | AK85: 56.234 | AL85: 56.662 | AM85: 56.957 | AN85: 57.241 | AO85: 57.525 | AP85: 57.835 | AQ85: 58.139 | AR85: 58.403 | AS85: 58.709 | AT85: 59.014 | AU85: 59.316 | AV85: 59.638 | AW85: 59.975 | AX85: 60.282 | AY85: 60.578 | AZ85: 60.928 | BA85: 61.297 | BB85: 61.617 | BC85: 61.995 | BD85: 62.397 | BE85: 62.832 | BF85: 63.175 | BG85: 63.522 | BH85: 63.829 | BI85: 64.138 | BJ85: 64.455 | BK85: 64.309 | BL85: 64.286 | BM85: 65.246 | BN85: 65.498 | BO85: 65.695 | BP85: Sub-Saharan Africa | BQ85: Lower middle income
A86: Gibraltar | B86: GIB | C86: 70.209 | D86: 70.165 | E86: 70.174 | F86: 70.249 | G86: 70.438 | H86: 70.755 | I86: 71.178 | J86: 71.54 | K86: 71.709 | L86: 71.812 | M86: 71.888 | N86: 72.103 | O86: 72.356 | P86: 72.707 | Q86: 73.053 | R86: 73.322 | S86: 73.443 | T86: 73.479 | U86: 73.512 | V86: 73.585 | W86: 73.755 | X86: 73.999 | Y86: 74.325 | Z86: 74.613 | AA86: 74.935 | AB86: 75.232 | AC86: 75.557 | AD86: 75.871 | AE86: 76.18 | AF86: 76.474 | AG86: 76.814 | AH86: 77.118 | AI86: 77.412 | AJ86: 77.722 | AK86: 78.052 | AL86: 78.345 | AM86: 78.696 | AN86: 79.097 | AO86: 79.477 | AP86: 79.812 | AQ86: 80.145 | AR86: 80.419 | AS86: 80.59 | AT86: 80.713 | AU86: 80.856 | AV86: 80.991 | AW86: 81.103 | AX86: 81.269 | AY86: 81.541 | AZ86: 81.807 | BA86: 82.08 | BB86: 82.333 | BC86: 82.527 | BD86: 82.586 | BE86: 82.644 | BF86: 82.668 | BG86: 82.741 | BH86: 82.858 | BI86: 83.028 | BJ86: 83.183 | BK86: 83.07 | BL86: 80.274 | BM86: 83.517 | BN86: 83.553 | BO86: 83.63 | BP86: Europe & Central Asia | BQ86: High income
A87: Guinea | B87: GIN | C87: 36.623 | D87: 36.816 | E87: 36.997 | F87: 37.196 | G87: 37.415 | H87: 37.653 | I87: 37.959 | J87: 38.224 | K87: 38.501 | L87: 38.824 | M87: 39.06 | N87: 39.372 | O87: 39.683 | P87: 39.937 | Q87: 40.229 | R87: 40.606 | S87: 41.028 | T87: 41.409 | U87: 41.882 | V87: 42.343 | W87: 42.842 | X87: 43.33 | Y87: 43.863 | Z87: 44.226 | AA87: 44.858 | AB87: 45.31 | AC87: 45.719 | AD87: 46.107 | AE87: 46.478 | AF87: 46.86 | AG87: 47.252 | AH87: 47.781 | AI87: 48.266 | AJ87: 48.819 | AK87: 49.188 | AL87: 49.836 | AM87: 50.546 | AN87: 51.113 | AO87: 51.61 | AP87: 51.987 | AQ87: 52.42 | AR87: 52.669 | AS87: 53.2 | AT87: 53.589 | AU87: 53.975 | AV87: 54.422 | AW87: 54.875 | AX87: 55.233 | AY87: 55.703 | AZ87: 56.052 | BA87: 56.431 | BB87: 56.778 | BC87: 57.117 | BD87: 57.459 | BE87: 57.581 | BF87: 57.899 | BG87: 58.49 | BH87: 58.715 | BI87: 59.043 | BJ87: 59.379 | BK87: 59.35 | BL87: 59.373 | BM87: 60.432 | BN87: 60.74 | BO87: 60.904 | BP87: Sub-Saharan Africa | BQ87: Lower middle income
A88: Gambia, The | B88: GMB | C88: 34.574 | D88: 35.063 | E88: 35.599 | F88: 36.086 | G88: 36.579 | H88: 37.12 | I88: 37.559 | J88: 38.063 | K88: 38.533 | L88: 39.004 | M88: 39.532 | N88: 40.048 | O88: 40.549 | P88: 41.088 | Q88: 41.676 | R88: 42.192 | S88: 42.876 | T88: 43.366 | U88: 43.573 | V88: 44.517 | W88: 44.977 | X88: 44.489 | Y88: 46.25 | Z88: 46.892 | AA88: 47.513 | AB88: 48.151 | AC88: 48.798 | AD88: 49.392 | AE88: 50.146 | AF88: 50.725 | AG88: 51.278 | AH88: 51.857 | AI88: 52.477 | AJ88: 53.15 | AK88: 53.768 | AL88: 54.292 | AM88: 54.849 | AN88: 55.225 | AO88: 56.007 | AP88: 56.466 | AQ88: 56.899 | AR88: 57.283 | AS88: 57.736 | AT88: 58.223 | AU88: 58.749 | AV88: 59.11 | AW88: 59.667 | AX88: 60.001 | AY88: 60.473 | AZ88: 60.735 | BA88: 61.167 | BB88: 61.561 | BC88: 61.9 | BD88: 62.252 | BE88: 62.576 | BF88: 62.971 | BG88: 63.386 | BH88: 63.708 | BI88: 64.034 | BJ88: 64.427 | BK88: 64.418 | BL88: 63.847 | BM88: 64.859 | BN88: 65.86 | BO88: 66.057 | BP88: Sub-Saharan Africa | BQ88: Low income
... A96: Guyana | B96: GUY | C96: 57.51 | D96: 57.912 | E96: 58.303 | F96: 58.644 | G96: 58.958 | H96: 59.137 | I96: 59.329 | J96: 59.53 | K96: 59.69 | L96: 59.835 | M96: 59.961 | N96: 60.068 | O96: 60.133 | P96: 60.211 | Q96: 60.305 | R96: 60.375 | S96: 60.449 | T96: 60.558 | U96: 60.646 | V96: 60.735 | W96: 60.808 | X96: 60.91 | Y96: 61.01 | Z96: 61.157 | AA96: 61.255 | AB96: 61.379 | AC96: 61.521 | AD96: 61.698 | AE96: 61.849 | AF96: 62.054 | AG96: 62.254 | AH96: 62.463 | AI96: 62.816 | AJ96: 63.016 | AK96: 63.007 | AL96: 62.668 | AM96: 62.691 | AN96: 62.879 | AO96: 63.429 | AP96: 63.772 | AQ96: 64.075 | AR96: 64.38 | AS96: 64.183 | AT96: 64.117 | AU96: 64.214 | AV96: 64.392 | AW96: 64.848 | AX96: 65.462 | AY96: 65.721 | AZ96: 66.03 | BA96: 66.204 | BB96: 66.469 | BC96: 66.443 | BD96: 66.71 | BE96: 67.334 | BF96: 67.719 | BG96: 68.069 | BH96: 68.543 | BI96: 68.829 | BJ96: 69.067 | BK96: 67.751 | BL96: 64.323 | BM96: 69.888 | BN96: 70.18 | BO96: 70.319 | BP96: Latin America & Caribbean | BQ96: High income
A97: High income | B97: HIC | C97: 68.336473 | D97: 68.70926 | E97: 68.663908 | F97: 68.945032 | G97: 69.385162 | H97: 69.448312 | I97: 69.653209 | J97: 69.972922 | K97: 69.836495 | L97: 69.897467 | M97: 70.202545 | N97: 70.504525 | O97: 70.710901 | P97: 70.863948 | Q97: 71.200916 | R97: 71.392551 | S97: 71.610441 | T97: 71.927976 | U97: 72.059928 | V97: 72.325521 | W97: 72.341234 | X97: 72.687391 | Y97: 73.032088 | Z97: 73.107774 | AA97: 73.296953 | AB97: 73.466652 | AC97: 73.872248 | AD97: 74.108695 | AE97: 74.213601 | AF97: 74.377915 | AG97: 74.473873 | AH97: 74.582387 | AI97: 74.609195 | AJ97: 74.438243 | AK97: 74.630026 | AL97: 74.718827 | AM97: 75.182959 | AN97: 75.571683 | AO97: 75.798357 | AP97: 75.819199 | AQ97: 76.041757 | AR97: 76.314714 | AS97: 76.439404 | AT97: 76.548318 | AU97: 76.989927 | AV97: 77.109684 | AW97: 77.542288 | AX97: 77.863114 | AY97: 78.05284 | AZ97: 78.40498 | BA97: 78.595666 | BB97: 78.921125 | BC97: 79.075341 | BD97: 79.312702 | BE97: 79.565353 | BF97: 79.524319 | BG97: 79.724312 | BH97: 79.853625 | BI97: 79.966639 | BJ97: 80.199264 | BK97: 79.204145 | BL97: 78.798163 | BM97: 79.426777 | BN97: 80.149626 | BO97: 80.394368
A98: Hong Kong SAR, China | B98: HKG | C98: 65.697122 | D98: 66.441659 | E98: 66.910463 | F98: 67.645171 | G98: 68.219098 | H98: 68.866805 | I98: 69.265854 | J98: 69.827854 | K98: 70.217024 | L98: 70.627171 | M98: 70.934683 | N98: 71.468049 | O98: 71.450976 | P98: 72.090244 | Q98: 72.597805 | R98: 73.362195 | S98: 72.789024 | T98: 73.349268 | U98: 73.540732 | V98: 73.663171 | W98: 74.653415 | X98: 75.349024 | Y98: 75.438537 | Z98: 75.286341 | AA98: 76.009512 | AB98: 76.429268 | AC98: 76.68439 | AD98: 76.897805 | AE98: 77.083415 | AF98: 77.02878 | AG98: 77.370732 | AH98: 77.872927 | AI98: 77.673415 | AJ98: 78.016098 | AK98: 78.543659 | AL98: 78.67878 | AM98: 79.627561 | AN98: 80.112195 | AO98: 80.106829 | AP98: 80.372683 | AQ98: 80.873171 | AR98: 81.419268 | AS98: 81.452195 | AT98: 81.343415 | AU98: 81.799268 | AV98: 81.609024 | AW98: 82.384878 | AX98: 82.366829 | AY98: 82.340488 | AZ98: 82.775122 | BA98: 82.957561 | BB98: 83.411951 | BC98: 83.450244 | BD98: 83.83122 | BE98: 83.93561 | BF98: 84.252683 | BG98: 84.211463 | BH98: 84.69561 | BI98: 84.869756 | BJ98: 85.155854 | BK98: 85.496341 | BL98: 85.532683 | BM98: 83.660976 | BN98: 85.247317 | BO98: 85.392683 | BP98: East Asia & Pacific | BQ98: High income
A99: Honduras | B99: HND | C99: 47.149 | D99: 47.71 | E99: 48.647 | F99: 49.385 | G99: 50.197 | H99: 50.863 | I99: 51.588 | J99: 52.331 | K99: 53.041 | L99: 53.712 | M99: 54.36 | N99: 55.012 | O99: 55.689 | P99: 54.565 | Q99: 52.519 | R99: 57.523 | S99: 58.151 | T99: 58.704 | U99: 59.248 | V99: 59.829 | W99: 60.388 | X99: 61.033 | Y99: 61.688 | Z99: 62.408 | AA99: 62.819 | AB99: 63.223 | AC99: 63.651 | AD99: 64.066 | AE99: 64.393 | AF99: 64.782 | AG99: 65.183 | AH99: 65.584 | AI99: 65.908 | AJ99: 66.074 | AK99: 66.523 | AL99: 66.919 | AM99: 67.263 | AN99: 67.542 | AO99: 62.432 | AP99: 68.005 | AQ99: 68.302 | AR99: 68.491 | AS99: 68.714 | AT99: 68.874 | AU99: 69.05 | AV99: 69.198 | AW99: 69.364 | AX99: 69.539 | AY99: 69.657 | AZ99: 69.823 | BA99: 69.77 | BB99: 70.116 | BC99: 70.46 | BD99: 70.765 | BE99: 71.032 | BF99: 71.323 | BG99: 71.615 | BH99: 71.805 | BI99: 72.001 | BJ99: 72.124 | BK99: 70.864 | BL99: 69.492 | BM99: 72.715 | BN99: 72.884 | BO99: 73.044 | BP99: Latin America & Caribbean | BQ99: Lower middle income
A100: Heavily indebted poor countries (HIPC) | B100: HPC | C100: 40.799038 | D100: 41.114819 | E100: 41.693417 | F100: 41.931846 | G100: 42.269363 | H100: 42.600484 | I100: 42.718011 | J100: 43.360105 | K100: 43.681765 | L100: 43.97317 | M100: 44.286788 | N100: 44.435617 | O100: 44.246888 | P100: 44.814675 | Q100: 44.892006 | R100: 45.263825 | S100: 45.907538 | T100: 46.268849 | U100: 46.424913 | V100: 46.774531 | W100: 47.196742 | X100: 47.445199 | Y100: 47.627193 | Z100: 46.614137 | AA100: 46.581022 | AB100: 46.990788 | AC100: 47.850986 | AD100: 49.091018 | AE100: 49.38401 | AF100: 49.631539 | AG100: 49.672867 | AH100: 49.639861 | AI100: 49.885745 | AJ100: 50.533608 | AK100: 50.316479 | AL100: 51.116777 | AM100: 51.26012 | AN100: 51.593342 | AO100: 51.685556 | AP100: 52.165512 | AQ100: 53.002777 | AR100: 53.535003 | AS100: 54.057895 | AT100: 54.607738 | AU100: 55.151439 | AV100: 55.777539 | AW100: 56.573949 | AX100: 57.246067 | AY100: 57.855688 | AZ100: 58.239341 | BA100: 58.732594 | BB100: 59.230201 | BC100: 60.085602 | BD100: 60.628343 | BE100: 61.040385 | BF100: 61.561898 | BG100: 62.003891 | BH100: 62.315299 | BI100: 62.798616 | BJ100: 63.089862 | BK100: 63.072806 | BL100: 62.531465 | BM100: 63.840466 | BN100: 64.715916 | BO100: 64.91806
A101: Croatia | B101: HRV | C101: 65.746488 | D101: 66.346146 | E101: 67.065268 | F101: 67.422146 | G101: 67.848878 | H101: 68.278195 | I101: 68.711829 | J101: 68.845024 | K101: 68.699073 | L101: 68.766293 | M101: 68.989122 | N101: 69.264171 | O101: 69.573927 | P101: 69.923902 | Q101: 70.433341 | R101: 70.001951 | S101: 70.455366 | T101: 70.74439 | U101: 70.53878 | V101: 70.427317 | W101: 70.175366 | X101: 70.34439 | Y101: 70.482683 | Z101: 70.274878 | AA101: 70.218537 | AB101: 70.886098 | AC101: 71.419024 | AD101: 71.470244 | AE101: 71.488293 | AF101: 71.844634 | AG101: 72.170488 | AH101: 72.185366 | AI101: 71.241463 | AJ101: 71.522439 | AK101: 71.803415 | AL101: 72.08439 | AM101: 72.365366 | AN101: 72.495122 | AO101: 72.317073 | AP101: 72.641951 | AQ101: 72.807805 | AR101: 74.512927 | AS101: 74.717317 | AT101: 74.613902 | AU101: 75.520244 | AV101: 75.244634 | AW101: 75.836829 | AX101: 75.70561 | AY101: 75.912195 | AZ101: 76.168293 | BA101: 76.47561 | BB101: 76.77561 | BC101: 77.168293 | BD101: 77.570732 | BE101: 77.72439 | BF101: 77.27561 | BG101: 77.921951 | BH101: 77.726829 | BI101: 77.919512 | BJ101: 78.22439 | BK101: 77.52439 | BL101: 76.42439 | BM101: 77.57561 | BN101: 78.473171 | BO101: 78.929268 | BP101: Europe & Central Asia | BQ101: High income
